Workbook

Sheet Coverage Dashboard
A1: PJM 2026/27 | 2025 Reported Heat-Rate Coverage
A3: FINAL 2025 EIA-923 and EIA-860 | Provisional EIA plant/group matches; NOT independently verified PJM unit measurements
A5: COVERAGE METRIC | B5: RESOURCE COUNT
A6: All PJM resource records | B6: =COUNTA('Resource Estimates'!A2:A1300) -> 1299
A7: Nonthermal resources - not applicable | B7: =COUNTIF('Resource Estimates'!AE2:AE1300,"N/A (nonthermal)") -> 507
A8: High-confidence EIA reported plant/group proxies | B8: =COUNTIF('Resource Estimates'!AF2:AF1300,"High – plant proxy") -> 327
A9: Medium-confidence EIA reported plant/group proxies | B9: =COUNTIF('Resource Estimates'!AF2:AF1300,"Medium – plant proxy; confirm") -> 104
A10: Unconfirmed EIA candidate; technology estimate retained | B10: =COUNTIF('Resource Estimates'!AF2:AF1300,"Unconfirmed") -> 119
A11: No usable EIA 2025 data | B11: =COUNTIF('Resource Estimates'!AE2:AE1300,"No usable 2025 EIA fuel/generation") -> 10
A12: No technically compatible EIA candidate | B12: =COUNTIF('Resource Estimates'!AE2:AE1300,"No match") -> 232
A13: Distinct EIA matched plant IDs | B13: 142
A14: Independent PJM unit-specific heat rates verified | B14: 0
A17: INTERPRETATION & NEXT STEPS
A18: 2025 EIA-923 reports plant x prime mover x fuel-group fuel consumption and electricity generation, which may aggregate multiple units.
A19: An accepted PJM-to-EIA match is proposed using names, state, fuel and EIA-860 generator technology. It is not a verified unit identity.
A20: The same EIA group heat rate can appear on several PJM resource rows; do NOT sum those duplicated MWh or fuel inputs.
A21: Workbook Resource Estimates column S divides column R by Q, and column X uses it before falling back to the technology estimate.
A22: For actual unit-level hourly performance, next link EPA CAMPD facility-unit identifiers to PJM/EIA generator equipment.
A23: 2025 reported average net heat rates are not the incremental heat rates used in dispatch bids.
A25: Official data sources
A26: https://www.eia.gov/electricity/data/eia923/
A27: https://www.eia.gov/electricity/data/eia860/

Sheet Resource Estimates
A1: Resource Name | B1: ICAP (MW) | C1: Zone | D1: LDA | E1: PJM Class | F1: Assumed Fuel | G1: Technology | H1: Low HR (MMBtu/MWh) | I1: Base HR (MMBtu/MWh) | J1: High HR (MMBtu/MWh) | K1: Assessment | L1: Assumption Notes | M1: Base Thermal Input at ICAP (MMBtu/h) | N1: Historical Data Status | O1: EIA Plant ID | P1: EIA Plant Name | Q1: 2025 Net Generation (MWh) | R1: 2025 Fuel for Electricity (MMBtu) | S1: 2025 Historical Net HR (MMBtu/MWh) | T1: Match Scope | U1: Fuel / Prime Mover | V1: Historical Data URL | W1: Match / Data Quality Notes | X1: Selected Modeling HR (MMBtu/MWh) | Y1: Selected HR Basis | Z1: Review Flag | AA1: Suggested EIA Match Score | AB1: EIA Plant State | AC1: EIA-860 Generator IDs | AD1: EIA-860 Plant Operable MW | AE1: 2025 Heat Rate Coverage | AF1: EIA Match Confidence | AG1: Original Reported Heat Rate (MMBtu/MWh) | AH1: OUTPUT | AI1: outage adjusted gen | AJ1: RGGI compliance? | AK1: =1-$AL$1 -> 0.62448249 | AL1: 0.37551751 | AT1: RGGI Zones
A2: VIRGINIA OFFSHORE 1 WF | B2: 1.5 | C2: DOM | D2: DOM | E2: Offshore Wind | F2: Wind | G2: Wind turbine | K2: Not applicable | L2: Not applicable: no thermal fuel input | M2: =IF(OR(B2="",I2=""),"",B2*I2) | N2: Not applicable – nonthermal | S2: =IF(AND(ISNUMBER(Q2),Q2>0,ISNUMBER(R2),R2>0),R2/Q2,"") | X2: =IF(ISNUMBER(S2),S2,IF(ISNUMBER(I2),I2,"")) | Y2: =IF(ISNUMBER(S2),"2025 EIA-923 plant/group proxy",IF(ISNUMBER(I2),"Technology estimate","No thermal heat rate")) -> No thermal heat rate | Z2: =IF(ISNUMBER(S2),"Review: NOT unit verified",IF(AE2="No match","No EIA match",IF(AF2="Unconfirmed","Unconfirmed EIA candidate",""))) | AE2: N/A (nonthermal) | AF2: No thermal fuel input | AG2: =IF(ISBLANK(S2),S2,I2) -> 0 | AH2: =B2 -> 1.5 | AI2: =AH2*$AK$1 -> 0.93672374 | AJ2: {=OR(D2=$AT$2:$AT$8)} -> TRUE | AT2: JCPL
A3: ALLEGHENY RIDGE WF | B3: 11.1 | C3: PENELEC | D3: MAAC | E3: Onshore Wind | F3: Wind | G3: Wind turbine | K3: Not applicable | L3: Not applicable: no thermal fuel input | M3: =IF(OR(B3="",I3=""),"",B3*I3) | N3: Not applicable – nonthermal | S3: =IF(AND(ISNUMBER(Q3),Q3>0,ISNUMBER(R3),R3>0),R3/Q3,"") | X3: =IF(ISNUMBER(S3),S3,IF(ISNUMBER(I3),I3,"")) | Y3: =IF(ISNUMBER(S3),"2025 EIA-923 plant/group proxy",IF(ISNUMBER(I3),"Technology estimate","No thermal heat rate")) -> No thermal heat rate | Z3: =IF(ISNUMBER(S3),"Review: NOT unit verified",IF(AE3="No match","No EIA match",IF(AF3="Unconfirmed","Unconfirmed EIA candidate",""))) | AE3: N/A (nonthermal) | AF3: No thermal fuel input | AG3: =IF(ISBLANK(S3),S3,I3) -> 0 | AH3: =AH2+B3 -> 12.6 | AI3: =AH3*$AK$1 -> 7.8684794 | AJ3: {=OR(D3=$AT$2:$AT$8)} -> FALSE | AT3: BGE
A4: ALTA WF | B4: 94 | C4: COMED | D4: COMED | E4: Onshore Wind | F4: Wind | G4: Wind turbine | K4: Not applicable | L4: Not applicable: no thermal fuel input | M4: =IF(OR(B4="",I4=""),"",B4*I4) | N4: Not applicable – nonthermal | S4: =IF(AND(ISNUMBER(Q4),Q4>0,ISNUMBER(R4),R4>0),R4/Q4,"") | X4: =IF(ISNUMBER(S4),S4,IF(ISNUMBER(I4),I4,"")) | Y4: =IF(ISNUMBER(S4),"2025 EIA-923 plant/group proxy",IF(ISNUMBER(I4),"Technology estimate","No thermal heat rate")) -> No thermal heat rate | Z4: =IF(ISNUMBER(S4),"Review: NOT unit verified",IF(AE4="No match","No EIA match",IF(AF4="Unconfirmed","Unconfirmed EIA candidate",""))) | AE4: N/A (nonthermal) | AF4: No thermal fuel input | AG4: =IF(ISBLANK(S4),S4,I4) -> 0 | AH4: =AH3+B4 -> 106.6 | AI4: =AH4*$AK$1 -> 66.569833 | AJ4: {=OR(D4=$AT$2:$AT$8)} -> FALSE | AT4: DOM
A5: ARMENIA MOUNTAIN WF | B5: 14.4 | C5: PENELEC | D5: MAAC | E5: Onshore Wind | F5: Wind | G5: Wind turbine | K5: Not applicable | L5: Not applicable: no thermal fuel input | M5: =IF(OR(B5="",I5=""),"",B5*I5) | N5: Not applicable – nonthermal | S5: =IF(AND(ISNUMBER(Q5),Q5>0,ISNUMBER(R5),R5>0),R5/Q5,"") | X5: =IF(ISNUMBER(S5),S5,IF(ISNUMBER(I5),I5,"")) | Y5: =IF(ISNUMBER(S5),"2025 EIA-923 plant/group proxy",IF(ISNUMBER(I5),"Technology estimate","No thermal heat rate")) -> No thermal heat rate | Z5: =IF(ISNUMBER(S5),"Review: NOT unit verified",IF(AE5="No match","No EIA match",IF(AF5="Unconfirmed","Unconfirmed EIA candidate",""))) | AE5: N/A (nonthermal) | AF5: No thermal fuel input | AG5: =IF(ISBLANK(S5),S5,I5) -> 0 | AH5: =AH4+B5 -> 121 | AI5: =AH5*$AK$1 -> 75.562381 | AJ5: {=OR(D5=$AT$2:$AT$8)} -> FALSE | AT5: PEPCO
A6: BACKBONE MT WF | B6: 8 | C6: APS | D6: RTO | E6: Onshore Wind | F6: Wind | G6: Wind turbine | K6: Not applicable | L6: Not applicable: no thermal fuel input | M6: =IF(OR(B6="",I6=""),"",B6*I6) | N6: Not applicable – nonthermal | S6: =IF(AND(ISNUMBER(Q6),Q6>0,ISNUMBER(R6),R6>0),R6/Q6,"") | X6: =IF(ISNUMBER(S6),S6,IF(ISNUMBER(I6),I6,"")) | Y6: =IF(ISNUMBER(S6),"2025 EIA-923 plant/group proxy",IF(ISNUMBER(I6),"Technology estimate","No thermal heat rate")) -> No thermal heat rate | Z6: =IF(ISNUMBER(S6),"Review: NOT unit verified",IF(AE6="No match","No EIA match",IF(AF6="Unconfirmed","Unconfirmed EIA candidate",""))) | AE6: N/A (nonthermal) | AF6: No thermal fuel input | AG6: =IF(ISBLANK(S6),S6,I6) -> 0 | AH6: =AH5+B6 -> 129 | AI6: =AH6*$AK$1 -> 80.558241 | AJ6: {=OR(D6=$AT$2:$AT$8)} -> FALSE | AT6: PSEG
A7: BEAR CREEK WF | B7: 3.3 | C7: PPL | D7: PPL | E7: Onshore Wind | F7: Wind | G7: Wind turbine | K7: Not applicable | L7: Not applicable: no thermal fuel input | M7: =IF(OR(B7="",I7=""),"",B7*I7) | N7: Not applicable – nonthermal | S7: =IF(AND(ISNUMBER(Q7),Q7>0,ISNUMBER(R7),R7>0),R7/Q7,"") | X7: =IF(ISNUMBER(S7),S7,IF(ISNUMBER(I7),I7,"")) | Y7: =IF(ISNUMBER(S7),"2025 EIA-923 plant/group proxy",IF(ISNUMBER(I7),"Technology estimate","No thermal heat rate")) -> No thermal heat rate | Z7: =IF(ISNUMBER(S7),"Review: NOT unit verified",IF(AE7="No match","No EIA match",IF(AF7="Unconfirmed","Unconfirmed EIA candidate",""))) | AE7: N/A (nonthermal) | AF7: No thermal fuel input | AG7: =IF(ISBLANK(S7),S7,I7) -> 0 | AH7: =AH6+B7 -> 132.3 | AI7: =AH7*$AK$1 -> 82.619033 | AJ7: {=OR(D7=$AT$2:$AT$8)} -> FALSE | AT7: DPL
A8: BEECH RIDGE 2 WF | B8: 7.3 | C8: APS | D8: RTO | E8: Onshore Wind | F8: Wind | G8: Wind turbine | K8: Not applicable | L8: Not applicable: no thermal fuel input | M8: =IF(OR(B8="",I8=""),"",B8*I8) | N8: Not applicable – nonthermal | S8: =IF(AND(ISNUMBER(Q8),Q8>0,ISNUMBER(R8),R8>0),R8/Q8,"") | X8: =IF(ISNUMBER(S8),S8,IF(ISNUMBER(I8),I8,"")) | Y8: =IF(ISNUMBER(S8),"2025 EIA-923 plant/group proxy",IF(ISNUMBER(I8),"Technology estimate","No thermal heat rate")) -> No thermal heat rate | Z8: =IF(ISNUMBER(S8),"Review: NOT unit verified",IF(AE8="No match","No EIA match",IF(AF8="Unconfirmed","Unconfirmed EIA candidate",""))) | AE8: N/A (nonthermal) | AF8: No thermal fuel input | AG8: =IF(ISBLANK(S8),S8,I8) -> 0 | AH8: =AH7+B8 -> 139.6 | AI8: =AH8*$AK$1 -> 87.177756 | AJ8: {=OR(D8=$AT$2:$AT$8)} -> FALSE | AT8: AE
A9: BIG SKY WF | B9: 30.4 | C9: COMED | D9: COMED | E9: Onshore Wind | F9: Wind | G9: Wind turbine | K9: Not applicable | L9: Not applicable: no thermal fuel input | M9: =IF(OR(B9="",I9=""),"",B9*I9) | N9: Not applicable – nonthermal | S9: =IF(AND(ISNUMBER(Q9),Q9>0,ISNUMBER(R9),R9>0),R9/Q9,"") | X9: =IF(ISNUMBER(S9),S9,IF(ISNUMBER(I9),I9,"")) | Y9: =IF(ISNUMBER(S9),"2025 EIA-923 plant/group proxy",IF(ISNUMBER(I9),"Technology estimate","No thermal heat rate")) -> No thermal heat rate | Z9: =IF(ISNUMBER(S9),"Review: NOT unit verified",IF(AE9="No match","No EIA match",IF(AF9="Unconfirmed","Unconfirmed EIA candidate",""))) | AE9: N/A (nonthermal) | AF9: No thermal fuel input | AG9: =IF(ISBLANK(S9),S9,I9) -> 0 | AH9: =AH8+B9 -> 170 | AI9: =AH9*$AK$1 -> 106.16202 | AJ9: {=OR(D9=$AT$2:$AT$8)} -> FALSE
A10: BISHOP HILL WF | B10: 40 | C10: COMED | D10: COMED | E10: Onshore Wind | F10: Wind | G10: Wind turbine | K10: Not applicable | L10: Not applicable: no thermal fuel input | M10: =IF(OR(B10="",I10=""),"",B10*I10) | N10: Not applicable – nonthermal | S10: =IF(AND(ISNUMBER(Q10),Q10>0,ISNUMBER(R10),R10>0),R10/Q10,"") | X10: =IF(ISNUMBER(S10),S10,IF(ISNUMBER(I10),I10,"")) | Y10: =IF(ISNUMBER(S10),"2025 EIA-923 plant/group proxy",IF(ISNUMBER(I10),"Technology estimate","No thermal heat rate")) -> No thermal heat rate | Z10: =IF(ISNUMBER(S10),"Review: NOT unit verified",IF(AE10="No match","No EIA match",IF(AF10="Unconfirmed","Unconfirmed EIA candidate",""))) | AE10: N/A (nonthermal) | AF10: No thermal fuel input | AG10: =IF(ISBLANK(S10),S10,I10) -> 0 | AH10: =AH9+B10 -> 210 | AI10: =AH10*$AK$1 -> 131.14132 | AJ10: {=OR(D10=$AT$2:$AT$8)} -> FALSE
A11: BITTER RIDGE WF | B11: 16.9 | C11: AEP | D11: RTO | E11: Onshore Wind | F11: Wind | G11: Wind turbine | K11: Not applicable | L11: Not applicable: no thermal fuel input | M11: =IF(OR(B11="",I11=""),"",B11*I11) | N11: Not applicable – nonthermal | S11: =IF(AND(ISNUMBER(Q11),Q11>0,ISNUMBER(R11),R11>0),R11/Q11,"") | X11: =IF(ISNUMBER(S11),S11,IF(ISNUMBER(I11),I11,"")) | Y11: =IF(ISNUMBER(S11),"2025 EIA-923 plant/group proxy",IF(ISNUMBER(I11),"Technology estimate","No thermal heat rate")) -> No thermal heat rate | Z11: =IF(ISNUMBER(S11),"Review: NOT unit verified",IF(AE11="No match","No EIA match",IF(AF11="Unconfirmed","Unconfirmed EIA candidate",""))) | AE11: N/A (nonthermal) | AF11: No thermal fuel input | AG11: =IF(ISBLANK(S11),S11,I11) -> 0 | AH11: =AH10+B11 -> 226.9 | AI11: =AH11*$AK$1 -> 141.69508 | AJ11: {=OR(D11=$AT$2:$AT$8)} -> FALSE
A12: BLACK ROCK WF | B12: 51.7 | C12: APS | D12: RTO | E12: Onshore Wind | F12: Wind | G12: Wind turbine | K12: Not applicable | L12: Not applicable: no thermal fuel input | M12: =IF(OR(B12="",I12=""),"",B12*I12) | N12: Not applicable – nonthermal | S12: =IF(AND(ISNUMBER(Q12),Q12>0,ISNUMBER(R12),R12>0),R12/Q12,"") | X12: =IF(ISNUMBER(S12),S12,IF(ISNUMBER(I12),I12,"")) | Y12: =IF(ISNUMBER(S12),"2025 EIA-923 plant/group proxy",IF(ISNUMBER(I12),"Technology estimate","No thermal heat rate")) -> No thermal heat rate | Z12: =IF(ISNUMBER(S12),"Review: NOT unit verified",IF(AE12="No match","No EIA match",IF(AF12="Unconfirmed","Unconfirmed EIA candidate",""))) | AE12: N/A (nonthermal) | AF12: No thermal fuel input | AG12: =IF(ISBLANK(S12),S12,I12) -> 0 | AH12: =AH11+B12 -> 278.6 | AI12: =AH12*$AK$1 -> 173.98082 | AJ12: {=OR(D12=$AT$2:$AT$8)} -> FALSE
A13: BLOOMING GROVE WF | B13: 117.5 | C13: COMED | D13: COMED | E13: Onshore Wind | F13: Wind | G13: Wind turbine | K13: Not applicable | L13: Not applicable: no thermal fuel input | M13: =IF(OR(B13="",I13=""),"",B13*I13) | N13: Not applicable – nonthermal | S13: =IF(AND(ISNUMBER(Q13),Q13>0,ISNUMBER(R13),R13>0),R13/Q13,"") | X13: =IF(ISNUMBER(S13),S13,IF(ISNUMBER(I13),I13,"")) | Y13: =IF(ISNUMBER(S13),"2025 EIA-923 plant/group proxy",IF(ISNUMBER(I13),"Technology estimate","No thermal heat rate")) -> No thermal heat rate | Z13: =IF(ISNUMBER(S13),"Review: NOT unit verified",IF(AE13="No match","No EIA match",IF(AF13="Unconfirmed","Unconfirmed EIA candidate",""))) | AE13: N/A (nonthermal) | AF13: No thermal fuel input | AG13: =IF(ISBLANK(S13),S13,I13) -> 0 | AH13: =AH12+B13 -> 396.1 | AI13: =AH13*$AK$1 -> 247.35751 | AJ13: {=OR(D13=$AT$2:$AT$8)} -> FALSE
A14: BLUE CREEK WF | B14: 49.3 | C14: AEP | D14: RTO | E14: Onshore Wind | F14: Wind | G14: Wind turbine | K14: Not applicable | L14: Not applicable: no thermal fuel input | M14: =IF(OR(B14="",I14=""),"",B14*I14) | N14: Not applicable – nonthermal | S14: =IF(AND(ISNUMBER(Q14),Q14>0,ISNUMBER(R14),R14>0),R14/Q14,"") | X14: =IF(ISNUMBER(S14),S14,IF(ISNUMBER(I14),I14,"")) | Y14: =IF(ISNUMBER(S14),"2025 EIA-923 plant/group proxy",IF(ISNUMBER(I14),"Technology estimate","No thermal heat rate")) -> No thermal heat rate | Z14: =IF(ISNUMBER(S14),"Review: NOT unit verified",IF(AE14="No match","No EIA match",IF(AF14="Unconfirmed","Unconfirmed EIA candidate",""))) | AE14: N/A (nonthermal) | AF14: No thermal fuel input | AG14: =IF(ISBLANK(S14),S14,I14) -> 0 | AH14: =AH13+B14 -> 445.4 | AI14: =AH14*$AK$1 -> 278.1445 | AJ14: {=OR(D14=$AT$2:$AT$8)} -> FALSE
A15: BLUFF POINT WF | B15: 24 | C15: AEP | D15: RTO | E15: Onshore Wind | F15: Wind | G15: Wind turbine | K15: Not applicable | L15: Not applicable: no thermal fuel input | M15: =IF(OR(B15="",I15=""),"",B15*I15) | N15: Not applicable – nonthermal | S15: =IF(AND(ISNUMBER(Q15),Q15>0,ISNUMBER(R15),R15>0),R15/Q15,"") | X15: =IF(ISNUMBER(S15),S15,IF(ISNUMBER(I15),I15,"")) | Y15: =IF(ISNUMBER(S15),"2025 EIA-923 plant/group proxy",IF(ISNUMBER(I15),"Technology estimate","No thermal heat rate")) -> No thermal heat rate | Z15: =IF(ISNUMBER(S15),"Review: NOT unit verified",IF(AE15="No match","No EIA match",IF(AF15="Unconfirmed","Unconfirmed EIA candidate",""))) | AE15: N/A (nonthermal) | AF15: No thermal fuel input | AG15: =IF(ISBLANK(S15),S15,I15) -> 0 | AH15: =AH14+B15 -> 469.4 | AI15: =AH15*$AK$1 -> 293.13208 | AJ15: {=OR(D15=$AT$2:$AT$8)} -> FALSE
A16: BRIGHT STALK WF | B16: 94 | C16: COMED | D16: COMED | E16: Onshore Wind | F16: Wind | G16: Wind turbine | K16: Not applicable | L16: Not applicable: no thermal fuel input | M16: =IF(OR(B16="",I16=""),"",B16*I16) | N16: Not applicable – nonthermal | S16: =IF(AND(ISNUMBER(Q16),Q16>0,ISNUMBER(R16),R16>0),R16/Q16,"") | X16: =IF(ISNUMBER(S16),S16,IF(ISNUMBER(I16),I16,"")) | Y16: =IF(ISNUMBER(S16),"2025 EIA-923 plant/group proxy",IF(ISNUMBER(I16),"Technology estimate","No thermal heat rate")) -> No thermal heat rate | Z16: =IF(ISNUMBER(S16),"Review: NOT unit verified",IF(AE16="No match","No EIA match",IF(AF16="Unconfirmed","Unconfirmed EIA candidate",""))) | AE16: N/A (nonthermal) | AF16: No thermal fuel input | AG16: =IF(ISBLANK(S16),S16,I16) -> 0 | AH16: =AH15+B16 -> 563.4 | AI16: =AH16*$AK$1 -> 351.83344 | AJ16: {=OR(D16=$AT$2:$AT$8)} -> FALSE
A17: CAMP GROVE 2 WF | B17: 13 | C17: COMED | D17: COMED | E17: Onshore Wind | F17: Wind | G17: Wind turbine | K17: Not applicable | L17: Not applicable: no thermal fuel input | M17: =IF(OR(B17="",I17=""),"",B17*I17) | N17: Not applicable – nonthermal | S17: =IF(AND(ISNUMBER(Q17),Q17>0,ISNUMBER(R17),R17>0),R17/Q17,"") | X17: =IF(ISNUMBER(S17),S17,IF(ISNUMBER(I17),I17,"")) | Y17: =IF(ISNUMBER(S17),"2025 EIA-923 plant/group proxy",IF(ISNUMBER(I17),"Technology estimate","No thermal heat rate")) -> No thermal heat rate | Z17: =IF(ISNUMBER(S17),"Review: NOT unit verified",IF(AE17="No match","No EIA match",IF(AF17="Unconfirmed","Unconfirmed EIA candidate",""))) | AE17: N/A (nonthermal) | AF17: No thermal fuel input | AG17: =IF(ISBLANK(S17),S17,I17) -> 0 | AH17: =AH16+B17 -> 576.4 | AI17: =AH17*$AK$1 -> 359.95171 | AJ17: {=OR(D17=$AT$2:$AT$8)} -> FALSE
A18: CAMP GROVE WF | B18: 13 | C18: COMED | D18: COMED | E18: Onshore Wind | F18: Wind | G18: Wind turbine | K18: Not applicable | L18: Not applicable: no thermal fuel input | M18: =IF(OR(B18="",I18=""),"",B18*I18) | N18: Not applicable – nonthermal | S18: =IF(AND(ISNUMBER(Q18),Q18>0,ISNUMBER(R18),R18>0),R18/Q18,"") | X18: =IF(ISNUMBER(S18),S18,IF(ISNUMBER(I18),I18,"")) | Y18: =IF(ISNUMBER(S18),"2025 EIA-923 plant/group proxy",IF(ISNUMBER(I18),"Technology estimate","No thermal heat rate")) -> No thermal heat rate | Z18: =IF(ISNUMBER(S18),"Review: NOT unit verified",IF(AE18="No match","No EIA match",IF(AF18="Unconfirmed","Unconfirmed EIA candidate",""))) | AE18: N/A (nonthermal) | AF18: No thermal fuel input | AG18: =IF(ISBLANK(S18),S18,I18) -> 0 | AH18: =AH17+B18 -> 589.4 | AI18: =AH18*$AK$1 -> 368.06998 | AJ18: {=OR(D18=$AT$2:$AT$8)} -> FALSE
A19: CASSELMAN WF | B19: 5.7 | C19: PENELEC | D19: MAAC | E19: Onshore Wind | F19: Wind | G19: Wind turbine | K19: Not applicable | L19: Not applicable: no thermal fuel input | M19: =IF(OR(B19="",I19=""),"",B19*I19) | N19: Not applicable – nonthermal | S19: =IF(AND(ISNUMBER(Q19),Q19>0,ISNUMBER(R19),R19>0),R19/Q19,"") | X19: =IF(ISNUMBER(S19),S19,IF(ISNUMBER(I19),I19,"")) | Y19: =IF(ISNUMBER(S19),"2025 EIA-923 plant/group proxy",IF(ISNUMBER(I19),"Technology estimate","No thermal heat rate")) -> No thermal heat rate | Z19: =IF(ISNUMBER(S19),"Review: NOT unit verified",IF(AE19="No match","No EIA match",IF(AF19="Unconfirmed","Unconfirmed EIA candidate",""))) | AE19: N/A (nonthermal) | AF19: No thermal fuel input | AG19: =IF(ISBLANK(S19),S19,I19) -> 0 | AH19: =AH18+B19 -> 595.1 | AI19: =AH19*$AK$1 -> 371.62953 | AJ19: {=OR(D19=$AT$2:$AT$8)} -> FALSE
A20: CAYUGA RIDGE WF | B20: 45 | C20: COMED | D20: COMED | E20: Onshore Wind | F20: Wind | G20: Wind turbine | K20: Not applicable | L20: Not applicable: no thermal fuel input | M20: =IF(OR(B20="",I20=""),"",B20*I20) | N20: Not applicable – nonthermal | S20: =IF(AND(ISNUMBER(Q20),Q20>0,ISNUMBER(R20),R20>0),R20/Q20,"") | X20: =IF(ISNUMBER(S20),S20,IF(ISNUMBER(I20),I20,"")) | Y20: =IF(ISNUMBER(S20),"2025 EIA-923 plant/group proxy",IF(ISNUMBER(I20),"Technology estimate","No thermal heat rate")) -> No thermal heat rate | Z20: =IF(ISNUMBER(S20),"Review: NOT unit verified",IF(AE20="No match","No EIA match",IF(AF20="Unconfirmed","Unconfirmed EIA candidate",""))) | AE20: N/A (nonthermal) | AF20: No thermal fuel input | AG20: =IF(ISBLANK(S20),S20,I20) -> 0 | AH20: =AH19+B20 -> 640.1 | AI20: =AH20*$AK$1 -> 399.73124 | AJ20: {=OR(D20=$AT$2:$AT$8)} -> FALSE
... A25: DANS MOUNTAIN WF | B25: 25.8 | C25: APS | D25: RTO | E25: Onshore Wind | F25: Wind | G25: Wind turbine | K25: Not applicable | L25: Not applicable: no thermal fuel input | M25: =IF(OR(B25="",I25=""),"",B25*I25) | N25: Not applicable – nonthermal | S25: =IF(AND(ISNUMBER(Q25),Q25>0,ISNUMBER(R25),R25>0),R25/Q25,"") | X25: =IF(ISNUMBER(S25),S25,IF(ISNUMBER(I25),I25,"")) | Y25: =IF(ISNUMBER(S25),"2025 EIA-923 plant/group proxy",IF(ISNUMBER(I25),"Technology estimate","No thermal heat rate")) -> No thermal heat rate | Z25: =IF(ISNUMBER(S25),"Review: NOT unit verified",IF(AE25="No match","No EIA match",IF(AF25="Unconfirmed","Unconfirmed EIA candidate",""))) | AE25: N/A (nonthermal) | AF25: No thermal fuel input | AG25: =IF(ISBLANK(S25),S25,I25) -> 0 | AH25: =AH24+B25 -> 716.9 | AI25: =AH25*$AK$1 -> 447.6915 | AJ25: {=OR(D25=$AT$2:$AT$8)} -> FALSE
A26: DESERT WF | B26: 27 | C26: DOM | D26: DOM | E26: Onshore Wind | F26: Wind | G26: Wind turbine | K26: Not applicable | L26: Not applicable: no thermal fuel input | M26: =IF(OR(B26="",I26=""),"",B26*I26) | N26: Not applicable – nonthermal | S26: =IF(AND(ISNUMBER(Q26),Q26>0,ISNUMBER(R26),R26>0),R26/Q26,"") | X26: =IF(ISNUMBER(S26),S26,IF(ISNUMBER(I26),I26,"")) | Y26: =IF(ISNUMBER(S26),"2025 EIA-923 plant/group proxy",IF(ISNUMBER(I26),"Technology estimate","No thermal heat rate")) -> No thermal heat rate | Z26: =IF(ISNUMBER(S26),"Review: NOT unit verified",IF(AE26="No match","No EIA match",IF(AF26="Unconfirmed","Unconfirmed EIA candidate",""))) | AE26: N/A (nonthermal) | AF26: No thermal fuel input | AG26: =IF(ISBLANK(S26),S26,I26) -> 0 | AH26: =AH25+B26 -> 743.9 | AI26: =AH26*$AK$1 -> 464.55252 | AJ26: {=OR(D26=$AT$2:$AT$8)} -> TRUE | AL26: 23 | AM26: 91962 | AN26: forecasted heat rate | AO26: =_xlfn.XLOOKUP(AM26,AI:AI,AG:AG,,-1) -> 10.7686
A27: EAST CARBONDALE WF | B27: 8.3 | C27: PPL | D27: PPL | E27: Onshore Wind | F27: Wind | G27: Wind turbine | K27: Not applicable | L27: Not applicable: no thermal fuel input | M27: =IF(OR(B27="",I27=""),"",B27*I27) | N27: Not applicable – nonthermal | S27: =IF(AND(ISNUMBER(Q27),Q27>0,ISNUMBER(R27),R27>0),R27/Q27,"") | X27: =IF(ISNUMBER(S27),S27,IF(ISNUMBER(I27),I27,"")) | Y27: =IF(ISNUMBER(S27),"2025 EIA-923 plant/group proxy",IF(ISNUMBER(I27),"Technology estimate","No thermal heat rate")) -> No thermal heat rate | Z27: =IF(ISNUMBER(S27),"Review: NOT unit verified",IF(AE27="No match","No EIA match",IF(AF27="Unconfirmed","Unconfirmed EIA candidate",""))) | AE27: N/A (nonthermal) | AF27: No thermal fuel input | AG27: =IF(ISBLANK(S27),S27,I27) -> 0 | AH27: =AH26+B27 -> 752.2 | AI27: =AH27*$AK$1 -> 469.73573 | AJ27: {=OR(D27=$AT$2:$AT$8)} -> FALSE | AL27: 0 | AM27: 91962 | AP27: RS | AQ27: LKWD CT 1 | AR27: LKWD NuG
A28: ECOGROVE WF | B28: 19.4 | C28: COMED | D28: COMED | E28: Onshore Wind | F28: Wind | G28: Wind turbine | K28: Not applicable | L28: Not applicable: no thermal fuel input | M28: =IF(OR(B28="",I28=""),"",B28*I28) | N28: Not applicable – nonthermal | S28: =IF(AND(ISNUMBER(Q28),Q28>0,ISNUMBER(R28),R28>0),R28/Q28,"") | X28: =IF(ISNUMBER(S28),S28,IF(ISNUMBER(I28),I28,"")) | Y28: =IF(ISNUMBER(S28),"2025 EIA-923 plant/group proxy",IF(ISNUMBER(I28),"Technology estimate","No thermal heat rate")) -> No thermal heat rate | Z28: =IF(ISNUMBER(S28),"Review: NOT unit verified",IF(AE28="No match","No EIA match",IF(AF28="Unconfirmed","Unconfirmed EIA candidate",""))) | AE28: N/A (nonthermal) | AF28: No thermal fuel input | AG28: =IF(ISBLANK(S28),S28,I28) -> 0 | AH28: =AH27+B28 -> 771.6 | AI28: =AH28*$AK$1 -> 481.85069 | AJ28: {=OR(D28=$AT$2:$AT$8)} -> FALSE | AK28: 46317 | AL28: HE 1 | AM28: 77671 | AN28: =_xlfn.XLOOKUP(AM28,$AI:$AI,$AG:$AG,,-1) -> 10.1627 | AP28: =$AT$28 -> 10.5628 | AQ28: =$AT$29 -> 10.5 | AR28: =$AT$30 -> 7.4 | AS28: Rock Springs CT1 | AT28: =_xlfn.XLOOKUP(AS28,$A:$A,$AG:$AG,,-1) -> 10.5628
A29: FIELD MOUNTAIN WF | B29: 14.1 | C29: APS | D29: RTO | E29: Onshore Wind | F29: Wind | G29: Wind turbine | K29: Not applicable | L29: Not applicable: no thermal fuel input | M29: =IF(OR(B29="",I29=""),"",B29*I29) | N29: Not applicable – nonthermal | S29: =IF(AND(ISNUMBER(Q29),Q29>0,ISNUMBER(R29),R29>0),R29/Q29,"") | X29: =IF(ISNUMBER(S29),S29,IF(ISNUMBER(I29),I29,"")) | Y29: =IF(ISNUMBER(S29),"2025 EIA-923 plant/group proxy",IF(ISNUMBER(I29),"Technology estimate","No thermal heat rate")) -> No thermal heat rate | Z29: =IF(ISNUMBER(S29),"Review: NOT unit verified",IF(AE29="No match","No EIA match",IF(AF29="Unconfirmed","Unconfirmed EIA candidate",""))) | AE29: N/A (nonthermal) | AF29: No thermal fuel input | AG29: =IF(ISBLANK(S29),S29,I29) -> 0 | AH29: =AH28+B29 -> 785.7 | AI29: =AH29*$AK$1 -> 490.65589 | AJ29: {=OR(D29=$AT$2:$AT$8)} -> FALSE | AL29: HE 2 | AM29: 75828 | AN29: =_xlfn.XLOOKUP(AM29,$AI:$AI,$AG:$AG,,-1) -> 9.9859 | AP29: =$AT$28 -> 10.5628 | AQ29: =$AT$29 -> 10.5 | AR29: =$AT$30 -> 7.4 | AS29: Lakewood CT1 | AT29: =_xlfn.XLOOKUP(AS29,$A:$A,$AG:$AG,,-1) -> 10.5
A30: FORWARD WF | B30: 10 | C30: PENELEC | D30: MAAC | E30: Onshore Wind | F30: Wind | G30: Wind turbine | K30: Not applicable | L30: Not applicable: no thermal fuel input | M30: =IF(OR(B30="",I30=""),"",B30*I30) | N30: Not applicable – nonthermal | S30: =IF(AND(ISNUMBER(Q30),Q30>0,ISNUMBER(R30),R30>0),R30/Q30,"") | X30: =IF(ISNUMBER(S30),S30,IF(ISNUMBER(I30),I30,"")) | Y30: =IF(ISNUMBER(S30),"2025 EIA-923 plant/group proxy",IF(ISNUMBER(I30),"Technology estimate","No thermal heat rate")) -> No thermal heat rate | Z30: =IF(ISNUMBER(S30),"Review: NOT unit verified",IF(AE30="No match","No EIA match",IF(AF30="Unconfirmed","Unconfirmed EIA candidate",""))) | AE30: N/A (nonthermal) | AF30: No thermal fuel input | AG30: =IF(ISBLANK(S30),S30,I30) -> 0 | AH30: =AH29+B30 -> 795.7 | AI30: =AH30*$AK$1 -> 496.90072 | AJ30: {=OR(D30=$AT$2:$AT$8)} -> FALSE | AL30: HE 3 | AM30: 74857 | AN30: =_xlfn.XLOOKUP(AM30,$AI:$AI,$AG:$AG,,-1) -> 9.9708 | AP30: =$AT$28 -> 10.5628 | AQ30: =$AT$29 -> 10.5 | AR30: =$AT$30 -> 7.4 | AS30: Lakewood NUG | AT30: =_xlfn.XLOOKUP(AS30,$A:$A,$AG:$AG,,-1) -> 7.4
A31: FOUR MILE RIDGE WF | B31: 5.2 | C31: APS | D31: RTO | E31: Onshore Wind | F31: Wind | G31: Wind turbine | K31: Not applicable | L31: Not applicable: no thermal fuel input | M31: =IF(OR(B31="",I31=""),"",B31*I31) | N31: Not applicable – nonthermal | S31: =IF(AND(ISNUMBER(Q31),Q31>0,ISNUMBER(R31),R31>0),R31/Q31,"") | X31: =IF(ISNUMBER(S31),S31,IF(ISNUMBER(I31),I31,"")) | Y31: =IF(ISNUMBER(S31),"2025 EIA-923 plant/group proxy",IF(ISNUMBER(I31),"Technology estimate","No thermal heat rate")) -> No thermal heat rate | Z31: =IF(ISNUMBER(S31),"Review: NOT unit verified",IF(AE31="No match","No EIA match",IF(AF31="Unconfirmed","Unconfirmed EIA candidate",""))) | AE31: N/A (nonthermal) | AF31: No thermal fuel input | AG31: =IF(ISBLANK(S31),S31,I31) -> 0 | AH31: =AH30+B31 -> 800.9 | AI31: =AH31*$AK$1 -> 500.14803 | AJ31: {=OR(D31=$AT$2:$AT$8)} -> FALSE | AL31: HE 4 | AM31: 74756 | AN31: =_xlfn.XLOOKUP(AM31,$AI:$AI,$AG:$AG,,-1) -> 9.9708 | AP31: =$AT$28 -> 10.5628 | AQ31: =$AT$29 -> 10.5 | AR31: =$AT$30 -> 7.4
A32: FOWLER RIDGE 2 WF | B32: 26 | C32: AEP | D32: RTO | E32: Onshore Wind | F32: Wind | G32: Wind turbine | K32: Not applicable | L32: Not applicable: no thermal fuel input | M32: =IF(OR(B32="",I32=""),"",B32*I32) | N32: Not applicable – nonthermal | S32: =IF(AND(ISNUMBER(Q32),Q32>0,ISNUMBER(R32),R32>0),R32/Q32,"") | X32: =IF(ISNUMBER(S32),S32,IF(ISNUMBER(I32),I32,"")) | Y32: =IF(ISNUMBER(S32),"2025 EIA-923 plant/group proxy",IF(ISNUMBER(I32),"Technology estimate","No thermal heat rate")) -> No thermal heat rate | Z32: =IF(ISNUMBER(S32),"Review: NOT unit verified",IF(AE32="No match","No EIA match",IF(AF32="Unconfirmed","Unconfirmed EIA candidate",""))) | AE32: N/A (nonthermal) | AF32: No thermal fuel input | AG32: =IF(ISBLANK(S32),S32,I32) -> 0 | AH32: =AH31+B32 -> 826.9 | AI32: =AH32*$AK$1 -> 516.38457 | AJ32: {=OR(D32=$AT$2:$AT$8)} -> FALSE | AL32: HE 5 | AM32: 76041 | AN32: =_xlfn.XLOOKUP(AM32,$AI:$AI,$AG:$AG,,-1) -> 10.0705 | AP32: =$AT$28 -> 10.5628 | AQ32: =$AT$29 -> 10.5 | AR32: =$AT$30 -> 7.4
A33: FOWLER RIDGE 3 WF | B33: 12.5 | C33: AEP | D33: RTO | E33: Onshore Wind | F33: Wind | G33: Wind turbine | K33: Not applicable | L33: Not applicable: no thermal fuel input | M33: =IF(OR(B33="",I33=""),"",B33*I33) | N33: Not applicable – nonthermal | S33: =IF(AND(ISNUMBER(Q33),Q33>0,ISNUMBER(R33),R33>0),R33/Q33,"") | X33: =IF(ISNUMBER(S33),S33,IF(ISNUMBER(I33),I33,"")) | Y33: =IF(ISNUMBER(S33),"2025 EIA-923 plant/group proxy",IF(ISNUMBER(I33),"Technology estimate","No thermal heat rate")) -> No thermal heat rate | Z33: =IF(ISNUMBER(S33),"Review: NOT unit verified",IF(AE33="No match","No EIA match",IF(AF33="Unconfirmed","Unconfirmed EIA candidate",""))) | AE33: N/A (nonthermal) | AF33: No thermal fuel input | AG33: =IF(ISBLANK(S33),S33,I33) -> 0 | AH33: =AH32+B33 -> 839.4 | AI33: =AH33*$AK$1 -> 524.1906 | AJ33: {=OR(D33=$AT$2:$AT$8)} -> FALSE | AL33: HE 6 | AM33: 79787 | AN33: =_xlfn.XLOOKUP(AM33,$AI:$AI,$AG:$AG,,-1) -> 10.2551 | AP33: =$AT$28 -> 10.5628 | AQ33: =$AT$29 -> 10.5 | AR33: =$AT$30 -> 7.4
A34: FOWLER RIDGE 4 WF | B34: 26.8 | C34: AEP | D34: RTO | E34: Onshore Wind | F34: Wind | G34: Wind turbine | K34: Not applicable | L34: Not applicable: no thermal fuel input | M34: =IF(OR(B34="",I34=""),"",B34*I34) | N34: Not applicable – nonthermal | S34: =IF(AND(ISNUMBER(Q34),Q34>0,ISNUMBER(R34),R34>0),R34/Q34,"") | X34: =IF(ISNUMBER(S34),S34,IF(ISNUMBER(I34),I34,"")) | Y34: =IF(ISNUMBER(S34),"2025 EIA-923 plant/group proxy",IF(ISNUMBER(I34),"Technology estimate","No thermal heat rate")) -> No thermal heat rate | Z34: =IF(ISNUMBER(S34),"Review: NOT unit verified",IF(AE34="No match","No EIA match",IF(AF34="Unconfirmed","Unconfirmed EIA candidate",""))) | AE34: N/A (nonthermal) | AF34: No thermal fuel input | AG34: =IF(ISBLANK(S34),S34,I34) -> 0 | AH34: =AH33+B34 -> 866.2 | AI34: =AH34*$AK$1 -> 540.92673 | AJ34: {=OR(D34=$AT$2:$AT$8)} -> FALSE | AL34: HE 7 | AM34: 85947 | AN34: =_xlfn.XLOOKUP(AM34,$AI:$AI,$AG:$AG,,-1) -> 10.4275 | AP34: =$AT$28 -> 10.5628 | AQ34: =$AT$29 -> 10.5 | AR34: =$AT$30 -> 7.4
A35: FOWLER RIDGE WF | B35: 37 | C35: AEP | D35: RTO | E35: Onshore Wind | F35: Wind | G35: Wind turbine | K35: Not applicable | L35: Not applicable: no thermal fuel input | M35: =IF(OR(B35="",I35=""),"",B35*I35) | N35: Not applicable – nonthermal | S35: =IF(AND(ISNUMBER(Q35),Q35>0,ISNUMBER(R35),R35>0),R35/Q35,"") | X35: =IF(ISNUMBER(S35),S35,IF(ISNUMBER(I35),I35,"")) | Y35: =IF(ISNUMBER(S35),"2025 EIA-923 plant/group proxy",IF(ISNUMBER(I35),"Technology estimate","No thermal heat rate")) -> No thermal heat rate | Z35: =IF(ISNUMBER(S35),"Review: NOT unit verified",IF(AE35="No match","No EIA match",IF(AF35="Unconfirmed","Unconfirmed EIA candidate",""))) | AE35: N/A (nonthermal) | AF35: No thermal fuel input | AG35: =IF(ISBLANK(S35),S35,I35) -> 0 | AH35: =AH34+B35 -> 903.2 | AI35: =AH35*$AK$1 -> 564.03259 | AJ35: {=OR(D35=$AT$2:$AT$8)} -> FALSE | AL35: HE 8 | AM35: 90182 | AN35: =_xlfn.XLOOKUP(AM35,$AI:$AI,$AG:$AG,,-1) -> 10.6032 | AP35: =$AT$28 -> 10.5628 | AQ35: =$AT$29 -> 10.5 | AR35: =$AT$30 -> 7.4
A36: GRAND RIDGE 2 WF | B36: 19.7 | C36: COMED | D36: COMED | E36: Onshore Wind | F36: Wind | G36: Wind turbine | K36: Not applicable | L36: Not applicable: no thermal fuel input | M36: =IF(OR(B36="",I36=""),"",B36*I36) | N36: Not applicable – nonthermal | S36: =IF(AND(ISNUMBER(Q36),Q36>0,ISNUMBER(R36),R36>0),R36/Q36,"") | X36: =IF(ISNUMBER(S36),S36,IF(ISNUMBER(I36),I36,"")) | Y36: =IF(ISNUMBER(S36),"2025 EIA-923 plant/group proxy",IF(ISNUMBER(I36),"Technology estimate","No thermal heat rate")) -> No thermal heat rate | Z36: =IF(ISNUMBER(S36),"Review: NOT unit verified",IF(AE36="No match","No EIA match",IF(AF36="Unconfirmed","Unconfirmed EIA candidate",""))) | AE36: N/A (nonthermal) | AF36: No thermal fuel input | AG36: =IF(ISBLANK(S36),S36,I36) -> 0 | AH36: =AH35+B36 -> 922.9 | AI36: =AH36*$AK$1 -> 576.33489 | AJ36: {=OR(D36=$AT$2:$AT$8)} -> FALSE | AL36: HE 9 | AM36: 90430 | AN36: =_xlfn.XLOOKUP(AM36,$AI:$AI,$AG:$AG,,-1) -> 10.6381 | AP36: =$AT$28 -> 10.5628 | AQ36: =$AT$29 -> 10.5 | AR36: =$AT$30 -> 7.4
A37: GRAND RIDGE 3 WF | B37: 13.3 | C37: COMED | D37: COMED | E37: Onshore Wind | F37: Wind | G37: Wind turbine | K37: Not applicable | L37: Not applicable: no thermal fuel input | M37: =IF(OR(B37="",I37=""),"",B37*I37) | N37: Not applicable – nonthermal | S37: =IF(AND(ISNUMBER(Q37),Q37>0,ISNUMBER(R37),R37>0),R37/Q37,"") | X37: =IF(ISNUMBER(S37),S37,IF(ISNUMBER(I37),I37,"")) | Y37: =IF(ISNUMBER(S37),"2025 EIA-923 plant/group proxy",IF(ISNUMBER(I37),"Technology estimate","No thermal heat rate")) -> No thermal heat rate | Z37: =IF(ISNUMBER(S37),"Review: NOT unit verified",IF(AE37="No match","No EIA match",IF(AF37="Unconfirmed","Unconfirmed EIA candidate",""))) | AE37: N/A (nonthermal) | AF37: No thermal fuel input | AG37: =IF(ISBLANK(S37),S37,I37) -> 0 | AH37: =AH36+B37 -> 936.2 | AI37: =AH37*$AK$1 -> 584.64051 | AJ37: {=OR(D37=$AT$2:$AT$8)} -> FALSE | AL37: HE 10 | AM37: 88805 | AN37: =_xlfn.XLOOKUP(AM37,$AI:$AI,$AG:$AG,,-1) -> 10.5278 | AP37: =$AT$28 -> 10.5628 | AQ37: =$AT$29 -> 10.5 | AR37: =$AT$30 -> 7.4
A38: GRAND RIDGE 4 WF | B38: 2.8 | C38: COMED | D38: COMED | E38: Onshore Wind | F38: Wind | G38: Wind turbine | K38: Not applicable | L38: Not applicable: no thermal fuel input | M38: =IF(OR(B38="",I38=""),"",B38*I38) | N38: Not applicable – nonthermal | S38: =IF(AND(ISNUMBER(Q38),Q38>0,ISNUMBER(R38),R38>0),R38/Q38,"") | X38: =IF(ISNUMBER(S38),S38,IF(ISNUMBER(I38),I38,"")) | Y38: =IF(ISNUMBER(S38),"2025 EIA-923 plant/group proxy",IF(ISNUMBER(I38),"Technology estimate","No thermal heat rate")) -> No thermal heat rate | Z38: =IF(ISNUMBER(S38),"Review: NOT unit verified",IF(AE38="No match","No EIA match",IF(AF38="Unconfirmed","Unconfirmed EIA candidate",""))) | AE38: N/A (nonthermal) | AF38: No thermal fuel input | AG38: =IF(ISBLANK(S38),S38,I38) -> 0 | AH38: =AH37+B38 -> 939 | AI38: =AH38*$AK$1 -> 586.38906 | AJ38: {=OR(D38=$AT$2:$AT$8)} -> FALSE | AL38: HE 11 | AM38: 87252 | AN38: =_xlfn.XLOOKUP(AM38,$AI:$AI,$AG:$AG,,-1) -> 10.5 | AP38: =$AT$28 -> 10.5628 | AQ38: =$AT$29 -> 10.5 | AR38: =$AT$30 -> 7.4
A39: GRAND RIDGE WF | B39: 38.2 | C39: COMED | D39: COMED | E39: Onshore Wind | F39: Wind | G39: Wind turbine | K39: Not applicable | L39: Not applicable: no thermal fuel input | M39: =IF(OR(B39="",I39=""),"",B39*I39) | N39: Not applicable – nonthermal | S39: =IF(AND(ISNUMBER(Q39),Q39>0,ISNUMBER(R39),R39>0),R39/Q39,"") | X39: =IF(ISNUMBER(S39),S39,IF(ISNUMBER(I39),I39,"")) | Y39: =IF(ISNUMBER(S39),"2025 EIA-923 plant/group proxy",IF(ISNUMBER(I39),"Technology estimate","No thermal heat rate")) -> No thermal heat rate | Z39: =IF(ISNUMBER(S39),"Review: NOT unit verified",IF(AE39="No match","No EIA match",IF(AF39="Unconfirmed","Unconfirmed EIA candidate",""))) | AE39: N/A (nonthermal) | AF39: No thermal fuel input | AG39: =IF(ISBLANK(S39),S39,I39) -> 0 | AH39: =AH38+B39 -> 977.2 | AI39: =AH39*$AK$1 -> 610.24429 | AJ39: {=OR(D39=$AT$2:$AT$8)} -> FALSE | AL39: HE 12 | AM39: 86068 | AN39: =_xlfn.XLOOKUP(AM39,$AI:$AI,$AG:$AG,,-1) -> 10.4823 | AP39: =$AT$28 -> 10.5628 | AQ39: =$AT$29 -> 10.5 | AR39: =$AT$30 -> 7.4
A40: GREEN RIVER WF | B40: 85 | C40: COMED | D40: COMED | E40: Onshore Wind | F40: Wind | G40: Wind turbine | K40: Not applicable | L40: Not applicable: no thermal fuel input | M40: =IF(OR(B40="",I40=""),"",B40*I40) | N40: Not applicable – nonthermal | S40: =IF(AND(ISNUMBER(Q40),Q40>0,ISNUMBER(R40),R40>0),R40/Q40,"") | X40: =IF(ISNUMBER(S40),S40,IF(ISNUMBER(I40),I40,"")) | Y40: =IF(ISNUMBER(S40),"2025 EIA-923 plant/group proxy",IF(ISNUMBER(I40),"Technology estimate","No thermal heat rate")) -> No thermal heat rate | Z40: =IF(ISNUMBER(S40),"Review: NOT unit verified",IF(AE40="No match","No EIA match",IF(AF40="Unconfirmed","Unconfirmed EIA candidate",""))) | AE40: N/A (nonthermal) | AF40: No thermal fuel input | AG40: =IF(ISBLANK(S40),S40,I40) -> 0 | AH40: =AH39+B40 -> 1062.2 | AI40: =AH40*$AK$1 -> 663.3253 | AJ40: {=OR(D40=$AT$2:$AT$8)} -> FALSE | AL40: HE 13 | AM40: 85257 | AN40: =_xlfn.XLOOKUP(AM40,$AI:$AI,$AG:$AG,,-1) -> 10.3833 | AP40: =$AT$28 -> 10.5628 | AQ40: =$AT$29 -> 10.5 | AR40: =$AT$30 -> 7.4
A41: GREENLAND GAP WF | B41: 141 | C41: APS | D41: RTO | E41: Onshore Wind | F41: Wind | G41: Wind turbine | K41: Not applicable | L41: Not applicable: no thermal fuel input | M41: =IF(OR(B41="",I41=""),"",B41*I41) | N41: Not applicable – nonthermal | S41: =IF(AND(ISNUMBER(Q41),Q41>0,ISNUMBER(R41),R41>0),R41/Q41,"") | X41: =IF(ISNUMBER(S41),S41,IF(ISNUMBER(I41),I41,"")) | Y41: =IF(ISNUMBER(S41),"2025 EIA-923 plant/group proxy",IF(ISNUMBER(I41),"Technology estimate","No thermal heat rate")) -> No thermal heat rate | Z41: =IF(ISNUMBER(S41),"Review: NOT unit verified",IF(AE41="No match","No EIA match",IF(AF41="Unconfirmed","Unconfirmed EIA candidate",""))) | AE41: N/A (nonthermal) | AF41: No thermal fuel input | AG41: =IF(ISBLANK(S41),S41,I41) -> 0 | AH41: =AH40+B41 -> 1203.2 | AI41: =AH41*$AK$1 -> 751.37733 | AJ41: {=OR(D41=$AT$2:$AT$8)} -> FALSE | AL41: HE 14 | AM41: 84932 | AN41: =_xlfn.XLOOKUP(AM41,$AI:$AI,$AG:$AG,,-1) -> 10.3833 | AP41: =$AT$28 -> 10.5628 | AQ41: =$AT$29 -> 10.5 | AR41: =$AT$30 -> 7.4
A42: HAVILAND WF | B42: 13 | C42: AEP | D42: RTO | E42: Onshore Wind | F42: Wind | G42: Wind turbine | K42: Not applicable | L42: Not applicable: no thermal fuel input | M42: =IF(OR(B42="",I42=""),"",B42*I42) | N42: Not applicable – nonthermal | S42: =IF(AND(ISNUMBER(Q42),Q42>0,ISNUMBER(R42),R42>0),R42/Q42,"") | X42: =IF(ISNUMBER(S42),S42,IF(ISNUMBER(I42),I42,"")) | Y42: =IF(ISNUMBER(S42),"2025 EIA-923 plant/group proxy",IF(ISNUMBER(I42),"Technology estimate","No thermal heat rate")) -> No thermal heat rate | Z42: =IF(ISNUMBER(S42),"Review: NOT unit verified",IF(AE42="No match","No EIA match",IF(AF42="Unconfirmed","Unconfirmed EIA candidate",""))) | AE42: N/A (nonthermal) | AF42: No thermal fuel input | AG42: =IF(ISBLANK(S42),S42,I42) -> 0 | AH42: =AH41+B42 -> 1216.2 | AI42: =AH42*$AK$1 -> 759.4956 | AJ42: {=OR(D42=$AT$2:$AT$8)} -> FALSE | AL42: HE 15 | AM42: 84726 | AN42: =_xlfn.XLOOKUP(AM42,$AI:$AI,$AG:$AG,,-1) -> 10.3833 | AP42: =$AT$28 -> 10.5628 | AQ42: =$AT$29 -> 10.5 | AR42: =$AT$30 -> 7.4
... A51: LOCUST RIDGE 2 WF | B51: 10.3 | C51: PPL | D51: PPL | E51: Onshore Wind | F51: Wind | G51: Wind turbine | K51: Not applicable | L51: Not applicable: no thermal fuel input | M51: =IF(OR(B51="",I51=""),"",B51*I51) | N51: Not applicable – nonthermal | S51: =IF(AND(ISNUMBER(Q51),Q51>0,ISNUMBER(R51),R51>0),R51/Q51,"") | X51: =IF(ISNUMBER(S51),S51,IF(ISNUMBER(I51),I51,"")) | Y51: =IF(ISNUMBER(S51),"2025 EIA-923 plant/group proxy",IF(ISNUMBER(I51),"Technology estimate","No thermal heat rate")) -> No thermal heat rate | Z51: =IF(ISNUMBER(S51),"Review: NOT unit verified",IF(AE51="No match","No EIA match",IF(AF51="Unconfirmed","Unconfirmed EIA candidate",""))) | AE51: N/A (nonthermal) | AF51: No thermal fuel input | AG51: =IF(ISBLANK(S51),S51,I51) -> 0 | AH51: =AH50+B51 -> 1655.8 | AI51: =AH51*$AK$1 -> 1034.0181 | AJ51: {=OR(D51=$AT$2:$AT$8)} -> FALSE | AL51: HE 24 | AM51: 80370 | AN51: =_xlfn.XLOOKUP(AM51,$AI:$AI,$AG:$AG,,-1) -> 10.2551 | AP51: =$AT$28 -> 10.5628 | AQ51: =$AT$29 -> 10.5 | AR51: =$AT$30 -> 7.4
A52: LOCUST RIDGE WF | B52: 3 | C52: PPL | D52: PPL | E52: Onshore Wind | F52: Wind | G52: Wind turbine | K52: Not applicable | L52: Not applicable: no thermal fuel input | M52: =IF(OR(B52="",I52=""),"",B52*I52) | N52: Not applicable – nonthermal | S52: =IF(AND(ISNUMBER(Q52),Q52>0,ISNUMBER(R52),R52>0),R52/Q52,"") | X52: =IF(ISNUMBER(S52),S52,IF(ISNUMBER(I52),I52,"")) | Y52: =IF(ISNUMBER(S52),"2025 EIA-923 plant/group proxy",IF(ISNUMBER(I52),"Technology estimate","No thermal heat rate")) -> No thermal heat rate | Z52: =IF(ISNUMBER(S52),"Review: NOT unit verified",IF(AE52="No match","No EIA match",IF(AF52="Unconfirmed","Unconfirmed EIA candidate",""))) | AE52: N/A (nonthermal) | AF52: No thermal fuel input | AG52: =IF(ISBLANK(S52),S52,I52) -> 0 | AH52: =AH51+B52 -> 1658.8 | AI52: =AH52*$AK$1 -> 1035.8916 | AJ52: {=OR(D52=$AT$2:$AT$8)} -> FALSE
A53: LOGAN COUNTY WF | B53: 86.9 | C53: COMED | D53: COMED | E53: Onshore Wind | F53: Wind | G53: Wind turbine | K53: Not applicable | L53: Not applicable: no thermal fuel input | M53: =IF(OR(B53="",I53=""),"",B53*I53) | N53: Not applicable – nonthermal | S53: =IF(AND(ISNUMBER(Q53),Q53>0,ISNUMBER(R53),R53>0),R53/Q53,"") | X53: =IF(ISNUMBER(S53),S53,IF(ISNUMBER(I53),I53,"")) | Y53: =IF(ISNUMBER(S53),"2025 EIA-923 plant/group proxy",IF(ISNUMBER(I53),"Technology estimate","No thermal heat rate")) -> No thermal heat rate | Z53: =IF(ISNUMBER(S53),"Review: NOT unit verified",IF(AE53="No match","No EIA match",IF(AF53="Unconfirmed","Unconfirmed EIA candidate",""))) | AE53: N/A (nonthermal) | AF53: No thermal fuel input | AG53: =IF(ISBLANK(S53),S53,I53) -> 0 | AH53: =AH52+B53 -> 1745.7 | AI53: =AH53*$AK$1 -> 1090.1591 | AJ53: {=OR(D53=$AT$2:$AT$8)} -> FALSE
A54: LONE TREE WF | B54: 19 | C54: COMED | D54: COMED | E54: Onshore Wind | F54: Wind | G54: Wind turbine | K54: Not applicable | L54: Not applicable: no thermal fuel input | M54: =IF(OR(B54="",I54=""),"",B54*I54) | N54: Not applicable – nonthermal | S54: =IF(AND(ISNUMBER(Q54),Q54>0,ISNUMBER(R54),R54>0),R54/Q54,"") | X54: =IF(ISNUMBER(S54),S54,IF(ISNUMBER(I54),I54,"")) | Y54: =IF(ISNUMBER(S54),"2025 EIA-923 plant/group proxy",IF(ISNUMBER(I54),"Technology estimate","No thermal heat rate")) -> No thermal heat rate | Z54: =IF(ISNUMBER(S54),"Review: NOT unit verified",IF(AE54="No match","No EIA match",IF(AF54="Unconfirmed","Unconfirmed EIA candidate",""))) | AE54: N/A (nonthermal) | AF54: No thermal fuel input | AG54: =IF(ISBLANK(S54),S54,I54) -> 0 | AH54: =AH53+B54 -> 1764.7 | AI54: =AH54*$AK$1 -> 1102.0243 | AJ54: {=OR(D54=$AT$2:$AT$8)} -> FALSE
A55: LOOKOUT WF | B55: 12.9 | C55: PENELEC | D55: MAAC | E55: Onshore Wind | F55: Wind | G55: Wind turbine | K55: Not applicable | L55: Not applicable: no thermal fuel input | M55: =IF(OR(B55="",I55=""),"",B55*I55) | N55: Not applicable – nonthermal | S55: =IF(AND(ISNUMBER(Q55),Q55>0,ISNUMBER(R55),R55>0),R55/Q55,"") | X55: =IF(ISNUMBER(S55),S55,IF(ISNUMBER(I55),I55,"")) | Y55: =IF(ISNUMBER(S55),"2025 EIA-923 plant/group proxy",IF(ISNUMBER(I55),"Technology estimate","No thermal heat rate")) -> No thermal heat rate | Z55: =IF(ISNUMBER(S55),"Review: NOT unit verified",IF(AE55="No match","No EIA match",IF(AF55="Unconfirmed","Unconfirmed EIA candidate",""))) | AE55: N/A (nonthermal) | AF55: No thermal fuel input | AG55: =IF(ISBLANK(S55),S55,I55) -> 0 | AH55: =AH54+B55 -> 1777.6 | AI55: =AH55*$AK$1 -> 1110.0801 | AJ55: {=OR(D55=$AT$2:$AT$8)} -> FALSE
A56: MEADOW LAKE 2 WF | B56: 46.1 | C56: AEP | D56: RTO | E56: Onshore Wind | F56: Wind | G56: Wind turbine | K56: Not applicable | L56: Not applicable: no thermal fuel input | M56: =IF(OR(B56="",I56=""),"",B56*I56) | N56: Not applicable – nonthermal | S56: =IF(AND(ISNUMBER(Q56),Q56>0,ISNUMBER(R56),R56>0),R56/Q56,"") | X56: =IF(ISNUMBER(S56),S56,IF(ISNUMBER(I56),I56,"")) | Y56: =IF(ISNUMBER(S56),"2025 EIA-923 plant/group proxy",IF(ISNUMBER(I56),"Technology estimate","No thermal heat rate")) -> No thermal heat rate | Z56: =IF(ISNUMBER(S56),"Review: NOT unit verified",IF(AE56="No match","No EIA match",IF(AF56="Unconfirmed","Unconfirmed EIA candidate",""))) | AE56: N/A (nonthermal) | AF56: No thermal fuel input | AG56: =IF(ISBLANK(S56),S56,I56) -> 0 | AH56: =AH55+B56 -> 1823.7 | AI56: =AH56*$AK$1 -> 1138.8687 | AJ56: {=OR(D56=$AT$2:$AT$8)} -> FALSE
A57: MEADOW LAKE 3 WF | B57: 47.9 | C57: AEP | D57: RTO | E57: Onshore Wind | F57: Wind | G57: Wind turbine | K57: Not applicable | L57: Not applicable: no thermal fuel input | M57: =IF(OR(B57="",I57=""),"",B57*I57) | N57: Not applicable – nonthermal | S57: =IF(AND(ISNUMBER(Q57),Q57>0,ISNUMBER(R57),R57>0),R57/Q57,"") | X57: =IF(ISNUMBER(S57),S57,IF(ISNUMBER(I57),I57,"")) | Y57: =IF(ISNUMBER(S57),"2025 EIA-923 plant/group proxy",IF(ISNUMBER(I57),"Technology estimate","No thermal heat rate")) -> No thermal heat rate | Z57: =IF(ISNUMBER(S57),"Review: NOT unit verified",IF(AE57="No match","No EIA match",IF(AF57="Unconfirmed","Unconfirmed EIA candidate",""))) | AE57: N/A (nonthermal) | AF57: No thermal fuel input | AG57: =IF(ISBLANK(S57),S57,I57) -> 0 | AH57: =AH56+B57 -> 1871.6 | AI57: =AH57*$AK$1 -> 1168.7814 | AJ57: {=OR(D57=$AT$2:$AT$8)} -> FALSE
A58: MEADOW LAKE 4 WF | B58: 46.5 | C58: AEP | D58: RTO | E58: Onshore Wind | F58: Wind | G58: Wind turbine | K58: Not applicable | L58: Not applicable: no thermal fuel input | M58: =IF(OR(B58="",I58=""),"",B58*I58) | N58: Not applicable – nonthermal | S58: =IF(AND(ISNUMBER(Q58),Q58>0,ISNUMBER(R58),R58>0),R58/Q58,"") | X58: =IF(ISNUMBER(S58),S58,IF(ISNUMBER(I58),I58,"")) | Y58: =IF(ISNUMBER(S58),"2025 EIA-923 plant/group proxy",IF(ISNUMBER(I58),"Technology estimate","No thermal heat rate")) -> No thermal heat rate | Z58: =IF(ISNUMBER(S58),"Review: NOT unit verified",IF(AE58="No match","No EIA match",IF(AF58="Unconfirmed","Unconfirmed EIA candidate",""))) | AE58: N/A (nonthermal) | AF58: No thermal fuel input | AG58: =IF(ISBLANK(S58),S58,I58) -> 0 | AH58: =AH57+B58 -> 1918.1 | AI58: =AH58*$AK$1 -> 1197.8199 | AJ58: {=OR(D58=$AT$2:$AT$8)} -> FALSE
A59: MEADOW LAKE 5 WF | B59: 47.5 | C59: AEP | D59: RTO | E59: Onshore Wind | F59: Wind | G59: Wind turbine | K59: Not applicable | L59: Not applicable: no thermal fuel input | M59: =IF(OR(B59="",I59=""),"",B59*I59) | N59: Not applicable – nonthermal | S59: =IF(AND(ISNUMBER(Q59),Q59>0,ISNUMBER(R59),R59>0),R59/Q59,"") | X59: =IF(ISNUMBER(S59),S59,IF(ISNUMBER(I59),I59,"")) | Y59: =IF(ISNUMBER(S59),"2025 EIA-923 plant/group proxy",IF(ISNUMBER(I59),"Technology estimate","No thermal heat rate")) -> No thermal heat rate | Z59: =IF(ISNUMBER(S59),"Review: NOT unit verified",IF(AE59="No match","No EIA match",IF(AF59="Unconfirmed","Unconfirmed EIA candidate",""))) | AE59: N/A (nonthermal) | AF59: No thermal fuel input | AG59: =IF(ISBLANK(S59),S59,I59) -> 0 | AH59: =AH58+B59 -> 1965.6 | AI59: =AH59*$AK$1 -> 1227.4828 | AJ59: {=OR(D59=$AT$2:$AT$8)} -> FALSE
A60: MEADOW LAKE 6 WF | B60: 94 | C60: AEP | D60: RTO | E60: Onshore Wind | F60: Wind | G60: Wind turbine | K60: Not applicable | L60: Not applicable: no thermal fuel input | M60: =IF(OR(B60="",I60=""),"",B60*I60) | N60: Not applicable – nonthermal | S60: =IF(AND(ISNUMBER(Q60),Q60>0,ISNUMBER(R60),R60>0),R60/Q60,"") | X60: =IF(ISNUMBER(S60),S60,IF(ISNUMBER(I60),I60,"")) | Y60: =IF(ISNUMBER(S60),"2025 EIA-923 plant/group proxy",IF(ISNUMBER(I60),"Technology estimate","No thermal heat rate")) -> No thermal heat rate | Z60: =IF(ISNUMBER(S60),"Review: NOT unit verified",IF(AE60="No match","No EIA match",IF(AF60="Unconfirmed","Unconfirmed EIA candidate",""))) | AE60: N/A (nonthermal) | AF60: No thermal fuel input | AG60: =IF(ISBLANK(S60),S60,I60) -> 0 | AH60: =AH59+B60 -> 2059.6 | AI60: =AH60*$AK$1 -> 1286.1841 | AJ60: {=OR(D60=$AT$2:$AT$8)} -> FALSE
A61: MEADOW LAKE WF | B61: 94 | C61: AEP | D61: RTO | E61: Onshore Wind | F61: Wind | G61: Wind turbine | K61: Not applicable | L61: Not applicable: no thermal fuel input | M61: =IF(OR(B61="",I61=""),"",B61*I61) | N61: Not applicable – nonthermal | S61: =IF(AND(ISNUMBER(Q61),Q61>0,ISNUMBER(R61),R61>0),R61/Q61,"") | X61: =IF(ISNUMBER(S61),S61,IF(ISNUMBER(I61),I61,"")) | Y61: =IF(ISNUMBER(S61),"2025 EIA-923 plant/group proxy",IF(ISNUMBER(I61),"Technology estimate","No thermal heat rate")) -> No thermal heat rate | Z61: =IF(ISNUMBER(S61),"Review: NOT unit verified",IF(AE61="No match","No EIA match",IF(AF61="Unconfirmed","Unconfirmed EIA candidate",""))) | AE61: N/A (nonthermal) | AF61: No thermal fuel input | AG61: =IF(ISBLANK(S61),S61,I61) -> 0 | AH61: =AH60+B61 -> 2153.6 | AI61: =AH61*$AK$1 -> 1344.8855 | AJ61: {=OR(D61=$AT$2:$AT$8)} -> FALSE
A62: MEHOOPANY WF | B62: 21.9 | C62: PENELEC | D62: MAAC | E62: Onshore Wind | F62: Wind | G62: Wind turbine | K62: Not applicable | L62: Not applicable: no thermal fuel input | M62: =IF(OR(B62="",I62=""),"",B62*I62) | N62: Not applicable – nonthermal | S62: =IF(AND(ISNUMBER(Q62),Q62>0,ISNUMBER(R62),R62>0),R62/Q62,"") | X62: =IF(ISNUMBER(S62),S62,IF(ISNUMBER(I62),I62,"")) | Y62: =IF(ISNUMBER(S62),"2025 EIA-923 plant/group proxy",IF(ISNUMBER(I62),"Technology estimate","No thermal heat rate")) -> No thermal heat rate | Z62: =IF(ISNUMBER(S62),"Review: NOT unit verified",IF(AE62="No match","No EIA match",IF(AF62="Unconfirmed","Unconfirmed EIA candidate",""))) | AE62: N/A (nonthermal) | AF62: No thermal fuel input | AG62: =IF(ISBLANK(S62),S62,I62) -> 0 | AH62: =AH61+B62 -> 2175.5 | AI62: =AH62*$AK$1 -> 1358.5617 | AJ62: {=OR(D62=$AT$2:$AT$8)} -> FALSE
A63: MENDOTA HILLS WF | B63: 35.8 | C63: COMED | D63: COMED | E63: Onshore Wind | F63: Wind | G63: Wind turbine | K63: Not applicable | L63: Not applicable: no thermal fuel input | M63: =IF(OR(B63="",I63=""),"",B63*I63) | N63: Not applicable – nonthermal | S63: =IF(AND(ISNUMBER(Q63),Q63>0,ISNUMBER(R63),R63>0),R63/Q63,"") | X63: =IF(ISNUMBER(S63),S63,IF(ISNUMBER(I63),I63,"")) | Y63: =IF(ISNUMBER(S63),"2025 EIA-923 plant/group proxy",IF(ISNUMBER(I63),"Technology estimate","No thermal heat rate")) -> No thermal heat rate | Z63: =IF(ISNUMBER(S63),"Review: NOT unit verified",IF(AE63="No match","No EIA match",IF(AF63="Unconfirmed","Unconfirmed EIA candidate",""))) | AE63: N/A (nonthermal) | AF63: No thermal fuel input | AG63: =IF(ISBLANK(S63),S63,I63) -> 0 | AH63: =AH62+B63 -> 2211.3 | AI63: =AH63*$AK$1 -> 1380.9181 | AJ63: {=OR(D63=$AT$2:$AT$8)} -> FALSE
... A102: WILDCAT 1B WF | B102: 46.3 | C102: AEP | D102: RTO | E102: Onshore Wind | F102: Wind | G102: Wind turbine | K102: Not applicable | L102: Not applicable: no thermal fuel input | M102: =IF(OR(B102="",I102=""),"",B102*I102) | N102: Not applicable – nonthermal | S102: =IF(AND(ISNUMBER(Q102),Q102>0,ISNUMBER(R102),R102>0),R102/Q102,"") | X102: =IF(ISNUMBER(S102),S102,IF(ISNUMBER(I102),I102,"")) | Y102: =IF(ISNUMBER(S102),"2025 EIA-923 plant/group proxy",IF(ISNUMBER(I102),"Technology estimate","No thermal heat rate")) -> No thermal heat rate | Z102: =IF(ISNUMBER(S102),"Review: NOT unit verified",IF(AE102="No match","No EIA match",IF(AF102="Unconfirmed","Unconfirmed EIA candidate",""))) | AE102: N/A (nonthermal) | AF102: No thermal fuel input | AG102: =IF(ISBLANK(S102),S102,I102) -> 0 | AH102: =AH101+B102 -> 3476.3 | AI102: =AH102*$AK$1 -> 2170.8885 | AJ102: {=OR(D102=$AT$2:$AT$8)} -> FALSE
A103: MORGANTOWN CT 5 | B103: 54 | C103: PEPCO | D103: PEPCO | E103: Other Unlimited Resource | F103: Unknown | G103: Other / unspecified | K103: Needs classification | L103: Insufficient technology and fuel information | M103: =IF(OR(B103="",I103=""),"",B103*I103) | N103: No technically compatible EIA candidate | S103: =IF(AND(ISNUMBER(Q103),Q103>0,ISNUMBER(R103),R103>0),R103/Q103,"") | X103: =IF(ISNUMBER(S103),S103,IF(ISNUMBER(I103),I103,"")) | Y103: =IF(ISNUMBER(S103),"2025 EIA-923 plant/group proxy",IF(ISNUMBER(I103),"Technology estimate","No thermal heat rate")) -> No thermal heat rate | Z103: =IF(ISNUMBER(S103),"Review: NOT unit verified",IF(AE103="No match","No EIA match",IF(AF103="Unconfirmed","Unconfirmed EIA candidate",""))) -> No EIA match | AE103: No match | AG103: =IF(ISBLANK(S103),S103,I103) -> 0 | AH103: =AH102+B103 -> 3530.3 | AI103: =AH103*$AK$1 -> 2204.6105 | AJ103: {=OR(D103=$AT$2:$AT$8)} -> TRUE
A104: MORGANTOWN CT 6 | B104: 42.2 | C104: PEPCO | D104: PEPCO | E104: Other Unlimited Resource | F104: Unknown | G104: Other / unspecified | K104: Needs classification | L104: Insufficient technology and fuel information | M104: =IF(OR(B104="",I104=""),"",B104*I104) | N104: No technically compatible EIA candidate | S104: =IF(AND(ISNUMBER(Q104),Q104>0,ISNUMBER(R104),R104>0),R104/Q104,"") | X104: =IF(ISNUMBER(S104),S104,IF(ISNUMBER(I104),I104,"")) | Y104: =IF(ISNUMBER(S104),"2025 EIA-923 plant/group proxy",IF(ISNUMBER(I104),"Technology estimate","No thermal heat rate")) -> No thermal heat rate | Z104: =IF(ISNUMBER(S104),"Review: NOT unit verified",IF(AE104="No match","No EIA match",IF(AF104="Unconfirmed","Unconfirmed EIA candidate",""))) -> No EIA match | AE104: No match | AG104: =IF(ISBLANK(S104),S104,I104) -> 0 | AH104: =AH103+B104 -> 3572.5 | AI104: =AH104*$AK$1 -> 2230.9637 | AJ104: {=OR(D104=$AT$2:$AT$8)} -> TRUE
A105: ROSEMARY | B105: 154.7 | C105: DOM | D105: DOM | E105: Other Unlimited Resource | F105: Unknown | G105: Other / unspecified | K105: Needs classification | L105: Insufficient technology and fuel information | M105: =IF(OR(B105="",I105=""),"",B105*I105) | N105: No technically compatible EIA candidate | S105: =IF(AND(ISNUMBER(Q105),Q105>0,ISNUMBER(R105),R105>0),R105/Q105,"") | X105: =IF(ISNUMBER(S105),S105,IF(ISNUMBER(I105),I105,"")) | Y105: =IF(ISNUMBER(S105),"2025 EIA-923 plant/group proxy",IF(ISNUMBER(I105),"Technology estimate","No thermal heat rate")) -> No thermal heat rate | Z105: =IF(ISNUMBER(S105),"Review: NOT unit verified",IF(AE105="No match","No EIA match",IF(AF105="Unconfirmed","Unconfirmed EIA candidate",""))) -> No EIA match | AE105: No match | AG105: =IF(ISBLANK(S105),S105,I105) -> 0 | AH105: =AH104+B105 -> 3727.2 | AI105: =AH105*$AK$1 -> 2327.5711 | AJ105: {=OR(D105=$AT$2:$AT$8)} -> TRUE
A106: BAYSHORE 1 | B106: 136 | C106: ATSI | D106: ATSI | E106: Steam | F106: Unknown | G106: Unspecified steam | K106: Needs classification | L106: Cannot infer fuel from class; requires plant-level mapping | M106: =IF(OR(B106="",I106=""),"",B106*I106) | N106: No technically compatible EIA candidate | S106: =IF(AND(ISNUMBER(Q106),Q106>0,ISNUMBER(R106),R106>0),R106/Q106,"") | X106: =IF(ISNUMBER(S106),S106,IF(ISNUMBER(I106),I106,"")) | Y106: =IF(ISNUMBER(S106),"2025 EIA-923 plant/group proxy",IF(ISNUMBER(I106),"Technology estimate","No thermal heat rate")) -> No thermal heat rate | Z106: =IF(ISNUMBER(S106),"Review: NOT unit verified",IF(AE106="No match","No EIA match",IF(AF106="Unconfirmed","Unconfirmed EIA candidate",""))) -> No EIA match | AE106: No match | AG106: =IF(ISBLANK(S106),S106,I106) -> 0 | AH106: =AH105+B106 -> 3863.2 | AI106: =AH106*$AK$1 -> 2412.5008 | AJ106: {=OR(D106=$AT$2:$AT$8)} -> FALSE
A107: BRESCO NUG | B107: 50.3 | C107: BGE | D107: BGE | E107: Steam | F107: Unknown | G107: Unspecified steam | K107: Needs classification | L107: Cannot infer fuel from class; requires plant-level mapping | M107: =IF(OR(B107="",I107=""),"",B107*I107) | N107: No technically compatible EIA candidate | S107: =IF(AND(ISNUMBER(Q107),Q107>0,ISNUMBER(R107),R107>0),R107/Q107,"") | X107: =IF(ISNUMBER(S107),S107,IF(ISNUMBER(I107),I107,"")) | Y107: =IF(ISNUMBER(S107),"2025 EIA-923 plant/group proxy",IF(ISNUMBER(I107),"Technology estimate","No thermal heat rate")) -> No thermal heat rate | Z107: =IF(ISNUMBER(S107),"Review: NOT unit verified",IF(AE107="No match","No EIA match",IF(AF107="Unconfirmed","Unconfirmed EIA candidate",""))) -> No EIA match | AE107: No match | AG107: =IF(ISBLANK(S107),S107,I107) -> 0 | AH107: =AH106+B107 -> 3913.5 | AI107: =AH107*$AK$1 -> 2443.9122 | AJ107: {=OR(D107=$AT$2:$AT$8)} -> TRUE
A108: CAMDEN COUNTY R.R. NUG | B108: 23 | C108: PSEG | D108: PSEG | E108: Steam | F108: Unknown | G108: Unspecified steam | K108: Needs classification | L108: Cannot infer fuel from class; requires plant-level mapping | M108: =IF(OR(B108="",I108=""),"",B108*I108) | N108: Unconfirmed EIA candidate – keep technology estimate | S108: =IF(AND(ISNUMBER(Q108),Q108>0,ISNUMBER(R108),R108>0),R108/Q108,"") | W108: Candidate EIA plant 10435: Camden Resource Recovery Facility; name fit 0.421; unresolved alternatives. Do NOT treat as resource-specific data. | X108: =IF(ISNUMBER(S108),S108,IF(ISNUMBER(I108),I108,"")) | Y108: =IF(ISNUMBER(S108),"2025 EIA-923 plant/group proxy",IF(ISNUMBER(I108),"Technology estimate","No thermal heat rate")) -> No thermal heat rate | Z108: =IF(ISNUMBER(S108),"Review: NOT unit verified",IF(AE108="No match","No EIA match",IF(AF108="Unconfirmed","Unconfirmed EIA candidate",""))) -> Unconfirmed EIA candidate | AA108: 0.4208 | AB108: NJ | AD108: 0 | AE108: 2025 EIA data found, match unresolved | AF108: Unconfirmed | AG108: =IF(ISBLANK(S108),S108,I108) -> 0 | AH108: =AH107+B108 -> 3936.5 | AI108: =AH108*$AK$1 -> 2458.2753 | AJ108: {=OR(D108=$AT$2:$AT$8)} -> TRUE
A109: DELAWARE CITY 3 NUG | B109: 71.3 | C109: DPL | D109: EMAAC | E109: Steam | F109: Unknown | G109: Unspecified steam | K109: Needs classification | L109: Cannot infer fuel from class; requires plant-level mapping | M109: =IF(OR(B109="",I109=""),"",B109*I109) | N109: Unconfirmed EIA candidate – keep technology estimate | S109: =IF(AND(ISNUMBER(Q109),Q109>0,ISNUMBER(R109),R109>0),R109/Q109,"") | W109: Candidate EIA plant 997: Michigan City; name fit 0.392; unresolved alternatives. Do NOT treat as resource-specific data. | X109: =IF(ISNUMBER(S109),S109,IF(ISNUMBER(I109),I109,"")) | Y109: =IF(ISNUMBER(S109),"2025 EIA-923 plant/group proxy",IF(ISNUMBER(I109),"Technology estimate","No thermal heat rate")) -> No thermal heat rate | Z109: =IF(ISNUMBER(S109),"Review: NOT unit verified",IF(AE109="No match","No EIA match",IF(AF109="Unconfirmed","Unconfirmed EIA candidate",""))) -> Unconfirmed EIA candidate | AA109: 0.3923 | AB109: IN | AC109: 12 | AD109: 455 | AE109: 2025 EIA data found, match unresolved | AF109: Unconfirmed | AG109: =IF(ISBLANK(S109),S109,I109) -> 0 | AH109: =AH108+B109 -> 4007.8 | AI109: =AH109*$AK$1 -> 2502.8009 | AJ109: {=OR(D109=$AT$2:$AT$8)} -> FALSE
A110: DRMI NUG | B110: 75 | C110: PECO | D110: EMAAC | E110: Steam | F110: Unknown | G110: Unspecified steam | K110: Needs classification | L110: Cannot infer fuel from class; requires plant-level mapping | M110: =IF(OR(B110="",I110=""),"",B110*I110) | N110: No technically compatible EIA candidate | S110: =IF(AND(ISNUMBER(Q110),Q110>0,ISNUMBER(R110),R110>0),R110/Q110,"") | X110: =IF(ISNUMBER(S110),S110,IF(ISNUMBER(I110),I110,"")) | Y110: =IF(ISNUMBER(S110),"2025 EIA-923 plant/group proxy",IF(ISNUMBER(I110),"Technology estimate","No thermal heat rate")) -> No thermal heat rate | Z110: =IF(ISNUMBER(S110),"Review: NOT unit verified",IF(AE110="No match","No EIA match",IF(AF110="Unconfirmed","Unconfirmed EIA candidate",""))) -> No EIA match | AE110: No match | AG110: =IF(ISBLANK(S110),S110,I110) -> 0 | AH110: =AH109+B110 -> 4082.8 | AI110: =AH110*$AK$1 -> 2549.6371 | AJ110: {=OR(D110=$AT$2:$AT$8)} -> FALSE
A111: ESSEX CO. RES. RCRVRY 1 | B111: 28.4 | C111: PSEG | D111: PS-NORTH | E111: Steam | F111: Unknown | G111: Unspecified steam | K111: Needs classification | L111: Cannot infer fuel from class; requires plant-level mapping | M111: =IF(OR(B111="",I111=""),"",B111*I111) | N111: No technically compatible EIA candidate | S111: =IF(AND(ISNUMBER(Q111),Q111>0,ISNUMBER(R111),R111>0),R111/Q111,"") | X111: =IF(ISNUMBER(S111),S111,IF(ISNUMBER(I111),I111,"")) | Y111: =IF(ISNUMBER(S111),"2025 EIA-923 plant/group proxy",IF(ISNUMBER(I111),"Technology estimate","No thermal heat rate")) -> No thermal heat rate | Z111: =IF(ISNUMBER(S111),"Review: NOT unit verified",IF(AE111="No match","No EIA match",IF(AF111="Unconfirmed","Unconfirmed EIA candidate",""))) -> No EIA match | AE111: No match | AG111: =IF(ISBLANK(S111),S111,I111) -> 0 | AH111: =AH110+B111 -> 4111.2 | AI111: =AH111*$AK$1 -> 2567.3724 | AJ111: {=OR(D111=$AT$2:$AT$8)} -> FALSE
A112: ESSEX CO. RES. RCRVRY 2 | B112: 30.9 | C112: PSEG | D112: PS-NORTH | E112: Steam | F112: Unknown | G112: Unspecified steam | K112: Needs classification | L112: Cannot infer fuel from class; requires plant-level mapping | M112: =IF(OR(B112="",I112=""),"",B112*I112) | N112: No technically compatible EIA candidate | S112: =IF(AND(ISNUMBER(Q112),Q112>0,ISNUMBER(R112),R112>0),R112/Q112,"") | X112: =IF(ISNUMBER(S112),S112,IF(ISNUMBER(I112),I112,"")) | Y112: =IF(ISNUMBER(S112),"2025 EIA-923 plant/group proxy",IF(ISNUMBER(I112),"Technology estimate","No thermal heat rate")) -> No thermal heat rate | Z112: =IF(ISNUMBER(S112),"Review: NOT unit verified",IF(AE112="No match","No EIA match",IF(AF112="Unconfirmed","Unconfirmed EIA candidate",""))) -> No EIA match | AE112: No match | AG112: =IF(ISBLANK(S112),S112,I112) -> 0 | AH112: =AH111+B112 -> 4142.1 | AI112: =AH112*$AK$1 -> 2586.6689 | AJ112: {=OR(D112=$AT$2:$AT$8)} -> FALSE
A113: GLOUCESTER COUNTY NUG | B113: 11.1 | C113: PSEG | D113: PSEG | E113: Steam | F113: Unknown | G113: Unspecified steam | K113: Needs classification | L113: Cannot infer fuel from class; requires plant-level mapping | M113: =IF(OR(B113="",I113=""),"",B113*I113) | N113: Unconfirmed EIA candidate – keep technology estimate | S113: =IF(AND(ISNUMBER(Q113),Q113>0,ISNUMBER(R113),R113>0),R113/Q113,"") | W113: Candidate EIA plant 6071: Trimble County; name fit 0.401; insufficient name or inventory agreement. Do NOT treat as resource-specific data. | X113: =IF(ISNUMBER(S113),S113,IF(ISNUMBER(I113),I113,"")) | Y113: =IF(ISNUMBER(S113),"2025 EIA-923 plant/group proxy",IF(ISNUMBER(I113),"Technology estimate","No thermal heat rate")) -> No thermal heat rate | Z113: =IF(ISNUMBER(S113),"Review: NOT unit verified",IF(AE113="No match","No EIA match",IF(AF113="Unconfirmed","Unconfirmed EIA candidate",""))) -> Unconfirmed EIA candidate | AA113: 0.4009 | AB113: KY | AC113: 1, 2 | AD113: 1225 | AE113: 2025 EIA data found, match unresolved | AF113: Unconfirmed | AG113: =IF(ISBLANK(S113),S113,I113) -> 0 | AH113: =AH112+B113 -> 4153.2 | AI113: =AH113*$AK$1 -> 2593.6007 | AJ113: {=OR(D113=$AT$2:$AT$8)} -> TRUE
A114: HALL BRANCH | B114: 51 | C114: DOM | D114: DOM | E114: Steam | F114: Unknown | G114: Unspecified steam | K114: Needs classification | L114: Cannot infer fuel from class; requires plant-level mapping | M114: =IF(OR(B114="",I114=""),"",B114*I114) | N114: No technically compatible EIA candidate | S114: =IF(AND(ISNUMBER(Q114),Q114>0,ISNUMBER(R114),R114>0),R114/Q114,"") | X114: =IF(ISNUMBER(S114),S114,IF(ISNUMBER(I114),I114,"")) | Y114: =IF(ISNUMBER(S114),"2025 EIA-923 plant/group proxy",IF(ISNUMBER(I114),"Technology estimate","No thermal heat rate")) -> No thermal heat rate | Z114: =IF(ISNUMBER(S114),"Review: NOT unit verified",IF(AE114="No match","No EIA match",IF(AF114="Unconfirmed","Unconfirmed EIA candidate",""))) -> No EIA match | AE114: No match | AG114: =IF(ISBLANK(S114),S114,I114) -> 0 | AH114: =AH113+B114 -> 4204.2 | AI114: =AH114*$AK$1 -> 2625.4493 | AJ114: {=OR(D114=$AT$2:$AT$8)} -> TRUE
A115: HARRISBURG STEAM NUG | B115: 9 | C115: PPL | D115: PPL | E115: Steam | F115: Unknown | G115: Unspecified steam | K115: Needs classification | L115: Cannot infer fuel from class; requires plant-level mapping | M115: =IF(OR(B115="",I115=""),"",B115*I115) | N115: Unconfirmed EIA candidate – keep technology estimate | S115: =IF(AND(ISNUMBER(Q115),Q115>0,ISNUMBER(R115),R115>0),R115/Q115,"") | W115: Candidate EIA plant 10118: Harrisburg Facility; name fit 0.665; insufficient name or inventory agreement. Do NOT treat as resource-specific data. | X115: =IF(ISNUMBER(S115),S115,IF(ISNUMBER(I115),I115,"")) | Y115: =IF(ISNUMBER(S115),"2025 EIA-923 plant/group proxy",IF(ISNUMBER(I115),"Technology estimate","No thermal heat rate")) -> No thermal heat rate | Z115: =IF(ISNUMBER(S115),"Review: NOT unit verified",IF(AE115="No match","No EIA match",IF(AF115="Unconfirmed","Unconfirmed EIA candidate",""))) -> Unconfirmed EIA candidate | AA115: 0.665 | AB115: PA | AD115: 0 | AE115: 2025 EIA data found, match unresolved | AF115: Unconfirmed | AG115: =IF(ISBLANK(S115),S115,I115) -> 0 | AH115: =AH114+B115 -> 4213.2 | AI115: =AH115*$AK$1 -> 2631.0696 | AJ115: {=OR(D115=$AT$2:$AT$8)} -> FALSE
A116: IUP NUG | B116: 13 | C116: PENELEC | D116: MAAC | E116: Steam | F116: Unknown | G116: Unspecified steam | K116: Needs classification | L116: Cannot infer fuel from class; requires plant-level mapping | M116: =IF(OR(B116="",I116=""),"",B116*I116) | N116: No technically compatible EIA candidate | S116: =IF(AND(ISNUMBER(Q116),Q116>0,ISNUMBER(R116),R116>0),R116/Q116,"") | X116: =IF(ISNUMBER(S116),S116,IF(ISNUMBER(I116),I116,"")) | Y116: =IF(ISNUMBER(S116),"2025 EIA-923 plant/group proxy",IF(ISNUMBER(I116),"Technology estimate","No thermal heat rate")) -> No thermal heat rate | Z116: =IF(ISNUMBER(S116),"Review: NOT unit verified",IF(AE116="No match","No EIA match",IF(AF116="Unconfirmed","Unconfirmed EIA candidate",""))) -> No EIA match | AE116: No match | AG116: =IF(ISBLANK(S116),S116,I116) -> 0 | AH116: =AH115+B116 -> 4226.2 | AI116: =AH116*$AK$1 -> 2639.1879 | AJ116: {=OR(D116=$AT$2:$AT$8)} -> FALSE
A117: LANCASTER COUNTY NUG | B117: 25 | C117: METED | D117: MAAC | E117: Steam | F117: Unknown | G117: Unspecified steam | K117: Needs classification | L117: Cannot infer fuel from class; requires plant-level mapping | M117: =IF(OR(B117="",I117=""),"",B117*I117) | N117: Unconfirmed EIA candidate – keep technology estimate | S117: =IF(AND(ISNUMBER(Q117),Q117>0,ISNUMBER(R117),R117>0),R117/Q117,"") | W117: Candidate EIA plant 6071: Trimble County; name fit 0.404; insufficient name or inventory agreement. Do NOT treat as resource-specific data. | X117: =IF(ISNUMBER(S117),S117,IF(ISNUMBER(I117),I117,"")) | Y117: =IF(ISNUMBER(S117),"2025 EIA-923 plant/group proxy",IF(ISNUMBER(I117),"Technology estimate","No thermal heat rate")) -> No thermal heat rate | Z117: =IF(ISNUMBER(S117),"Review: NOT unit verified",IF(AE117="No match","No EIA match",IF(AF117="Unconfirmed","Unconfirmed EIA candidate",""))) -> Unconfirmed EIA candidate | AA117: 0.4036 | AB117: KY | AC117: 1, 2 | AD117: 1225 | AE117: 2025 EIA data found, match unresolved | AF117: Unconfirmed | AG117: =IF(ISBLANK(S117),S117,I117) -> 0 | AH117: =AH116+B117 -> 4251.2 | AI117: =AH117*$AK$1 -> 2654.8 | AJ117: {=OR(D117=$AT$2:$AT$8)} -> FALSE
A118: MCRRF | B118: 52 | C118: PEPCO | D118: PEPCO | E118: Steam | F118: Unknown | G118: Unspecified steam | K118: Needs classification | L118: Cannot infer fuel from class; requires plant-level mapping | M118: =IF(OR(B118="",I118=""),"",B118*I118) | N118: No technically compatible EIA candidate | S118: =IF(AND(ISNUMBER(Q118),Q118>0,ISNUMBER(R118),R118>0),R118/Q118,"") | X118: =IF(ISNUMBER(S118),S118,IF(ISNUMBER(I118),I118,"")) | Y118: =IF(ISNUMBER(S118),"2025 EIA-923 plant/group proxy",IF(ISNUMBER(I118),"Technology estimate","No thermal heat rate")) -> No thermal heat rate | Z118: =IF(ISNUMBER(S118),"Review: NOT unit verified",IF(AE118="No match","No EIA match",IF(AF118="Unconfirmed","Unconfirmed EIA candidate",""))) -> No EIA match | AE118: No match | AG118: =IF(ISBLANK(S118),S118,I118) -> 0 | AH118: =AH117+B118 -> 4303.2 | AI118: =AH118*$AK$1 -> 2687.2731 | AJ118: {=OR(D118=$AT$2:$AT$8)} -> TRUE
A119: MMLP | B119: 28 | C119: PECO | D119: EMAAC | E119: Steam | F119: Unknown | G119: Unspecified steam | K119: Needs classification | L119: Cannot infer fuel from class; requires plant-level mapping | M119: =IF(OR(B119="",I119=""),"",B119*I119) | N119: No technically compatible EIA candidate | S119: =IF(AND(ISNUMBER(Q119),Q119>0,ISNUMBER(R119),R119>0),R119/Q119,"") | X119: =IF(ISNUMBER(S119),S119,IF(ISNUMBER(I119),I119,"")) | Y119: =IF(ISNUMBER(S119),"2025 EIA-923 plant/group proxy",IF(ISNUMBER(I119),"Technology estimate","No thermal heat rate")) -> No thermal heat rate | Z119: =IF(ISNUMBER(S119),"Review: NOT unit verified",IF(AE119="No match","No EIA match",IF(AF119="Unconfirmed","Unconfirmed EIA candidate",""))) -> No EIA match | AE119: No match | AG119: =IF(ISBLANK(S119),S119,I119) -> 0 | AH119: =AH118+B119 -> 4331.2 | AI119: =AH119*$AK$1 -> 2704.7586 | AJ119: {=OR(D119=$AT$2:$AT$8)} -> FALSE
A120: OGDEN MARTIN | B120: 78.9 | C120: DOM | D120: DOM | E120: Steam | F120: Unknown | G120: Unspecified steam | K120: Needs classification | L120: Cannot infer fuel from class; requires plant-level mapping | M120: =IF(OR(B120="",I120=""),"",B120*I120) | N120: Unconfirmed EIA candidate – keep technology estimate | S120: =IF(AND(ISNUMBER(Q120),Q120>0,ISNUMBER(R120),R120>0),R120/Q120,"") | W120: Candidate EIA plant 3943: FirstEnergy Fort Martin Power Station; name fit 0.437; unresolved alternatives. Do NOT treat as resource-specific data. | X120: =IF(ISNUMBER(S120),S120,IF(ISNUMBER(I120),I120,"")) | Y120: =IF(ISNUMBER(S120),"2025 EIA-923 plant/group proxy",IF(ISNUMBER(I120),"Technology estimate","No thermal heat rate")) -> No thermal heat rate | Z120: =IF(ISNUMBER(S120),"Review: NOT unit verified",IF(AE120="No match","No EIA match",IF(AF120="Unconfirmed","Unconfirmed EIA candidate",""))) -> Unconfirmed EIA candidate | AA120: 0.4367 | AB120: WV | AC120: 1, 2 | AD120: 1098 | AE120: 2025 EIA data found, match unresolved | AF120: Unconfirmed | AG120: =IF(ISBLANK(S120),S120,I120) -> 0 | AH120: =AH119+B120 -> 4410.1 | AI120: =AH120*$AK$1 -> 2754.0302 | AJ120: {=OR(D120=$AT$2:$AT$8)} -> TRUE
A121: P.H. GLATFELTER NUG | B121: 35 | C121: METED | D121: MAAC | E121: Steam | F121: Unknown | G121: Unspecified steam | K121: Needs classification | L121: Cannot infer fuel from class; requires plant-level mapping | M121: =IF(OR(B121="",I121=""),"",B121*I121) | N121: No technically compatible EIA candidate | S121: =IF(AND(ISNUMBER(Q121),Q121>0,ISNUMBER(R121),R121>0),R121/Q121,"") | X121: =IF(ISNUMBER(S121),S121,IF(ISNUMBER(I121),I121,"")) | Y121: =IF(ISNUMBER(S121),"2025 EIA-923 plant/group proxy",IF(ISNUMBER(I121),"Technology estimate","No thermal heat rate")) -> No thermal heat rate | Z121: =IF(ISNUMBER(S121),"Review: NOT unit verified",IF(AE121="No match","No EIA match",IF(AF121="Unconfirmed","Unconfirmed EIA candidate",""))) -> No EIA match | AE121: No match | AG121: =IF(ISBLANK(S121),S121,I121) -> 0 | AH121: =AH120+B121 -> 4445.1 | AI121: =AH121*$AK$1 -> 2775.8871 | AJ121: {=OR(D121=$AT$2:$AT$8)} -> FALSE
A122: POLYESTER 1 | B122: 51 | C122: DOM | D122: DOM | E122: Steam | F122: Unknown | G122: Unspecified steam | K122: Needs classification | L122: Cannot infer fuel from class; requires plant-level mapping | M122: =IF(OR(B122="",I122=""),"",B122*I122) | N122: No technically compatible EIA candidate | S122: =IF(AND(ISNUMBER(Q122),Q122>0,ISNUMBER(R122),R122>0),R122/Q122,"") | X122: =IF(ISNUMBER(S122),S122,IF(ISNUMBER(I122),I122,"")) | Y122: =IF(ISNUMBER(S122),"2025 EIA-923 plant/group proxy",IF(ISNUMBER(I122),"Technology estimate","No thermal heat rate")) -> No thermal heat rate | Z122: =IF(ISNUMBER(S122),"Review: NOT unit verified",IF(AE122="No match","No EIA match",IF(AF122="Unconfirmed","Unconfirmed EIA candidate",""))) -> No EIA match | AE122: No match | AG122: =IF(ISBLANK(S122),S122,I122) -> 0 | AH122: =AH121+B122 -> 4496.1 | AI122: =AH122*$AK$1 -> 2807.7357 | AJ122: {=OR(D122=$AT$2:$AT$8)} -> TRUE
A123: REEDY CREEK | B123: 45.4 | C123: DOM | D123: DOM | E123: Steam | F123: Unknown | G123: Unspecified steam | K123: Needs classification | L123: Cannot infer fuel from class; requires plant-level mapping | M123: =IF(OR(B123="",I123=""),"",B123*I123) | N123: Unconfirmed EIA candidate – keep technology estimate | S123: =IF(AND(ISNUMBER(Q123),Q123>0,ISNUMBER(R123),R123>0),R123/Q123,"") | W123: Candidate EIA plant 2876: Kyger Creek; name fit 0.524; unresolved alternatives. Do NOT treat as resource-specific data. | X123: =IF(ISNUMBER(S123),S123,IF(ISNUMBER(I123),I123,"")) | Y123: =IF(ISNUMBER(S123),"2025 EIA-923 plant/group proxy",IF(ISNUMBER(I123),"Technology estimate","No thermal heat rate")) -> No thermal heat rate | Z123: =IF(ISNUMBER(S123),"Review: NOT unit verified",IF(AE123="No match","No EIA match",IF(AF123="Unconfirmed","Unconfirmed EIA candidate",""))) -> Unconfirmed EIA candidate | AA123: 0.5245 | AB123: OH | AC123: 1, 2, 3, 4, 5 | AD123: 962.8 | AE123: 2025 EIA data found, match unresolved | AF123: Unconfirmed | AG123: =IF(ISBLANK(S123),S123,I123) -> 0 | AH123: =AH122+B123 -> 4541.5 | AI123: =AH123*$AK$1 -> 2836.0872 | AJ123: {=OR(D123=$AT$2:$AT$8)} -> TRUE
A124: SOUTHHAMPTON 1 | B124: 51 | C124: DOM | D124: DOM | E124: Steam | F124: Unknown | G124: Unspecified steam | K124: Needs classification | L124: Cannot infer fuel from class; requires plant-level mapping | M124: =IF(OR(B124="",I124=""),"",B124*I124) | N124: No technically compatible EIA candidate | S124: =IF(AND(ISNUMBER(Q124),Q124>0,ISNUMBER(R124),R124>0),R124/Q124,"") | X124: =IF(ISNUMBER(S124),S124,IF(ISNUMBER(I124),I124,"")) | Y124: =IF(ISNUMBER(S124),"2025 EIA-923 plant/group proxy",IF(ISNUMBER(I124),"Technology estimate","No thermal heat rate")) -> No thermal heat rate | Z124: =IF(ISNUMBER(S124),"Review: NOT unit verified",IF(AE124="No match","No EIA match",IF(AF124="Unconfirmed","Unconfirmed EIA candidate",""))) -> No EIA match | AE124: No match | AG124: =IF(ISBLANK(S124),S124,I124) -> 0 | AH124: =AH123+B124 -> 4592.5 | AI124: =AH124*$AK$1 -> 2867.9358 | AJ124: {=OR(D124=$AT$2:$AT$8)} -> TRUE
A125: SPRUANCE 2 RICH 3-4 | B125: 11 | C125: DOM | D125: DOM | E125: Steam | F125: Unknown | G125: Unspecified steam | K125: Needs classification | L125: Cannot infer fuel from class; requires plant-level mapping | M125: =IF(OR(B125="",I125=""),"",B125*I125) | N125: Unconfirmed EIA candidate – keep technology estimate | S125: =IF(AND(ISNUMBER(Q125),Q125>0,ISNUMBER(R125),R125>0),R125/Q125,"") | W125: Candidate EIA plant 54081: Spruance Operating Services LLC; name fit 0.483; unresolved alternatives. Do NOT treat as resource-specific data. | X125: =IF(ISNUMBER(S125),S125,IF(ISNUMBER(I125),I125,"")) | Y125: =IF(ISNUMBER(S125),"2025 EIA-923 plant/group proxy",IF(ISNUMBER(I125),"Technology estimate","No thermal heat rate")) -> No thermal heat rate | Z125: =IF(ISNUMBER(S125),"Review: NOT unit verified",IF(AE125="No match","No EIA match",IF(AF125="Unconfirmed","Unconfirmed EIA candidate",""))) -> Unconfirmed EIA candidate | AA125: 0.483 | AB125: VA | AC125: GEN3, GEN4 | AD125: 55 | AE125: 2025 EIA data found, match unresolved | AF125: Unconfirmed | AG125: =IF(ISBLANK(S125),S125,I125) -> 0 | AH125: =AH124+B125 -> 4603.5 | AI125: =AH125*$AK$1 -> 2874.8051 | AJ125: {=OR(D125=$AT$2:$AT$8)} -> TRUE
A126: UNION COUNTY RES. RCRVRY | B126: 37.4 | C126: PSEG | D126: PS-NORTH | E126: Steam | F126: Unknown | G126: Unspecified steam | K126: Needs classification | L126: Cannot infer fuel from class; requires plant-level mapping | M126: =IF(OR(B126="",I126=""),"",B126*I126) | N126: No technically compatible EIA candidate | S126: =IF(AND(ISNUMBER(Q126),Q126>0,ISNUMBER(R126),R126>0),R126/Q126,"") | X126: =IF(ISNUMBER(S126),S126,IF(ISNUMBER(I126),I126,"")) | Y126: =IF(ISNUMBER(S126),"2025 EIA-923 plant/group proxy",IF(ISNUMBER(I126),"Technology estimate","No thermal heat rate")) -> No thermal heat rate | Z126: =IF(ISNUMBER(S126),"Review: NOT unit verified",IF(AE126="No match","No EIA match",IF(AF126="Unconfirmed","Unconfirmed EIA candidate",""))) -> No EIA match | AE126: No match | AG126: =IF(ISBLANK(S126),S126,I126) -> 0 | AH126: =AH125+B126 -> 4640.9 | AI126: =AH126*$AK$1 -> 2898.1608 | AJ126: {=OR(D126=$AT$2:$AT$8)} -> FALSE
A127: WHEELABRATOR FALLS | B127: 43 | C127: PSEG | D127: PSEG | E127: Steam | F127: Unknown | G127: Unspecified steam | K127: Needs classification | L127: Cannot infer fuel from class; requires plant-level mapping | M127: =IF(OR(B127="",I127=""),"",B127*I127) | N127: Unconfirmed EIA candidate – keep technology estimate | S127: =IF(AND(ISNUMBER(Q127),Q127>0,ISNUMBER(R127),R127>0),R127/Q127,"") | W127: Candidate EIA plant 10503: Wheelabrator Hudson Falls; name fit 0.901; insufficient name or inventory agreement. Do NOT treat as resource-specific data. | X127: =IF(ISNUMBER(S127),S127,IF(ISNUMBER(I127),I127,"")) | Y127: =IF(ISNUMBER(S127),"2025 EIA-923 plant/group proxy",IF(ISNUMBER(I127),"Technology estimate","No thermal heat rate")) -> No thermal heat rate | Z127: =IF(ISNUMBER(S127),"Review: NOT unit verified",IF(AE127="No match","No EIA match",IF(AF127="Unconfirmed","Unconfirmed EIA candidate",""))) -> Unconfirmed EIA candidate | AA127: 0.9007 | AB127: NY | AD127: 0 | AE127: 2025 EIA data found, match unresolved | AF127: Unconfirmed | AG127: =IF(ISBLANK(S127),S127,I127) -> 0 | AH127: =AH126+B127 -> 4683.9 | AI127: =AH127*$AK$1 -> 2925.0135 | AJ127: {=OR(D127=$AT$2:$AT$8)} -> TRUE
A128: YORK COUNTY NUG | B128: 30 | C128: METED | D128: MAAC | E128: Steam | F128: Unknown | G128: Unspecified steam | K128: Needs classification | L128: Cannot infer fuel from class; requires plant-level mapping | M128: =IF(OR(B128="",I128=""),"",B128*I128) | N128: Unconfirmed EIA candidate – keep technology estimate | S128: =IF(AND(ISNUMBER(Q128),Q128>0,ISNUMBER(R128),R128>0),R128/Q128,"") | W128: Candidate EIA plant 50215: York County Resource Recovery; name fit 0.670; insufficient name or inventory agreement. Do NOT treat as resource-specific data. | X128: =IF(ISNUMBER(S128),S128,IF(ISNUMBER(I128),I128,"")) | Y128: =IF(ISNUMBER(S128),"2025 EIA-923 plant/group proxy",IF(ISNUMBER(I128),"Technology estimate","No thermal heat rate")) -> No thermal heat rate | Z128: =IF(ISNUMBER(S128),"Review: NOT unit verified",IF(AE128="No match","No EIA match",IF(AF128="Unconfirmed","Unconfirmed EIA candidate",""))) -> Unconfirmed EIA candidate | AA128: 0.6701 | AB128: PA | AD128: 0 | AE128: 2025 EIA data found, match unresolved | AF128: Unconfirmed | AG128: =IF(ISBLANK(S128),S128,I128) -> 0 | AH128: =AH127+B128 -> 4713.9 | AI128: =AH128*$AK$1 -> 2943.748 | AJ128: {=OR(D128=$AT$2:$AT$8)} -> FALSE
A129: SCOTT HYBRID SOLAR | B129: 10 | C129: DOM | D129: DOM | E129: Hybrid CL - Solar Tracking | F129: Solar / hybrid | G129: Hybrid solar | K129: Not applicable | L129: Not applicable to solar portion; verify hybrid components | M129: =IF(OR(B129="",I129=""),"",B129*I129) | N129: Not applicable – nonthermal | S129: =IF(AND(ISNUMBER(Q129),Q129>0,ISNUMBER(R129),R129>0),R129/Q129,"") | X129: =IF(ISNUMBER(S129),S129,IF(ISNUMBER(I129),I129,"")) | Y129: =IF(ISNUMBER(S129),"2025 EIA-923 plant/group proxy",IF(ISNUMBER(I129),"Technology estimate","No thermal heat rate")) -> No thermal heat rate | Z129: =IF(ISNUMBER(S129),"Review: NOT unit verified",IF(AE129="No match","No EIA match",IF(AF129="Unconfirmed","Unconfirmed EIA candidate",""))) | AE129: N/A (nonthermal) | AF129: No thermal fuel input | AG129: =IF(ISBLANK(S129),S129,I129) -> 0 | AH129: =AH128+B129 -> 4723.9 | AI129: =AH129*$AK$1 -> 2949.9928 | AJ129: {=OR(D129=$AT$2:$AT$8)} -> TRUE
A130: ABSECON SOLAR | B130: 0.9 | C130: AECO | D130: EMAAC | E130: Solar Fixed | F130: Solar | G130: Solar PV | K130: Not applicable | L130: Not applicable: no thermal fuel input | M130: =IF(OR(B130="",I130=""),"",B130*I130) | N130: Not applicable – nonthermal | S130: =IF(AND(ISNUMBER(Q130),Q130>0,ISNUMBER(R130),R130>0),R130/Q130,"") | X130: =IF(ISNUMBER(S130),S130,IF(ISNUMBER(I130),I130,"")) | Y130: =IF(ISNUMBER(S130),"2025 EIA-923 plant/group proxy",IF(ISNUMBER(I130),"Technology estimate","No thermal heat rate")) -> No thermal heat rate | Z130: =IF(ISNUMBER(S130),"Review: NOT unit verified",IF(AE130="No match","No EIA match",IF(AF130="Unconfirmed","Unconfirmed EIA candidate",""))) | AE130: N/A (nonthermal) | AF130: No thermal fuel input | AG130: =IF(ISBLANK(S130),S130,I130) -> 0 | AH130: =AH129+B130 -> 4724.8 | AI130: =AH130*$AK$1 -> 2950.5549 | AJ130: {=OR(D130=$AT$2:$AT$8)} -> FALSE
A131: ARGONNE SOLAR | B131: 4.9 | C131: JCPL | D131: JCPL | E131: Solar Fixed | F131: Solar | G131: Solar PV | K131: Not applicable | L131: Not applicable: no thermal fuel input | M131: =IF(OR(B131="",I131=""),"",B131*I131) | N131: Not applicable – nonthermal | S131: =IF(AND(ISNUMBER(Q131),Q131>0,ISNUMBER(R131),R131>0),R131/Q131,"") | X131: =IF(ISNUMBER(S131),S131,IF(ISNUMBER(I131),I131,"")) | Y131: =IF(ISNUMBER(S131),"2025 EIA-923 plant/group proxy",IF(ISNUMBER(I131),"Technology estimate","No thermal heat rate")) -> No thermal heat rate | Z131: =IF(ISNUMBER(S131),"Review: NOT unit verified",IF(AE131="No match","No EIA match",IF(AF131="Unconfirmed","Unconfirmed EIA candidate",""))) | AE131: N/A (nonthermal) | AF131: No thermal fuel input | AG131: =IF(ISBLANK(S131),S131,I131) -> 0 | AH131: =AH130+B131 -> 4729.7 | AI131: =AH131*$AK$1 -> 2953.6148 | AJ131: {=OR(D131=$AT$2:$AT$8)} -> TRUE
A132: AXTON SOLAR | B132: 41.9 | C132: AEP | D132: RTO | E132: Solar Fixed | F132: Solar | G132: Solar PV | K132: Not applicable | L132: Not applicable: no thermal fuel input | M132: =IF(OR(B132="",I132=""),"",B132*I132) | N132: Not applicable – nonthermal | S132: =IF(AND(ISNUMBER(Q132),Q132>0,ISNUMBER(R132),R132>0),R132/Q132,"") | X132: =IF(ISNUMBER(S132),S132,IF(ISNUMBER(I132),I132,"")) | Y132: =IF(ISNUMBER(S132),"2025 EIA-923 plant/group proxy",IF(ISNUMBER(I132),"Technology estimate","No thermal heat rate")) -> No thermal heat rate | Z132: =IF(ISNUMBER(S132),"Review: NOT unit verified",IF(AE132="No match","No EIA match",IF(AF132="Unconfirmed","Unconfirmed EIA candidate",""))) | AE132: N/A (nonthermal) | AF132: No thermal fuel input | AG132: =IF(ISBLANK(S132),S132,I132) -> 0 | AH132: =AH131+B132 -> 4771.6 | AI132: =AH132*$AK$1 -> 2979.7807 | AJ132: {=OR(D132=$AT$2:$AT$8)} -> FALSE
A133: BAKER POINT SOLAR | B133: 4.4 | C133: APS | D133: RTO | E133: Solar Fixed | F133: Solar | G133: Solar PV | K133: Not applicable | L133: Not applicable: no thermal fuel input | M133: =IF(OR(B133="",I133=""),"",B133*I133) | N133: Not applicable – nonthermal | S133: =IF(AND(ISNUMBER(Q133),Q133>0,ISNUMBER(R133),R133>0),R133/Q133,"") | X133: =IF(ISNUMBER(S133),S133,IF(ISNUMBER(I133),I133,"")) | Y133: =IF(ISNUMBER(S133),"2025 EIA-923 plant/group proxy",IF(ISNUMBER(I133),"Technology estimate","No thermal heat rate")) -> No thermal heat rate | Z133: =IF(ISNUMBER(S133),"Review: NOT unit verified",IF(AE133="No match","No EIA match",IF(AF133="Unconfirmed","Unconfirmed EIA candidate",""))) | AE133: N/A (nonthermal) | AF133: No thermal fuel input | AG133: =IF(ISBLANK(S133),S133,I133) -> 0 | AH133: =AH132+B133 -> 4776 | AI133: =AH133*$AK$1 -> 2982.5284 | AJ133: {=OR(D133=$AT$2:$AT$8)} -> FALSE
A134: BE PINE SOLAR 1 | B134: 10.2 | C134: DUQ | D134: RTO | E134: Solar Fixed | F134: Solar | G134: Solar PV | K134: Not applicable | L134: Not applicable: no thermal fuel input | M134: =IF(OR(B134="",I134=""),"",B134*I134) | N134: Not applicable – nonthermal | S134: =IF(AND(ISNUMBER(Q134),Q134>0,ISNUMBER(R134),R134>0),R134/Q134,"") | X134: =IF(ISNUMBER(S134),S134,IF(ISNUMBER(I134),I134,"")) | Y134: =IF(ISNUMBER(S134),"2025 EIA-923 plant/group proxy",IF(ISNUMBER(I134),"Technology estimate","No thermal heat rate")) -> No thermal heat rate | Z134: =IF(ISNUMBER(S134),"Review: NOT unit verified",IF(AE134="No match","No EIA match",IF(AF134="Unconfirmed","Unconfirmed EIA candidate",""))) | AE134: N/A (nonthermal) | AF134: No thermal fuel input | AG134: =IF(ISBLANK(S134),S134,I134) -> 0 | AH134: =AH133+B134 -> 4786.2 | AI134: =AH134*$AK$1 -> 2988.8981 | AJ134: {=OR(D134=$AT$2:$AT$8)} -> FALSE
A135: BE PINE SOLAR 2 | B135: 10.2 | C135: DUQ | D135: RTO | E135: Solar Fixed | F135: Solar | G135: Solar PV | K135: Not applicable | L135: Not applicable: no thermal fuel input | M135: =IF(OR(B135="",I135=""),"",B135*I135) | N135: Not applicable – nonthermal | S135: =IF(AND(ISNUMBER(Q135),Q135>0,ISNUMBER(R135),R135>0),R135/Q135,"") | X135: =IF(ISNUMBER(S135),S135,IF(ISNUMBER(I135),I135,"")) | Y135: =IF(ISNUMBER(S135),"2025 EIA-923 plant/group proxy",IF(ISNUMBER(I135),"Technology estimate","No thermal heat rate")) -> No thermal heat rate | Z135: =IF(ISNUMBER(S135),"Review: NOT unit verified",IF(AE135="No match","No EIA match",IF(AF135="Unconfirmed","Unconfirmed EIA candidate",""))) | AE135: N/A (nonthermal) | AF135: No thermal fuel input | AG135: =IF(ISBLANK(S135),S135,I135) -> 0 | AH135: =AH134+B135 -> 4796.4 | AI135: =AH135*$AK$1 -> 2995.2678 | AJ135: {=OR(D135=$AT$2:$AT$8)} -> FALSE
A136: BEAVER RUN SOLAR | B136: 3.2 | C136: JCPL | D136: JCPL | E136: Solar Fixed | F136: Solar | G136: Solar PV | K136: Not applicable | L136: Not applicable: no thermal fuel input | M136: =IF(OR(B136="",I136=""),"",B136*I136) | N136: Not applicable – nonthermal | S136: =IF(AND(ISNUMBER(Q136),Q136>0,ISNUMBER(R136),R136>0),R136/Q136,"") | X136: =IF(ISNUMBER(S136),S136,IF(ISNUMBER(I136),I136,"")) | Y136: =IF(ISNUMBER(S136),"2025 EIA-923 plant/group proxy",IF(ISNUMBER(I136),"Technology estimate","No thermal heat rate")) -> No thermal heat rate | Z136: =IF(ISNUMBER(S136),"Review: NOT unit verified",IF(AE136="No match","No EIA match",IF(AF136="Unconfirmed","Unconfirmed EIA candidate",""))) | AE136: N/A (nonthermal) | AF136: No thermal fuel input | AG136: =IF(ISBLANK(S136),S136,I136) -> 0 | AH136: =AH135+B136 -> 4799.6 | AI136: =AH136*$AK$1 -> 2997.2662 | AJ136: {=OR(D136=$AT$2:$AT$8)} -> TRUE
A137: BEAVERBROOK KINSLEY SOLAR | B137: 1.4 | C137: PSEG | D137: PSEG | E137: Solar Fixed | F137: Solar | G137: Solar PV | K137: Not applicable | L137: Not applicable: no thermal fuel input | M137: =IF(OR(B137="",I137=""),"",B137*I137) | N137: Not applicable – nonthermal | S137: =IF(AND(ISNUMBER(Q137),Q137>0,ISNUMBER(R137),R137>0),R137/Q137,"") | X137: =IF(ISNUMBER(S137),S137,IF(ISNUMBER(I137),I137,"")) | Y137: =IF(ISNUMBER(S137),"2025 EIA-923 plant/group proxy",IF(ISNUMBER(I137),"Technology estimate","No thermal heat rate")) -> No thermal heat rate | Z137: =IF(ISNUMBER(S137),"Review: NOT unit verified",IF(AE137="No match","No EIA match",IF(AF137="Unconfirmed","Unconfirmed EIA candidate",""))) | AE137: N/A (nonthermal) | AF137: No thermal fuel input | AG137: =IF(ISBLANK(S137),S137,I137) -> 0 | AH137: =AH136+B137 -> 4801 | AI137: =AH137*$AK$1 -> 2998.1404 | AJ137: {=OR(D137=$AT$2:$AT$8)} -> TRUE
A138: BELVIDERE SOLAR | B138: 0.8 | C138: JCPL | D138: JCPL | E138: Solar Fixed | F138: Solar | G138: Solar PV | K138: Not applicable | L138: Not applicable: no thermal fuel input | M138: =IF(OR(B138="",I138=""),"",B138*I138) | N138: Not applicable – nonthermal | S138: =IF(AND(ISNUMBER(Q138),Q138>0,ISNUMBER(R138),R138>0),R138/Q138,"") | X138: =IF(ISNUMBER(S138),S138,IF(ISNUMBER(I138),I138,"")) | Y138: =IF(ISNUMBER(S138),"2025 EIA-923 plant/group proxy",IF(ISNUMBER(I138),"Technology estimate","No thermal heat rate")) -> No thermal heat rate | Z138: =IF(ISNUMBER(S138),"Review: NOT unit verified",IF(AE138="No match","No EIA match",IF(AF138="Unconfirmed","Unconfirmed EIA candidate",""))) | AE138: N/A (nonthermal) | AF138: No thermal fuel input | AG138: =IF(ISBLANK(S138),S138,I138) -> 0 | AH138: =AH137+B138 -> 4801.8 | AI138: =AH138*$AK$1 -> 2998.64 | AJ138: {=OR(D138=$AT$2:$AT$8)} -> TRUE
A139: BERNARDSVILLE SOLAR | B139: 1.1 | C139: JCPL | D139: JCPL | E139: Solar Fixed | F139: Solar | G139: Solar PV | K139: Not applicable | L139: Not applicable: no thermal fuel input | M139: =IF(OR(B139="",I139=""),"",B139*I139) | N139: Not applicable – nonthermal | S139: =IF(AND(ISNUMBER(Q139),Q139>0,ISNUMBER(R139),R139>0),R139/Q139,"") | X139: =IF(ISNUMBER(S139),S139,IF(ISNUMBER(I139),I139,"")) | Y139: =IF(ISNUMBER(S139),"2025 EIA-923 plant/group proxy",IF(ISNUMBER(I139),"Technology estimate","No thermal heat rate")) -> No thermal heat rate | Z139: =IF(ISNUMBER(S139),"Review: NOT unit verified",IF(AE139="No match","No EIA match",IF(AF139="Unconfirmed","Unconfirmed EIA candidate",""))) | AE139: N/A (nonthermal) | AF139: No thermal fuel input | AG139: =IF(ISBLANK(S139),S139,I139) -> 0 | AH139: =AH138+B139 -> 4802.9 | AI139: =AH139*$AK$1 -> 2999.327 | AJ139: {=OR(D139=$AT$2:$AT$8)} -> TRUE
A140: BIGGS FORD SOLAR | B140: 5.7 | C140: APS | D140: RTO | E140: Solar Fixed | F140: Solar | G140: Solar PV | K140: Not applicable | L140: Not applicable: no thermal fuel input | M140: =IF(OR(B140="",I140=""),"",B140*I140) | N140: Not applicable – nonthermal | S140: =IF(AND(ISNUMBER(Q140),Q140>0,ISNUMBER(R140),R140>0),R140/Q140,"") | X140: =IF(ISNUMBER(S140),S140,IF(ISNUMBER(I140),I140,"")) | Y140: =IF(ISNUMBER(S140),"2025 EIA-923 plant/group proxy",IF(ISNUMBER(I140),"Technology estimate","No thermal heat rate")) -> No thermal heat rate | Z140: =IF(ISNUMBER(S140),"Review: NOT unit verified",IF(AE140="No match","No EIA match",IF(AF140="Unconfirmed","Unconfirmed EIA candidate",""))) | AE140: N/A (nonthermal) | AF140: No thermal fuel input | AG140: =IF(ISBLANK(S140),S140,I140) -> 0 | AH140: =AH139+B140 -> 4808.6 | AI140: =AH140*$AK$1 -> 3002.8865 | AJ140: {=OR(D140=$AT$2:$AT$8)} -> FALSE
... A446: YELLOWBUD SOLAR | B446: 178.7 | C446: AEP | D446: RTO | E446: Solar Tracking | F446: Solar | G446: Solar PV | K446: Not applicable | L446: Not applicable: no thermal fuel input | M446: =IF(OR(B446="",I446=""),"",B446*I446) | N446: Not applicable – nonthermal | S446: =IF(AND(ISNUMBER(Q446),Q446>0,ISNUMBER(R446),R446>0),R446/Q446,"") | X446: =IF(ISNUMBER(S446),S446,IF(ISNUMBER(I446),I446,"")) | Y446: =IF(ISNUMBER(S446),"2025 EIA-923 plant/group proxy",IF(ISNUMBER(I446),"Technology estimate","No thermal heat rate")) -> No thermal heat rate | Z446: =IF(ISNUMBER(S446),"Review: NOT unit verified",IF(AE446="No match","No EIA match",IF(AF446="Unconfirmed","Unconfirmed EIA candidate",""))) | AE446: N/A (nonthermal) | AF446: No thermal fuel input | AG446: =IF(ISBLANK(S446),S446,I446) -> 0 | AH446: =AH445+B446 -> 13380.1 | AI446: =AH446*$AK$1 -> 8355.6382 | AJ446: {=OR(D446=$AT$2:$AT$8)} -> FALSE
A447: BEAVER VALLEY 1 INT | B447: 898.5 | C447: DUQ | D447: RTO | E447: Nuclear | F447: Nuclear heat | G447: Nuclear steam | H447: 0 | I447: 0 | J447: 0 | K447: Estimated | L447: Thermal equivalent only; not a fossil-fuel cost heat rate | M447: =IF(OR(B447="",I447=""),"",B447*I447) -> 0 | N447: No technically compatible EIA candidate | S447: =IF(AND(ISNUMBER(Q447),Q447>0,ISNUMBER(R447),R447>0),R447/Q447,"") | X447: =IF(ISNUMBER(S447),S447,IF(ISNUMBER(I447),I447,"")) -> 0 | Y447: =IF(ISNUMBER(S447),"2025 EIA-923 plant/group proxy",IF(ISNUMBER(I447),"Technology estimate","No thermal heat rate")) -> Technology estimate | Z447: =IF(ISNUMBER(S447),"Review: NOT unit verified",IF(AE447="No match","No EIA match",IF(AF447="Unconfirmed","Unconfirmed EIA candidate",""))) -> No EIA match | AE447: No match | AG447: =IF(ISBLANK(S447),S447,I447) -> 0 | AH447: =AH446+B447 -> 14278.6 | AI447: =AH447*$AK$1 -> 8916.7357 | AJ447: {=OR(D447=$AT$2:$AT$8)} -> FALSE
A448: BEAVER VALLEY 2 INT | B448: 892 | C448: DUQ | D448: RTO | E448: Nuclear | F448: Nuclear heat | G448: Nuclear steam | H448: 0 | I448: 0 | J448: 0 | K448: Estimated | L448: Thermal equivalent only; not a fossil-fuel cost heat rate | M448: =IF(OR(B448="",I448=""),"",B448*I448) -> 0 | N448: No technically compatible EIA candidate | S448: =IF(AND(ISNUMBER(Q448),Q448>0,ISNUMBER(R448),R448>0),R448/Q448,"") | X448: =IF(ISNUMBER(S448),S448,IF(ISNUMBER(I448),I448,"")) -> 0 | Y448: =IF(ISNUMBER(S448),"2025 EIA-923 plant/group proxy",IF(ISNUMBER(I448),"Technology estimate","No thermal heat rate")) -> Technology estimate | Z448: =IF(ISNUMBER(S448),"Review: NOT unit verified",IF(AE448="No match","No EIA match",IF(AF448="Unconfirmed","Unconfirmed EIA candidate",""))) -> No EIA match | AE448: No match | AG448: =IF(ISBLANK(S448),S448,I448) -> 0 | AH448: =AH447+B448 -> 15170.6 | AI448: =AH448*$AK$1 -> 9473.7741 | AJ448: {=OR(D448=$AT$2:$AT$8)} -> FALSE
A449: BRAIDWOOD NUCLEAR 1 | B449: 1183 | C449: COMED | D449: COMED | E449: Nuclear | F449: Nuclear heat | G449: Nuclear steam | H449: 0 | I449: 0 | J449: 0 | K449: Estimated | L449: Thermal equivalent only; not a fossil-fuel cost heat rate | M449: =IF(OR(B449="",I449=""),"",B449*I449) -> 0 | N449: No technically compatible EIA candidate | S449: =IF(AND(ISNUMBER(Q449),Q449>0,ISNUMBER(R449),R449>0),R449/Q449,"") | X449: =IF(ISNUMBER(S449),S449,IF(ISNUMBER(I449),I449,"")) -> 0 | Y449: =IF(ISNUMBER(S449),"2025 EIA-923 plant/group proxy",IF(ISNUMBER(I449),"Technology estimate","No thermal heat rate")) -> Technology estimate | Z449: =IF(ISNUMBER(S449),"Review: NOT unit verified",IF(AE449="No match","No EIA match",IF(AF449="Unconfirmed","Unconfirmed EIA candidate",""))) -> No EIA match | AE449: No match | AG449: =IF(ISBLANK(S449),S449,I449) -> 0 | AH449: =AH448+B449 -> 16353.6 | AI449: =AH449*$AK$1 -> 10212.537 | AJ449: {=OR(D449=$AT$2:$AT$8)} -> FALSE
A450: BRAIDWOOD NUCLEAR 2 | B450: 1149.3 | C450: COMED | D450: COMED | E450: Nuclear | F450: Nuclear heat | G450: Nuclear steam | H450: 0 | I450: 0 | J450: 0 | K450: Estimated | L450: Thermal equivalent only; not a fossil-fuel cost heat rate | M450: =IF(OR(B450="",I450=""),"",B450*I450) -> 0 | N450: No technically compatible EIA candidate | S450: =IF(AND(ISNUMBER(Q450),Q450>0,ISNUMBER(R450),R450>0),R450/Q450,"") | X450: =IF(ISNUMBER(S450),S450,IF(ISNUMBER(I450),I450,"")) -> 0 | Y450: =IF(ISNUMBER(S450),"2025 EIA-923 plant/group proxy",IF(ISNUMBER(I450),"Technology estimate","No thermal heat rate")) -> Technology estimate | Z450: =IF(ISNUMBER(S450),"Review: NOT unit verified",IF(AE450="No match","No EIA match",IF(AF450="Unconfirmed","Unconfirmed EIA candidate",""))) -> No EIA match | AE450: No match | AG450: =IF(ISBLANK(S450),S450,I450) -> 0 | AH450: =AH449+B450 -> 17502.9 | AI450: =AH450*$AK$1 -> 10930.255 | AJ450: {=OR(D450=$AT$2:$AT$8)} -> FALSE
A451: BYRON NUCLEAR 1 | B451: 1164 | C451: COMED | D451: COMED | E451: Nuclear | F451: Nuclear heat | G451: Nuclear steam | H451: 0 | I451: 0 | J451: 0 | K451: Estimated | L451: Thermal equivalent only; not a fossil-fuel cost heat rate | M451: =IF(OR(B451="",I451=""),"",B451*I451) -> 0 | N451: No technically compatible EIA candidate | S451: =IF(AND(ISNUMBER(Q451),Q451>0,ISNUMBER(R451),R451>0),R451/Q451,"") | X451: =IF(ISNUMBER(S451),S451,IF(ISNUMBER(I451),I451,"")) -> 0 | Y451: =IF(ISNUMBER(S451),"2025 EIA-923 plant/group proxy",IF(ISNUMBER(I451),"Technology estimate","No thermal heat rate")) -> Technology estimate | Z451: =IF(ISNUMBER(S451),"Review: NOT unit verified",IF(AE451="No match","No EIA match",IF(AF451="Unconfirmed","Unconfirmed EIA candidate",""))) -> No EIA match | AE451: No match | AG451: =IF(ISBLANK(S451),S451,I451) -> 0 | AH451: =AH450+B451 -> 18666.9 | AI451: =AH451*$AK$1 -> 11657.152 | AJ451: {=OR(D451=$AT$2:$AT$8)} -> FALSE
A452: BYRON NUCLEAR 2 | B452: 1136 | C452: COMED | D452: COMED | E452: Nuclear | F452: Nuclear heat | G452: Nuclear steam | H452: 0 | I452: 0 | J452: 0 | K452: Estimated | L452: Thermal equivalent only; not a fossil-fuel cost heat rate | M452: =IF(OR(B452="",I452=""),"",B452*I452) -> 0 | N452: No technically compatible EIA candidate | S452: =IF(AND(ISNUMBER(Q452),Q452>0,ISNUMBER(R452),R452>0),R452/Q452,"") | X452: =IF(ISNUMBER(S452),S452,IF(ISNUMBER(I452),I452,"")) -> 0 | Y452: =IF(ISNUMBER(S452),"2025 EIA-923 plant/group proxy",IF(ISNUMBER(I452),"Technology estimate","No thermal heat rate")) -> Technology estimate | Z452: =IF(ISNUMBER(S452),"Review: NOT unit verified",IF(AE452="No match","No EIA match",IF(AF452="Unconfirmed","Unconfirmed EIA candidate",""))) -> No EIA match | AE452: No match | AG452: =IF(ISBLANK(S452),S452,I452) -> 0 | AH452: =AH451+B452 -> 19802.9 | AI452: =AH452*$AK$1 -> 12366.564 | AJ452: {=OR(D452=$AT$2:$AT$8)} -> FALSE
A453: CALVERT CLIFFS 1 | B453: 884.2 | C453: BGE | D453: SWMAAC | E453: Nuclear | F453: Nuclear heat | G453: Nuclear steam | H453: 0 | I453: 0 | J453: 0 | K453: Estimated | L453: Thermal equivalent only; not a fossil-fuel cost heat rate | M453: =IF(OR(B453="",I453=""),"",B453*I453) -> 0 | N453: No technically compatible EIA candidate | S453: =IF(AND(ISNUMBER(Q453),Q453>0,ISNUMBER(R453),R453>0),R453/Q453,"") | X453: =IF(ISNUMBER(S453),S453,IF(ISNUMBER(I453),I453,"")) -> 0 | Y453: =IF(ISNUMBER(S453),"2025 EIA-923 plant/group proxy",IF(ISNUMBER(I453),"Technology estimate","No thermal heat rate")) -> Technology estimate | Z453: =IF(ISNUMBER(S453),"Review: NOT unit verified",IF(AE453="No match","No EIA match",IF(AF453="Unconfirmed","Unconfirmed EIA candidate",""))) -> No EIA match | AE453: No match | AG453: =IF(ISBLANK(S453),S453,I453) -> 0 | AH453: =AH452+B453 -> 20687.1 | AI453: =AH453*$AK$1 -> 12918.732 | AJ453: {=OR(D453=$AT$2:$AT$8)} -> FALSE
A454: CALVERT CLIFFS 2 | B454: 861 | C454: BGE | D454: SWMAAC | E454: Nuclear | F454: Nuclear heat | G454: Nuclear steam | H454: 0 | I454: 0 | J454: 0 | K454: Estimated | L454: Thermal equivalent only; not a fossil-fuel cost heat rate | M454: =IF(OR(B454="",I454=""),"",B454*I454) -> 0 | N454: No technically compatible EIA candidate | S454: =IF(AND(ISNUMBER(Q454),Q454>0,ISNUMBER(R454),R454>0),R454/Q454,"") | X454: =IF(ISNUMBER(S454),S454,IF(ISNUMBER(I454),I454,"")) -> 0 | Y454: =IF(ISNUMBER(S454),"2025 EIA-923 plant/group proxy",IF(ISNUMBER(I454),"Technology estimate","No thermal heat rate")) -> Technology estimate | Z454: =IF(ISNUMBER(S454),"Review: NOT unit verified",IF(AE454="No match","No EIA match",IF(AF454="Unconfirmed","Unconfirmed EIA candidate",""))) -> No EIA match | AE454: No match | AG454: =IF(ISBLANK(S454),S454,I454) -> 0 | AH454: =AH453+B454 -> 21548.1 | AI454: =AH454*$AK$1 -> 13456.411 | AJ454: {=OR(D454=$AT$2:$AT$8)} -> FALSE
A455: COOK NUCLEAR 1 | B455: 1014 | C455: AEP | D455: RTO | E455: Nuclear | F455: Nuclear heat | G455: Nuclear steam | H455: 0 | I455: 0 | J455: 0 | K455: Estimated | L455: Thermal equivalent only; not a fossil-fuel cost heat rate | M455: =IF(OR(B455="",I455=""),"",B455*I455) -> 0 | N455: No technically compatible EIA candidate | S455: =IF(AND(ISNUMBER(Q455),Q455>0,ISNUMBER(R455),R455>0),R455/Q455,"") | X455: =IF(ISNUMBER(S455),S455,IF(ISNUMBER(I455),I455,"")) -> 0 | Y455: =IF(ISNUMBER(S455),"2025 EIA-923 plant/group proxy",IF(ISNUMBER(I455),"Technology estimate","No thermal heat rate")) -> Technology estimate | Z455: =IF(ISNUMBER(S455),"Review: NOT unit verified",IF(AE455="No match","No EIA match",IF(AF455="Unconfirmed","Unconfirmed EIA candidate",""))) -> No EIA match | AE455: No match | AG455: =IF(ISBLANK(S455),S455,I455) -> 0 | AH455: =AH454+B455 -> 22562.1 | AI455: =AH455*$AK$1 -> 14089.636 | AJ455: {=OR(D455=$AT$2:$AT$8)} -> FALSE
...

Sheet Class Assumptions
A1: PJM Class | B1: Assumed Fuel | C1: Technology | D1: Low HR | E1: Base HR | F1: High HR | G1: Notes
A2: 10-hr Storage | B2: Electricity | C2: Battery/storage | G2: Not applicable: use round-trip efficiency instead
A3: 4-hr Storage | B3: Electricity | C3: Battery/storage | G3: Not applicable: use round-trip efficiency instead
A4: 6-hr Storage | B4: Electricity | C4: Battery/storage | G4: Not applicable: use round-trip efficiency instead
A5: 8-hr Storage | B5: Electricity | C5: Battery/storage | G5: Not applicable: use round-trip efficiency instead
A6: Coal | B6: Coal | C6: Coal steam | D6: 9 | E6: 10.3 | F6: 12 | G6: Representative full-load net HHV
A7: Diesel Utility | B7: Distillate diesel (assumed) | C7: Diesel engine / oil-fired | D7: 8 | E7: 9.5 | F7: 12 | G7: Technology may vary; verify fuel and engine type
A8: Gas Combined Cycle | B8: Natural gas | C8: Combined cycle | D8: 6.5 | E8: 7.2 | F8: 8.2 | G8: Representative full-load net HHV
A9: Gas Combined Cycle Dual | B9: Natural gas (assumed) | C9: Combined cycle dual fuel | D9: 6.6 | E9: 7.4 | F9: 8.5 | G9: Gas firing assumed; oil operation may differ
A10: Gas Combustion Turbine | B10: Natural gas | C10: Simple-cycle turbine | D10: 9 | E10: 10.5 | F10: 13 | G10: Representative full-load net HHV
A11: Gas Combustion Turbine Dual | B11: Natural gas (assumed) | C11: Simple-cycle dual fuel | D11: 9.2 | E11: 10.8 | F11: 13.5 | G11: Gas firing assumed; oil operation may differ
A12: Hybrid CL - Solar Tracking | B12: Solar / hybrid | C12: Hybrid solar | G12: Not applicable to solar portion; verify hybrid components
A13: Hydro Intermittent | B13: Hydro | C13: Hydroelectric | G13: Not applicable: no thermal fuel input
A14: HydroNPS | B14: Hydro | C14: Hydroelectric | G14: Not applicable: no thermal fuel input
A15: Landfill Intermittent | B15: Landfill gas (assumed) | C15: Landfill gas | D15: 9 | E15: 12 | F15: 16 | G15: High uncertainty; may be reciprocating engine or turbine
A16: Nuclear | B16: Nuclear heat | C16: Nuclear steam | D16: 10 | E16: 10.5 | F16: 11.2 | G16: Thermal equivalent only; not a fossil-fuel cost heat rate
A17: Offshore Wind | B17: Wind | C17: Wind turbine | G17: Not applicable: no thermal fuel input
A18: Onshore Wind | B18: Wind | C18: Wind turbine | G18: Not applicable: no thermal fuel input
A19: Other | B19: Unknown | C19: Other / unspecified | G19: Insufficient technology and fuel information
A20: Other Unlimited Resource | B20: Unknown | C20: Other / unspecified | G20: Insufficient technology and fuel information
A21: Solar Fixed | B21: Solar | C21: Solar PV | G21: Not applicable: no thermal fuel input
A22: Solar Tracking | B22: Solar | C22: Solar PV | G22: Not applicable: no thermal fuel input
A23: Steam | B23: Unknown | C23: Unspecified steam | G23: Cannot infer fuel from class; requires plant-level mapping

Sheet Methodology
A1: Purpose | B1: Indicative resource-level full-load heat-rate estimates, not actual unit measurements.
A2: Input | B2: PJM 2026/2027 Existing Resource List, as of 2025-10-14 (user supplied).
A3: Basis | B3: MMBtu fuel energy per MWh electric generation; representative net HHV assumptions.
A4: Limitation | B4: PJM CLASSTYPE does not identify specific turbine model, vintage, fuel or dispatch load.
A5: Ranges | B5: Illustrative engineering screening assumptions, not PJM/EIA verified plant heat rates.
A6: Nuclear | B6: Thermal equivalent only; do not use to infer market fuel cost.
A7: Solar/wind/hydro/storage | B7: No thermal fuel heat rate. Storage should be modeled with efficiency.
A8: Steam/Other | B8: Not estimated because fuel and technology are not identifiable from source class.
A9: Dual fuel | B9: Natural-gas operation assumed; alternate fuel could have different characteristics.
A10: Partial load | B10: Heat rate often rises at low loading; base estimate represents approximate full-load performance.
A11: ICAP multiplication | B11: Thermal input at ICAP is hypothetical, not an actual output or availability forecast.
A12: External methodology reference | B12: https://www.eia.gov/electricity/annual/html/epa_08_01.html
... A39: 2025 reported formula | B39: EIA-923 Page 1 monthly Elec_MMBtu / Netgen; in workbook cells R/Q and in EIA Group Data F/G.

Sheet EIA Matching Review
A1: PJM Resource | B1: PJM Class | C1: Candidate Rank | D1: EIA Plant ID | E1: EIA Plant Name | F1: State | G1: Name Fit | H1: Overall Score | I1: EIA-860 Technology Match | J1: 2025 Data Present | K1: 2025 Net MWh | L1: 2025 Fuel for Electric MMBtu | M1: 2025 Group Heat Rate | N1: Fuel / Prime Movers | O1: EIA-860 Generator IDs | P1: EIA-860 Operable MW | Q1: Decision | R1: 2025 EIA-923 Source | S1: EIA-860 Source | T1: OUTPUT
A2: UNIVERSITY PARK NORTH CT10 | B2: Gas Combustion Turbine | C2: 2 | D2: 55250 | E2: University Park South | F2: IL | G2: 0.5599 | H2: 0.6059 | I2: Yes | J2: No / invalid | K2: 151438 | L2: 1725 | M2: 0.0114 | N2: GT/NG | O2: UPG1, UPG2, UPG3, UPG4, UPG5, UPG6 | P2: 300 | Q2: Candidate only – do not treat as matched | R2: https://www.eia.gov/electricity/data/eia923/ | S2: https://www.eia.gov/electricity/data/eia860/ | T2: =P2 -> 300
A3: UNIVERSITY PARK NORTH CT11 | B3: Gas Combustion Turbine | C3: 2 | D3: 55250 | E3: University Park South | F3: IL | G3: 0.5599 | H3: 0.6059 | I3: Yes | J3: No / invalid | K3: 151438 | L3: 1725 | M3: 0.0114 | N3: GT/NG | O3: UPG1, UPG2, UPG3, UPG4, UPG5, UPG6 | P3: 300 | Q3: Candidate only – do not treat as matched | R3: https://www.eia.gov/electricity/data/eia923/ | S3: https://www.eia.gov/electricity/data/eia860/ | T3: =T2+P3 -> 600
A4: UNIVERSITY PARK NORTH CT12 | B4: Gas Combustion Turbine | C4: 2 | D4: 55250 | E4: University Park South | F4: IL | G4: 0.5599 | H4: 0.6059 | I4: Yes | J4: No / invalid | K4: 151438 | L4: 1725 | M4: 0.0114 | N4: GT/NG | O4: UPG1, UPG2, UPG3, UPG4, UPG5, UPG6 | P4: 300 | Q4: Candidate only – do not treat as matched | R4: https://www.eia.gov/electricity/data/eia923/ | S4: https://www.eia.gov/electricity/data/eia860/ | T4: =T3+P4 -> 900
A5: COCHRAN MILL | B5: Gas Combined Cycle | C5: 1 | D5: 54096 | E5: International Paper Riverdale Mill | F5: AL | G5: 0.4123 | H5: 0.3403 | I5: Yes | J5: No / invalid | K5: 324666.87 | L5: 1099323 | M5: 3.386 | N5: CA/NG, CT/NG | O5: GEN3, GEN4 | P5: 55.2 | Q5: Candidate only – do not treat as matched | R5: https://www.eia.gov/electricity/data/eia923/ | S5: https://www.eia.gov/electricity/data/eia860/ | T5: =T4+P5 -> 955.2
A6: FORD MILL 1 ST | B6: Gas Combined Cycle | C6: 1 | D6: 54096 | E6: International Paper Riverdale Mill | F6: AL | G6: 0.4077 | H6: 0.3357 | I6: Yes | J6: No / invalid | K6: 324666.87 | L6: 1099323 | M6: 3.386 | N6: CA/NG, CT/NG | O6: GEN3, GEN4 | P6: 55.2 | Q6: Candidate only – do not treat as matched | R6: https://www.eia.gov/electricity/data/eia923/ | S6: https://www.eia.gov/electricity/data/eia860/ | T6: =T5+P6 -> 1010.4
A7: FORD MILL 2 ST | B7: Gas Combined Cycle | C7: 1 | D7: 54096 | E7: International Paper Riverdale Mill | F7: AL | G7: 0.4077 | H7: 0.3357 | I7: Yes | J7: No / invalid | K7: 324666.87 | L7: 1099323 | M7: 3.386 | N7: CA/NG, CT/NG | O7: GEN3, GEN4 | P7: 55.2 | Q7: Candidate only – do not treat as matched | R7: https://www.eia.gov/electricity/data/eia923/ | S7: https://www.eia.gov/electricity/data/eia860/ | T7: =T6+P7 -> 1065.6
A8: OREGON CC | B8: Gas Combined Cycle | C8: 3 | D8: 57653 | E8: Oregon State University Energy Center | F8: OR | G8: 0.7225 | H8: 0.6225 | I8: No | J8: No / invalid | K8: 33285 | L8: 146048 | M8: 4.3878 | N8: CT/NG | P8: 0 | Q8: Candidate only – do not treat as matched | R8: https://www.eia.gov/electricity/data/eia923/ | S8: https://www.eia.gov/electricity/data/eia860/ | T8: =T7+P8 -> 1065.6
A9: WASHINGTON 1 | B9: Gas Combined Cycle | C9: 3 | D9: 7697 | E9: Washington County Cogeneration Facility | F9: AL | G9: 0.77 | H9: 0.698 | I9: Yes | J9: No / invalid | K9: 810526 | L9: 3591230 | M9: 4.4307 | N9: CA/NG, CT/NG | O9: 1, 2 | P9: 100 | Q9: Candidate only – do not treat as matched | R9: https://www.eia.gov/electricity/data/eia923/ | S9: https://www.eia.gov/electricity/data/eia860/ | T9: =T8+P9 -> 1165.6
A10: WASHINGTON 2 | B10: Gas Combined Cycle | C10: 3 | D10: 7697 | E10: Washington County Cogeneration Facility | F10: AL | G10: 0.77 | H10: 0.698 | I10: Yes | J10: No / invalid | K10: 810526 | L10: 3591230 | M10: 4.4307 | N10: CA/NG, CT/NG | O10: 1, 2 | P10: 100 | Q10: Candidate only – do not treat as matched | R10: https://www.eia.gov/electricity/data/eia923/ | S10: https://www.eia.gov/electricity/data/eia860/ | T10: =T9+P10 -> 1265.6
A11: WASHINGTON 3 | B11: Gas Combined Cycle | C11: 3 | D11: 7697 | E11: Washington County Cogeneration Facility | F11: AL | G11: 0.77 | H11: 0.698 | I11: Yes | J11: No / invalid | K11: 810526 | L11: 3591230 | M11: 4.4307 | N11: CA/NG, CT/NG | O11: 1, 2 | P11: 100 | Q11: Candidate only – do not treat as matched | R11: https://www.eia.gov/electricity/data/eia923/ | S11: https://www.eia.gov/electricity/data/eia860/ | T11: =T10+P11 -> 1365.6
A12: BRUNNER ISLAND 1 | B12: Steam | C12: 3 | D12: 50479 | E12: Georgia-Pacific Big Island | F12: VA | G12: 0.4385 | H12: 0.4845 | I12: Yes | J12: No / invalid | K12: 23305.248 | L12: 107293 | M12: 4.6038 | N12: ST/NG | O12: GEN1 | P12: 7 | Q12: Candidate only – do not treat as matched | R12: https://www.eia.gov/electricity/data/eia923/ | S12: https://www.eia.gov/electricity/data/eia860/ | T12: =T11+P12 -> 1372.6
A13: BRUNNER ISLAND 2 | B13: Steam | C13: 3 | D13: 50479 | E13: Georgia-Pacific Big Island | F13: VA | G13: 0.4385 | H13: 0.4845 | I13: Yes | J13: No / invalid | K13: 23305.248 | L13: 107293 | M13: 4.6038 | N13: ST/NG | O13: GEN1 | P13: 7 | Q13: Candidate only – do not treat as matched | R13: https://www.eia.gov/electricity/data/eia923/ | S13: https://www.eia.gov/electricity/data/eia860/ | T13: =T12+P13 -> 1379.6
A14: BRUNNER ISLAND 3 | B14: Steam | C14: 3 | D14: 50479 | E14: Georgia-Pacific Big Island | F14: VA | G14: 0.4385 | H14: 0.4845 | I14: Yes | J14: No / invalid | K14: 23305.248 | L14: 107293 | M14: 4.6038 | N14: ST/NG | O14: GEN1 | P14: 7 | Q14: Candidate only – do not treat as matched | R14: https://www.eia.gov/electricity/data/eia923/ | S14: https://www.eia.gov/electricity/data/eia860/ | T14: =T13+P14 -> 1386.6
A15: WHEELABRATOR FALLS | B15: Steam | C15: 3 | D15: 10504 | E15: Amalgamated Sugar Twin Falls | F15: ID | G15: 0.4123 | H15: 0.3403 | I15: Yes | J15: No / invalid | K15: 20649.333 | L15: 101901 | M15: 4.9348 | N15: ST/NG | O15: 1500, 2000, 2500, 4000 | P15: 10.5 | Q15: Candidate only – do not treat as matched | R15: https://www.eia.gov/electricity/data/eia923/ | S15: https://www.eia.gov/electricity/data/eia860/ | T15: =T14+P15 -> 1397.1
A16: EAST BEND 2 | B16: Coal | C16: 3 | D16: 54214 | E16: American Crystal Sugar East Grand Forks | F16: MN | G16: 0.3925 | H16: 0.3205 | I16: Yes | J16: No / invalid | K16: 42576 | L16: 242116 | M16: 5.6867 | N16: ST/SUB | O16: G1, G2 | P16: 7.5 | Q16: Candidate only – do not treat as matched | R16: https://www.eia.gov/electricity/data/eia923/ | S16: https://www.eia.gov/electricity/data/eia860/ | T16: =T15+P16 -> 1404.6
A17: KENDALL CC 1 | B17: Gas Combined Cycle | C17: 2 | D17: 1595 | E17: Kendall Square Station | F17: MA | G17: 0.835 | H17: 0.763 | I17: Yes | J17: Yes | K17: 1533755 | L17: 8963771 | M17: 5.8443 | N17: CA/DFO, CA/NG, CT/DFO, CT/NG | O17: 3, GEN4 | P17: 206 | Q17: Candidate only – do not treat as matched | R17: https://www.eia.gov/electricity/data/eia923/ | S17: https://www.eia.gov/electricity/data/eia860/ | T17: =T16+P17 -> 1610.6
A18: KENDALL CC 2 | B18: Gas Combined Cycle | C18: 2 | D18: 1595 | E18: Kendall Square Station | F18: MA | G18: 0.835 | H18: 0.763 | I18: Yes | J18: Yes | K18: 1533755 | L18: 8963771 | M18: 5.8443 | N18: CA/DFO, CA/NG, CT/DFO, CT/NG | O18: 3, GEN4 | P18: 206 | Q18: Candidate only – do not treat as matched | R18: https://www.eia.gov/electricity/data/eia923/ | S18: https://www.eia.gov/electricity/data/eia860/ | T18: =T17+P18 -> 1816.6
A19: KENDALL CC 3 | B19: Gas Combined Cycle | C19: 2 | D19: 1595 | E19: Kendall Square Station | F19: MA | G19: 0.835 | H19: 0.763 | I19: Yes | J19: Yes | K19: 1533755 | L19: 8963771 | M19: 5.8443 | N19: CA/DFO, CA/NG, CT/DFO, CT/NG | O19: 3, GEN4 | P19: 206 | Q19: Candidate only – do not treat as matched | R19: https://www.eia.gov/electricity/data/eia923/ | S19: https://www.eia.gov/electricity/data/eia860/ | T19: =T18+P19 -> 2022.6
A20: KENDALL CC 4 | B20: Gas Combined Cycle | C20: 2 | D20: 1595 | E20: Kendall Square Station | F20: MA | G20: 0.835 | H20: 0.763 | I20: Yes | J20: Yes | K20: 1533755 | L20: 8963771 | M20: 5.8443 | N20: CA/DFO, CA/NG, CT/DFO, CT/NG | O20: 3, GEN4 | P20: 206 | Q20: Candidate only – do not treat as matched | R20: https://www.eia.gov/electricity/data/eia923/ | S20: https://www.eia.gov/electricity/data/eia860/ | T20: =T19+P20 -> 2228.6
... A46: MIDDLETOWN CC | B46: Gas Combined Cycle | C46: 1 | D46: 60376 | E46: Middletown- Ohio | F46: OH | G46: 0.859 | H46: 0.905 | I46: Yes | J46: Yes | K46: 6529885.6 | L46: 43153278 | M46: 6.6086 | N46: CA/NG, CT/NG | O46: CTG1, CTG2, STG1 | P46: 856.5 | Q46: Candidate only – do not treat as matched | R46: https://www.eia.gov/electricity/data/eia923/ | S46: https://www.eia.gov/electricity/data/eia860/ | T46: =T45+P46 -> 32082.7
A47: HARRISBURG STEAM NUG | B47: Steam | C47: 1 | D47: 10118 | E47: Harrisburg Facility | F47: PA | G47: 0.665 | H47: 0.683 | I47: No | J47: Yes | K47: 5365.7 | L47: 35477 | M47: 6.6118 | N47: ST/NG | P47: 0 | Q47: Candidate only – do not treat as matched | R47: https://www.eia.gov/electricity/data/eia923/ | S47: https://www.eia.gov/electricity/data/eia860/ | T47: =T46+P47 -> 32082.7
A48: HICKORY RUN | B48: Gas Combined Cycle | C48: 1 | D48: 61028 | E48: Hickory Run Energy Station | F48: PA | G48: 1 | H48: 1 | I48: Yes | J48: Yes | K48: 6668580 | L48: 44175102 | M48: 6.6244 | N48: CA/NG, CT/NG | O48: CTG1, CTG2, STG1 | P48: 962.3 | Q48: Accepted: high plant/group proxy | R48: https://www.eia.gov/electricity/data/eia923/ | S48: https://www.eia.gov/electricity/data/eia860/ | T48: =T47+P48 -> 33045
A49: GUERNSEY COUNTY CC 1 | B49: Gas Combined Cycle | C49: 1 | D49: 62949 | E49: Guernsey Power Station | F49: OH | G49: 0.6402 | H49: 0.6862 | I49: Yes | J49: Yes | K49: 11309051 | L49: 75101830 | M49: 6.6409 | N49: CS/NG | O49: GPS1, GPS2, GPS3 | P49: 1788.5 | Q49: Accepted: medium plant/group proxy | R49: https://www.eia.gov/electricity/data/eia923/ | S49: https://www.eia.gov/electricity/data/eia860/ | T49: =T48+P49 -> 34833.5
A50: GUERNSEY COUNTY CC 2 | B50: Gas Combined Cycle | C50: 1 | D50: 62949 | E50: Guernsey Power Station | F50: OH | G50: 0.6402 | H50: 0.6862 | I50: Yes | J50: Yes | K50: 11309051 | L50: 75101830 | M50: 6.6409 | N50: CS/NG | O50: GPS1, GPS2, GPS3 | P50: 1788.5 | Q50: Accepted: medium plant/group proxy | R50: https://www.eia.gov/electricity/data/eia923/ | S50: https://www.eia.gov/electricity/data/eia860/ | T50: =T49+P50 -> 36622
A51: GUERNSEY COUNTY CC 3 | B51: Gas Combined Cycle | C51: 1 | D51: 62949 | E51: Guernsey Power Station | F51: OH | G51: 0.6402 | H51: 0.6862 | I51: Yes | J51: Yes | K51: 11309051 | L51: 75101830 | M51: 6.6409 | N51: CS/NG | O51: GPS1, GPS2, GPS3 | P51: 1788.5 | Q51: Accepted: medium plant/group proxy | R51: https://www.eia.gov/electricity/data/eia923/ | S51: https://www.eia.gov/electricity/data/eia860/ | T51: =T50+P51 -> 38410.5
A52: MOXIE PATRIOT | B52: Gas Combined Cycle | C52: 1 | D52: 58426 | E52: Hamilton Patriot Generation Plant | F52: PA | G52: 0.5341 | H52: 0.5801 | I52: Yes | J52: Yes | K52: 6102059 | L52: 40765309 | M52: 6.6806 | N52: CS/NG | O52: GEN1, GEN2 | P52: 795 | Q52: Candidate only – do not treat as matched | R52: https://www.eia.gov/electricity/data/eia923/ | S52: https://www.eia.gov/electricity/data/eia860/ | T52: =T51+P52 -> 39205.5
A53: FOUR RIVERS 5 | B53: Gas Combined Cycle | C53: 1 | D53: 63931 | E53: CPV Three Rivers Energy Center | F53: IL | G53: 0.4422 | H53: 0.4882 | I53: Yes | J53: Yes | K53: 6456046 | L53: 43371450 | M53: 6.718 | N53: CS/NG | O53: GEN1, GEN2 | P53: 1220.9 | Q53: Candidate only – do not treat as matched | R53: https://www.eia.gov/electricity/data/eia923/ | S53: https://www.eia.gov/electricity/data/eia860/ | T53: =T52+P53 -> 40426.4
A54: THREE RIVERS CC | B54: Gas Combined Cycle | C54: 1 | D54: 63931 | E54: CPV Three Rivers Energy Center | F54: IL | G54: 0.8384 | H54: 0.8844 | I54: Yes | J54: Yes | K54: 6456046 | L54: 43371450 | M54: 6.718 | N54: CS/NG | O54: GEN1, GEN2 | P54: 1220.9 | Q54: Accepted: high plant/group proxy | R54: https://www.eia.gov/electricity/data/eia923/ | S54: https://www.eia.gov/electricity/data/eia860/ | T54: =T53+P54 -> 41647.3
A55: HICKORY RUN | B55: Gas Combined Cycle | C55: 2 | D55: 1363 | E55: Cane Run | F55: KY | G55: 0.5047 | H55: 0.5507 | I55: Yes | J55: Yes | K55: 5128350 | L55: 34557757 | M55: 6.7386 | N55: CA/NG, CT/NG | O55: 7A, 7B, 7S | P55: 691 | Q55: Candidate only – do not treat as matched | R55: https://www.eia.gov/electricity/data/eia923/ | S55: https://www.eia.gov/electricity/data/eia860/ | T55: =T54+P55 -> 42338.3
A56: ST JOSEPH COUNTY CC | B56: Gas Combined Cycle | C56: 1 | D56: 57794 | E56: St Joseph Energy Center | F56: IN | G56: 0.5485 | H56: 0.5945 | I56: Yes | J56: Yes | K56: 5335234 | L56: 36167541 | M56: 6.779 | N56: CA/NG, CT/NG | O56: CT1, CT2, ST1 | P56: 715 | Q56: Candidate only – do not treat as matched | R56: https://www.eia.gov/electricity/data/eia923/ | S56: https://www.eia.gov/electricity/data/eia860/ | T56: =T55+P56 -> 43053.3
A57: DRESDEN CT 1 | B57: Gas Combined Cycle | C57: 1 | D57: 55350 | E57: Dresden Energy Facility | F57: OH | G57: 1 | H57: 1 | I57: Yes | J57: Yes | K57: 4189180 | L57: 28402131 | M57: 6.7799 | N57: CA/NG, CT/NG | O57: 1, 2, 3 | P57: 540 | Q57: Accepted: high plant/group proxy | R57: https://www.eia.gov/electricity/data/eia923/ | S57: https://www.eia.gov/electricity/data/eia860/ | T57: =T56+P57 -> 43593.3
A58: DRESDEN CT 2 | B58: Gas Combined Cycle | C58: 1 | D58: 55350 | E58: Dresden Energy Facility | F58: OH | G58: 1 | H58: 1 | I58: Yes | J58: Yes | K58: 4189180 | L58: 28402131 | M58: 6.7799 | N58: CA/NG, CT/NG | O58: 1, 2, 3 | P58: 540 | Q58: Accepted: high plant/group proxy | R58: https://www.eia.gov/electricity/data/eia923/ | S58: https://www.eia.gov/electricity/data/eia860/ | T58: =T57+P58 -> 44133.3
A59: DRESDEN ST 1 | B59: Gas Combined Cycle | C59: 1 | D59: 55350 | E59: Dresden Energy Facility | F59: OH | G59: 1 | H59: 1 | I59: Yes | J59: Yes | K59: 4189180 | L59: 28402131 | M59: 6.7799 | N59: CA/NG, CT/NG | O59: 1, 2, 3 | P59: 540 | Q59: Accepted: high plant/group proxy | R59: https://www.eia.gov/electricity/data/eia923/ | S59: https://www.eia.gov/electricity/data/eia860/ | T59: =T58+P59 -> 44673.3
... A252: NORTH LONGVIEW | B252: Coal | C252: 1 | D252: 56671 | E252: Longview Power Plant | F252: WV | G252: 0.6459 | H252: 0.6919 | I252: Yes | J252: Yes | K252: 4615575 | L252: 40460006 | M252: 8.766 | N252: ST/BIT | O252: MKA01 | P252: 710 | Q252: Accepted: medium plant/group proxy | R252: https://www.eia.gov/electricity/data/eia923/ | S252: https://www.eia.gov/electricity/data/eia860/ | T252: =T251+P252 -> 198325.6
A253: PAXTON CREEK | B253: Diesel Utility | C253: 1 | D253: 50373 | E253: Paxton Creek Cogeneration | F253: PA | G253: 0.8668 | H253: 0.8848 | I253: No | J253: Yes | K253: 1228.086 | L253: 10926 | M253: 8.8968 | N253: IC/DFO | P253: 0 | Q253: Candidate only – do not treat as matched | R253: https://www.eia.gov/electricity/data/eia923/ | S253: https://www.eia.gov/electricity/data/eia860/ | T253: =T252+P253 -> 198325.6
A254: HOPEWELL HCF | B254: Gas Combined Cycle Dual | C254: 1 | D254: 10633 | E254: Hopewell Cogeneration | F254: VA | G254: 0.5191 | H254: 0.5651 | I254: Yes | J254: Yes | K254: 1773262 | L254: 15790787 | M254: 8.9049 | N254: CA/DFO, CA/NG, CT/DFO, CT/NG | O254: GT1, GT2, GT3, ST1 | P254: 378.3 | Q254: Candidate only – do not treat as matched | R254: https://www.eia.gov/electricity/data/eia923/ | S254: https://www.eia.gov/electricity/data/eia860/ | T254: =T253+P254 -> 198703.9
A255: ERIE COUNTY LF | B255: Landfill Intermittent | C255: 3 | D255: 56280 | E255: Hardin County LFGTE | F255: KY | G255: 0.4042 | H255: 0.4502 | I255: Yes | J255: Yes | K255: 3997 | L255: 36662 | M255: 9.1724 | N255: IC/LFG | O255: 1, 2, 3 | P255: 2.4 | Q255: Candidate only – do not treat as matched | R255: https://www.eia.gov/electricity/data/eia923/ | S255: https://www.eia.gov/electricity/data/eia860/ | T255: =T254+P255 -> 198706.3
A256: JAY COUNTY LF | B256: Landfill Intermittent | C256: 3 | D256: 56280 | E256: Hardin County LFGTE | F256: KY | G256: 0.3971 | H256: 0.4431 | I256: Yes | J256: Yes | K256: 3997 | L256: 36662 | M256: 9.1724 | N256: IC/LFG | O256: 1, 2, 3 | P256: 2.4 | Q256: Candidate only – do not treat as matched | R256: https://www.eia.gov/electricity/data/eia923/ | S256: https://www.eia.gov/electricity/data/eia860/ | T256: =T255+P256 -> 198708.7
A257: CAMDEN COGEN TECH | B257: Gas Combined Cycle | C257: 1 | D257: 10751 | E257: Camden Plant Holding LLC | F257: NJ | G257: 0.4128 | H257: 0.4588 | I257: Yes | J257: Yes | K257: 97880 | L257: 899846 | M257: 9.1934 | N257: CA/NG, CT/NG | O257: GEN1, GEN2 | P257: 145 | Q257: Candidate only – do not treat as matched | R257: https://www.eia.gov/electricity/data/eia923/ | S257: https://www.eia.gov/electricity/data/eia860/ | T257: =T256+P257 -> 198853.7
A258: CROWN POINT | B258: Gas Combined Cycle | C258: 1 | D258: 50561 | E258: Eagle Point Power Generation | F258: NJ | G258: 0.5082 | H258: 0.5542 | I258: Yes | J258: Yes | K258: 204800 | L258: 1895303 | M258: 9.2544 | N258: CA/DFO, CA/NG, CT/DFO, CT/NG | O258: GTG1, GTG2, STG1, STG2 | P258: 244 | Q258: Candidate only – do not treat as matched | R258: https://www.eia.gov/electricity/data/eia923/ | S258: https://www.eia.gov/electricity/data/eia860/ | T258: =T257+P258 -> 199097.7
A259: EAGLE POINT 1 | B259: Gas Combined Cycle | C259: 1 | D259: 50561 | E259: Eagle Point Power Generation | F259: NJ | G259: 1 | H259: 1 | I259: Yes | J259: Yes | K259: 204800 | L259: 1895303 | M259: 9.2544 | N259: CA/DFO, CA/NG, CT/DFO, CT/NG | O259: GTG1, GTG2, STG1, STG2 | P259: 244 | Q259: Accepted: high plant/group proxy | R259: https://www.eia.gov/electricity/data/eia923/ | S259: https://www.eia.gov/electricity/data/eia860/ | T259: =T258+P259 -> 199341.7
A260: EAGLE POINT 2 | B260: Gas Combined Cycle | C260: 1 | D260: 50561 | E260: Eagle Point Power Generation | F260: NJ | G260: 1 | H260: 1 | I260: Yes | J260: Yes | K260: 204800 | L260: 1895303 | M260: 9.2544 | N260: CA/DFO, CA/NG, CT/DFO, CT/NG | O260: GTG1, GTG2, STG1, STG2 | P260: 244 | Q260: Accepted: high plant/group proxy | R260: https://www.eia.gov/electricity/data/eia923/ | S260: https://www.eia.gov/electricity/data/eia860/ | T260: =T259+P260 -> 199585.7
A261: EAGLE POINT 3 | B261: Gas Combined Cycle | C261: 1 | D261: 50561 | E261: Eagle Point Power Generation | F261: NJ | G261: 1 | H261: 1 | I261: Yes | J261: Yes | K261: 204800 | L261: 1895303 | M261: 9.2544 | N261: CA/DFO, CA/NG, CT/DFO, CT/NG | O261: GTG1, GTG2, STG1, STG2 | P261: 244 | Q261: Accepted: high plant/group proxy | R261: https://www.eia.gov/electricity/data/eia923/ | S261: https://www.eia.gov/electricity/data/eia860/ | T261: =T260+P261 -> 199829.7
A262: EAGLE POINT 4 | B262: Gas Combined Cycle | C262: 1 | D262: 50561 | E262: Eagle Point Power Generation | F262: NJ | G262: 1 | H262: 1 | I262: Yes | J262: Yes | K262: 204800 | L262: 1895303 | M262: 9.2544 | N262: CA/DFO, CA/NG, CT/DFO, CT/NG | O262: GTG1, GTG2, STG1, STG2 | P262: 244 | Q262: Accepted: high plant/group proxy | R262: https://www.eia.gov/electricity/data/eia923/ | S262: https://www.eia.gov/electricity/data/eia860/ | T262: =T261+P262 -> 200073.7
A263: POSSUM POINT G6S | B263: Gas Combined Cycle Dual | C263: 2 | D263: 50561 | E263: Eagle Point Power Generation | F263: NJ | G263: 0.4017 | H263: 0.4477 | I263: Yes | J263: Yes | K263: 204800 | L263: 1895303 | M263: 9.2544 | N263: CA/DFO, CA/NG, CT/DFO, CT/NG | O263: GTG1, GTG2, STG1, STG2 | P263: 244 | Q263: Candidate only – do not treat as matched | R263: https://www.eia.gov/electricity/data/eia923/ | S263: https://www.eia.gov/electricity/data/eia860/ | T263: =T262+P263 -> 200317.7
A264: WILDCAT POINT CC | B264: Gas Combined Cycle | C264: 3 | D264: 50561 | E264: Eagle Point Power Generation | F264: NJ | G264: 0.485 | H264: 0.531 | I264: Yes | J264: Yes | K264: 204800 | L264: 1895303 | M264: 9.2544 | N264: CA/DFO, CA/NG, CT/DFO, CT/NG | O264: GTG1, GTG2, STG1, STG2 | P264: 244 | Q264: Candidate only – do not treat as matched | R264: https://www.eia.gov/electricity/data/eia923/ | S264: https://www.eia.gov/electricity/data/eia860/ | T264: =T263+P264 -> 200561.7
A265: CANTON DIESEL | B265: Diesel Utility | C265: 3 | D265: 60235 | E265: Perdue Diesel Generation Facility | F265: VA | G265: 0.4931 | H265: 0.5391 | I265: Yes | J265: Yes | K265: 554 | L265: 5131 | M265: 9.2617 | N265: IC/DFO | O265: PDG5, PDG6 | P265: 4 | Q265: Candidate only – do not treat as matched | R265: https://www.eia.gov/electricity/data/eia923/ | S265: https://www.eia.gov/electricity/data/eia860/ | T265: =T264+P265 -> 200565.7
... A582: SUGAR RUN DIESEL | B582: Diesel Utility | C582: 1 | D582: 56181 | E582: Genoa Diesel Generating Station | F582: OH | G582: 0.424 | H582: 0.47 | I582: Yes | J582: Yes | K582: 239 | L582: 2719 | M582: 11.3766 | N582: IC/DFO | O582: 1, 2, 3 | P582: 6 | Q582: Candidate only – do not treat as matched | R582: https://www.eia.gov/electricity/data/eia923/ | S582: https://www.eia.gov/electricity/data/eia860/ | T582: =T581+P582 -> 402581.34
A583: EAST BEND 2 | B583: Coal | C583: 2 | D583: 645 | E583: Big Bend | F583: FL | G583: 0.5159 | H583: 0.4159 | I583: No | J583: Yes | K583: 34124.341 | L583: 390360 | M583: 11.4393 | N583: ST/BIT | P583: 0 | Q583: Candidate only – do not treat as matched | R583: https://www.eia.gov/electricity/data/eia923/ | S583: https://www.eia.gov/electricity/data/eia860/ | T583: =T582+P583 -> 402581.34
A584: SHAWVILLE 5-7 DIESEL | B584: Diesel Utility | C584: 1 | D584: 3131 | E584: Shawville | F584: PA | G584: 0.6446 | H584: 0.6906 | I584: Yes | J584: Yes | K584: 322 | L584: 3689 | M584: 11.4565 | N584: IC/DFO | O584: 5, 6, 7 | P584: 6 | Q584: Accepted: medium plant/group proxy | R584: https://www.eia.gov/electricity/data/eia923/ | S584: https://www.eia.gov/electricity/data/eia860/ | T584: =T583+P584 -> 402587.34
A585: OGDEN MARTIN | B585: Steam | C585: 2 | D585: 6146 | E585: Martin Lake | F585: TX | G585: 0.5039 | H585: 0.4319 | I585: Yes | J585: Yes | K585: 8534307 | L585: 97902810 | M585: 11.4717 | N585: ST/DFO, ST/SUB | O585: 1, 2, 3 | P585: 2455 | Q585: Candidate only – do not treat as matched | R585: https://www.eia.gov/electricity/data/eia923/ | S585: https://www.eia.gov/electricity/data/eia860/ | T585: =T584+P585 -> 405042.34
A586: FORT MARTIN 1 | B586: Coal | C586: 3 | D586: 6146 | E586: Martin Lake | F586: TX | G586: 0.5245 | H586: 0.4525 | I586: Yes | J586: Yes | K586: 8506391.8 | L586: 97584698 | M586: 11.4719 | N586: ST/SUB | O586: 1, 2, 3 | P586: 2455 | Q586: Candidate only – do not treat as matched | R586: https://www.eia.gov/electricity/data/eia923/ | S586: https://www.eia.gov/electricity/data/eia860/ | T586: =T585+P586 -> 407497.34
A587: FORT MARTIN 2 | B587: Coal | C587: 3 | D587: 6146 | E587: Martin Lake | F587: TX | G587: 0.5245 | H587: 0.4525 | I587: Yes | J587: Yes | K587: 8506391.8 | L587: 97584698 | M587: 11.4719 | N587: ST/SUB | O587: 1, 2, 3 | P587: 2455 | Q587: Candidate only – do not treat as matched | R587: https://www.eia.gov/electricity/data/eia923/ | S587: https://www.eia.gov/electricity/data/eia860/ | T587: =T586+P587 -> 409952.34
A588: NORTH LONGVIEW | B588: Coal | C588: 3 | D588: 2291 | E588: North Omaha | F588: NE | G588: 0.482 | H588: 0.41 | I588: Yes | J588: Yes | K588: 1400204.8 | L588: 16085456 | M588: 11.4879 | N588: ST/SUB | O588: 4, 5 | P588: 323.9 | Q588: Candidate only – do not treat as matched | R588: https://www.eia.gov/electricity/data/eia923/ | S588: https://www.eia.gov/electricity/data/eia860/ | T588: =T587+P588 -> 410276.24
A589: DELAWARE CITY 6 | B589: Gas Combustion Turbine | C589: 3 | D589: 55201 | E589: Gibson City Energy Center LLC | F589: IL | G589: 0.4331 | H589: 0.4791 | I589: Yes | J589: Yes | K589: 77332.001 | L589: 893501 | M589: 11.5541 | N589: GT/NG | O589: 1, 2 | P589: 232 | Q589: Candidate only – do not treat as matched | R589: https://www.eia.gov/electricity/data/eia923/ | S589: https://www.eia.gov/electricity/data/eia860/ | T589: =T588+P589 -> 410508.24
A590: DELAWARE CITY 7 | B590: Gas Combustion Turbine | C590: 3 | D590: 55201 | E590: Gibson City Energy Center LLC | F590: IL | G590: 0.4331 | H590: 0.4791 | I590: Yes | J590: Yes | K590: 77332.001 | L590: 893501 | M590: 11.5541 | N590: GT/NG | O590: 1, 2 | P590: 232 | Q590: Candidate only – do not treat as matched | R590: https://www.eia.gov/electricity/data/eia923/ | S590: https://www.eia.gov/electricity/data/eia860/ | T590: =T589+P590 -> 410740.24
A591: MONTPELIER 1 | B591: Gas Combustion Turbine Dual | C591: 1 | D591: 55229 | E591: Montpelier Electric Generating Station | F591: IN | G591: 1 | H591: 1 | I591: Yes | J591: Yes | K591: 141926 | L591: 1639993 | M591: 11.5553 | N591: GT/NG | O591: GT1, GT2, GT3, GT4 | P591: 233.1 | Q591: Accepted: high plant/group proxy | R591: https://www.eia.gov/electricity/data/eia923/ | S591: https://www.eia.gov/electricity/data/eia860/ | T591: =T590+P591 -> 410973.34
A592: MONTPELIER 2 | B592: Gas Combustion Turbine Dual | C592: 1 | D592: 55229 | E592: Montpelier Electric Generating Station | F592: IN | G592: 1 | H592: 1 | I592: Yes | J592: Yes | K592: 141926 | L592: 1639993 | M592: 11.5553 | N592: GT/NG | O592: GT1, GT2, GT3, GT4 | P592: 233.1 | Q592: Accepted: high plant/group proxy | R592: https://www.eia.gov/electricity/data/eia923/ | S592: https://www.eia.gov/electricity/data/eia860/ | T592: =T591+P592 -> 411206.44
A593: MONTPELIER 3 | B593: Gas Combustion Turbine Dual | C593: 1 | D593: 55229 | E593: Montpelier Electric Generating Station | F593: IN | G593: 1 | H593: 1 | I593: Yes | J593: Yes | K593: 141926 | L593: 1639993 | M593: 11.5553 | N593: GT/NG | O593: GT1, GT2, GT3, GT4 | P593: 233.1 | Q593: Accepted: high plant/group proxy | R593: https://www.eia.gov/electricity/data/eia923/ | S593: https://www.eia.gov/electricity/data/eia860/ | T593: =T592+P593 -> 411439.54
A594: MONTPELIER 4 | B594: Gas Combustion Turbine Dual | C594: 1 | D594: 55229 | E594: Montpelier Electric Generating Station | F594: IN | G594: 1 | H594: 1 | I594: Yes | J594: Yes | K594: 141926 | L594: 1639993 | M594: 11.5553 | N594: GT/NG | O594: GT1, GT2, GT3, GT4 | P594: 233.1 | Q594: Accepted: high plant/group proxy | R594: https://www.eia.gov/electricity/data/eia923/ | S594: https://www.eia.gov/electricity/data/eia860/ | T594: =T593+P594 -> 411672.64
A595: BIG SANDY 1 | B595: Steam | C595: 2 | D595: 6055 | E595: Big Cajun 2 | F595: LA | G595: 0.53 | H595: 0.458 | I595: Yes | J595: Yes | K595: 2627281 | L595: 30383356 | M595: 11.5646 | N595: ST/NG, ST/SUB | O595: 1, 2, 3 | P595: 1614.7 | Q595: Candidate only – do not treat as matched | R595: https://www.eia.gov/electricity/data/eia923/ | S595: https://www.eia.gov/electricity/data/eia860/ | T595: =T594+P595 -> 413287.34
... A641: BRANDON SHORES 2 | B641: Coal | C641: 1 | D641: 602 | E641: Brandon Shores | F641: MD | G641: 1 | H641: 1 | I641: Yes | J641: Yes | K641: 2293558 | L641: 27255313 | M641: 11.8834 | N641: ST/BIT | O641: 1, 2 | P641: 1273 | Q641: Accepted: high plant/group proxy | R641: https://www.eia.gov/electricity/data/eia923/ | S641: https://www.eia.gov/electricity/data/eia860/ | T641: =T640+P641 -> 435322.14
A642: PAXTON CREEK | B642: Diesel Utility | C642: 2 | D642: 7845 | E642: Lagoon Creek | F642: TN | G642: 0.545 | H642: 0.563 | I642: No | J642: Yes | K642: 31.936 | L642: 380 | M642: 11.8988 | N642: GT/DFO | P642: 0 | Q642: Candidate only – do not treat as matched | R642: https://www.eia.gov/electricity/data/eia923/ | S642: https://www.eia.gov/electricity/data/eia860/ | T642: =T641+P642 -> 435322.14
A643: COLVER NUG | B643: Coal | C643: 1 | D643: 10143 | E643: Colver Green Energy | F643: PA | G643: 0.5409 | H643: 0.5869 | I643: Yes | J643: Yes | K643: 724370.94 | L643: 8627061 | M643: 11.9097 | N643: ST/WC | O643: COLV | P643: 110 | Q643: Candidate only – do not treat as matched | R643: https://www.eia.gov/electricity/data/eia923/ | S643: https://www.eia.gov/electricity/data/eia860/ | T643: =T642+P643 -> 435432.14
A644: MAHONING LF | B644: Landfill Intermittent | C644: 1 | D644: 57411 | E644: Mahoning | F644: OH | G644: 0.6666 | H644: 0.7126 | I644: Yes | J644: Yes | K644: 27413 | L644: 327802 | M644: 11.9579 | N644: IC/LFG | O644: GEN1, GEN2, GEN3, GEN4, GEN5 | P644: 4 | Q644: Accepted: medium plant/group proxy | R644: https://www.eia.gov/electricity/data/eia923/ | S644: https://www.eia.gov/electricity/data/eia860/ | T644: =T643+P644 -> 435436.14
A645: ARDEN LF | B645: Landfill Intermittent | C645: 1 | D645: 57014 | E645: Waste Management Arden LFGTE | F645: PA | G645: 0.4375 | H645: 0.4835 | I645: Yes | J645: Yes | K645: 36439 | L645: 436339 | M645: 11.9745 | N645: IC/LFG | O645: GEN1, GEN2, GEN3, GEN4, GEN5, GEN6 | P645: 4.8 | Q645: Candidate only – do not treat as matched | R645: https://www.eia.gov/electricity/data/eia923/ | S645: https://www.eia.gov/electricity/data/eia860/ | T645: =T644+P645 -> 435440.94
A646: NEW CASTLE 3 | B646: Steam | C646: 1 | D646: 3138 | E646: New Castle Plant | F646: PA | G646: 1 | H646: 1 | I646: Yes | J646: Yes | K646: 695342 | L646: 8352664 | M646: 12.0123 | N646: ST/NG | O646: 3, 4, 5 | P646: 326.3 | Q646: Accepted: high plant/group proxy | R646: https://www.eia.gov/electricity/data/eia923/ | S646: https://www.eia.gov/electricity/data/eia860/ | T646: =T645+P646 -> 435767.24
A647: NEW CASTLE 4 | B647: Steam | C647: 1 | D647: 3138 | E647: New Castle Plant | F647: PA | G647: 1 | H647: 1 | I647: Yes | J647: Yes | K647: 695342 | L647: 8352664 | M647: 12.0123 | N647: ST/NG | O647: 3, 4, 5 | P647: 326.3 | Q647: Accepted: high plant/group proxy | R647: https://www.eia.gov/electricity/data/eia923/ | S647: https://www.eia.gov/electricity/data/eia860/ | T647: =T646+P647 -> 436093.54
A648: NEW CASTLE 5 | B648: Steam | C648: 1 | D648: 3138 | E648: New Castle Plant | F648: PA | G648: 1 | H648: 1 | I648: Yes | J648: Yes | K648: 695342 | L648: 8352664 | M648: 12.0123 | N648: ST/NG | O648: 3, 4, 5 | P648: 326.3 | Q648: Accepted: high plant/group proxy | R648: https://www.eia.gov/electricity/data/eia923/ | S648: https://www.eia.gov/electricity/data/eia860/ | T648: =T647+P648 -> 436419.84
A649: NEW CASTLE 3 | B649: Steam | C649: 2 | D649: 6156 | E649: New Haven Steam | F649: CT | G649: 0.5237 | H649: 0.4517 | I649: Yes | J649: Yes | K649: 102832 | L649: 1235378 | M649: 12.0136 | N649: ST/DFO, ST/NG, ST/RFO | O649: 1 | P649: 432.6 | Q649: Candidate only – do not treat as matched | R649: https://www.eia.gov/electricity/data/eia923/ | S649: https://www.eia.gov/electricity/data/eia860/ | T649: =T648+P649 -> 436852.44
A650: NEW CASTLE 4 | B650: Steam | C650: 2 | D650: 6156 | E650: New Haven Steam | F650: CT | G650: 0.5237 | H650: 0.4517 | I650: Yes | J650: Yes | K650: 102832 | L650: 1235378 | M650: 12.0136 | N650: ST/DFO, ST/NG, ST/RFO | O650: 1 | P650: 432.6 | Q650: Candidate only – do not treat as matched | R650: https://www.eia.gov/electricity/data/eia923/ | S650: https://www.eia.gov/electricity/data/eia860/ | T650: =T649+P650 -> 437285.04
A651: NEW CASTLE 5 | B651: Steam | C651: 2 | D651: 6156 | E651: New Haven Steam | F651: CT | G651: 0.5237 | H651: 0.4517 | I651: Yes | J651: Yes | K651: 102832 | L651: 1235378 | M651: 12.0136 | N651: ST/DFO, ST/NG, ST/RFO | O651: 1 | P651: 432.6 | Q651: Candidate only – do not treat as matched | R651: https://www.eia.gov/electricity/data/eia923/ | S651: https://www.eia.gov/electricity/data/eia860/ | T651: =T650+P651 -> 437717.64
A652: HAZELTON CT 2 | B652: Gas Combustion Turbine Dual | C652: 1 | D652: 10870 | E652: Hazelton | F652: PA | G652: 1 | H652: 1 | I652: Yes | J652: Yes | K652: 8095.998 | L652: 97273 | M652: 12.0149 | N652: GT/DFO, GT/NG | O652: GEN1, GEN2, GEN3, GEN4 | P652: 145.6 | Q652: Accepted: high plant/group proxy | R652: https://www.eia.gov/electricity/data/eia923/ | S652: https://www.eia.gov/electricity/data/eia860/ | T652: =T651+P652 -> 437863.24
A653: HAZELTON CT 3 | B653: Gas Combustion Turbine Dual | C653: 1 | D653: 10870 | E653: Hazelton | F653: PA | G653: 1 | H653: 1 | I653: Yes | J653: Yes | K653: 8095.998 | L653: 97273 | M653: 12.0149 | N653: GT/DFO, GT/NG | O653: GEN1, GEN2, GEN3, GEN4 | P653: 145.6 | Q653: Accepted: high plant/group proxy | R653: https://www.eia.gov/electricity/data/eia923/ | S653: https://www.eia.gov/electricity/data/eia860/ | T653: =T652+P653 -> 438008.84
A654: HAZELTON CT 4 | B654: Gas Combustion Turbine Dual | C654: 1 | D654: 10870 | E654: Hazelton | F654: PA | G654: 1 | H654: 1 | I654: Yes | J654: Yes | K654: 8095.998 | L654: 97273 | M654: 12.0149 | N654: GT/DFO, GT/NG | O654: GEN1, GEN2, GEN3, GEN4 | P654: 145.6 | Q654: Accepted: high plant/group proxy | R654: https://www.eia.gov/electricity/data/eia923/ | S654: https://www.eia.gov/electricity/data/eia860/ | T654: =T653+P654 -> 438154.44
... A685: CEREDO 6 | B685: Gas Combustion Turbine | C685: 1 | D685: 55276 | E685: Ceredo Generating Station | F685: WV | G685: 1 | H685: 1 | I685: Yes | J685: Yes | K685: 702143 | L685: 8546211 | M685: 12.1716 | N685: GT/NG | O685: 01, 02, 03, 04, 05, 06 | P685: 450 | Q685: Accepted: high plant/group proxy | R685: https://www.eia.gov/electricity/data/eia923/ | S685: https://www.eia.gov/electricity/data/eia860/ | T685: =T684+P685 -> 449088.64
A686: CLINCH RIVER 1 | B686: Steam | C686: 3 | D686: 594 | E686: Indian River Generating Station | F686: DE | G686: 0.53 | H686: 0.548 | I686: No | J686: Yes | K686: 254312 | L686: 3095419 | M686: 12.1717 | N686: ST/BIT, ST/DFO | P686: 0 | Q686: Candidate only – do not treat as matched | R686: https://www.eia.gov/electricity/data/eia923/ | S686: https://www.eia.gov/electricity/data/eia860/ | T686: =T685+P686 -> 449088.64
A687: CLINCH RIVER 2 | B687: Steam | C687: 3 | D687: 594 | E687: Indian River Generating Station | F687: DE | G687: 0.53 | H687: 0.548 | I687: No | J687: Yes | K687: 254312 | L687: 3095419 | M687: 12.1717 | N687: ST/BIT, ST/DFO | P687: 0 | Q687: Candidate only – do not treat as matched | R687: https://www.eia.gov/electricity/data/eia923/ | S687: https://www.eia.gov/electricity/data/eia860/ | T687: =T686+P687 -> 449088.64
A688: WEST LORAIN 2 | B688: Gas Combustion Turbine Dual | C688: 1 | D688: 2869 | E688: West Lorain | F688: OH | G688: 1 | H688: 1 | I688: Yes | J688: Yes | K688: 1305712 | L688: 15943499 | M688: 12.2106 | N688: GT/DFO, GT/NG | O688: 1A, 1B, 2, 3, 4, 5, 6 | P688: 500.5 | Q688: Accepted: high plant/group proxy | R688: https://www.eia.gov/electricity/data/eia923/ | S688: https://www.eia.gov/electricity/data/eia860/ | T688: =T687+P688 -> 449589.14
A689: WEST LORAIN 3 | B689: Gas Combustion Turbine Dual | C689: 1 | D689: 2869 | E689: West Lorain | F689: OH | G689: 1 | H689: 1 | I689: Yes | J689: Yes | K689: 1305712 | L689: 15943499 | M689: 12.2106 | N689: GT/DFO, GT/NG | O689: 1A, 1B, 2, 3, 4, 5, 6 | P689: 500.5 | Q689: Accepted: high plant/group proxy | R689: https://www.eia.gov/electricity/data/eia923/ | S689: https://www.eia.gov/electricity/data/eia860/ | T689: =T688+P689 -> 450089.64
A690: WEST LORAIN 4 | B690: Gas Combustion Turbine Dual | C690: 1 | D690: 2869 | E690: West Lorain | F690: OH | G690: 1 | H690: 1 | I690: Yes | J690: Yes | K690: 1305712 | L690: 15943499 | M690: 12.2106 | N690: GT/DFO, GT/NG | O690: 1A, 1B, 2, 3, 4, 5, 6 | P690: 500.5 | Q690: Accepted: high plant/group proxy | R690: https://www.eia.gov/electricity/data/eia923/ | S690: https://www.eia.gov/electricity/data/eia860/ | T690: =T689+P690 -> 450590.14
A691: WEST LORAIN 5 | B691: Gas Combustion Turbine Dual | C691: 1 | D691: 2869 | E691: West Lorain | F691: OH | G691: 1 | H691: 1 | I691: Yes | J691: Yes | K691: 1305712 | L691: 15943499 | M691: 12.2106 | N691: GT/DFO, GT/NG | O691: 1A, 1B, 2, 3, 4, 5, 6 | P691: 500.5 | Q691: Accepted: high plant/group proxy | R691: https://www.eia.gov/electricity/data/eia923/ | S691: https://www.eia.gov/electricity/data/eia860/ | T691: =T690+P691 -> 451090.64
A692: WEST LORAIN 6 | B692: Gas Combustion Turbine Dual | C692: 1 | D692: 2869 | E692: West Lorain | F692: OH | G692: 1 | H692: 1 | I692: Yes | J692: Yes | K692: 1305712 | L692: 15943499 | M692: 12.2106 | N692: GT/DFO, GT/NG | O692: 1A, 1B, 2, 3, 4, 5, 6 | P692: 500.5 | Q692: Accepted: high plant/group proxy | R692: https://www.eia.gov/electricity/data/eia923/ | S692: https://www.eia.gov/electricity/data/eia860/ | T692: =T691+P692 -> 451591.14
A693: GRAND CENTRAL LF | B693: Landfill Intermittent | C693: 2 | D693: 54757 | E693: Grand Blanc Generating Station | F693: MI | G693: 0.4017 | H693: 0.4477 | I693: Yes | J693: Yes | K693: 50178 | L693: 612925 | M693: 12.215 | N693: IC/LFG | O693: 4-1, 4-2, 4-3, 4-4, 4-5, 4-7, 4-8 | P693: 7.2 | Q693: Candidate only – do not treat as matched | R693: https://www.eia.gov/electricity/data/eia923/ | S693: https://www.eia.gov/electricity/data/eia860/ | T693: =T692+P693 -> 451598.34
A694: HANDSOME LAKE 1 | B694: Gas Combustion Turbine | C694: 1 | D694: 55233 | E694: Handsome Lake Energy LLC | F694: PA | G694: 1 | H694: 1 | I694: Yes | J694: Yes | K694: 163619 | L694: 2013990 | M694: 12.309 | N694: GT/NG | O694: GT01, GT02, GT03, GT04, GT05 | P694: 267.5 | Q694: Accepted: high plant/group proxy | R694: https://www.eia.gov/electricity/data/eia923/ | S694: https://www.eia.gov/electricity/data/eia860/ | T694: =T693+P694 -> 451865.84
A695: HANDSOME LAKE 2 | B695: Gas Combustion Turbine | C695: 1 | D695: 55233 | E695: Handsome Lake Energy LLC | F695: PA | G695: 1 | H695: 1 | I695: Yes | J695: Yes | K695: 163619 | L695: 2013990 | M695: 12.309 | N695: GT/NG | O695: GT01, GT02, GT03, GT04, GT05 | P695: 267.5 | Q695: Accepted: high plant/group proxy | R695: https://www.eia.gov/electricity/data/eia923/ | S695: https://www.eia.gov/electricity/data/eia860/ | T695: =T694+P695 -> 452133.34
A696: HANDSOME LAKE 3 | B696: Gas Combustion Turbine | C696: 1 | D696: 55233 | E696: Handsome Lake Energy LLC | F696: PA | G696: 1 | H696: 1 | I696: Yes | J696: Yes | K696: 163619 | L696: 2013990 | M696: 12.309 | N696: GT/NG | O696: GT01, GT02, GT03, GT04, GT05 | P696: 267.5 | Q696: Accepted: high plant/group proxy | R696: https://www.eia.gov/electricity/data/eia923/ | S696: https://www.eia.gov/electricity/data/eia860/ | T696: =T695+P696 -> 452400.84
A697: HANDSOME LAKE 4 | B697: Gas Combustion Turbine | C697: 1 | D697: 55233 | E697: Handsome Lake Energy LLC | F697: PA | G697: 1 | H697: 1 | I697: Yes | J697: Yes | K697: 163619 | L697: 2013990 | M697: 12.309 | N697: GT/NG | O697: GT01, GT02, GT03, GT04, GT05 | P697: 267.5 | Q697: Accepted: high plant/group proxy | R697: https://www.eia.gov/electricity/data/eia923/ | S697: https://www.eia.gov/electricity/data/eia860/ | T697: =T696+P697 -> 452668.34
A698: HANDSOME LAKE 5 | B698: Gas Combustion Turbine | C698: 1 | D698: 55233 | E698: Handsome Lake Energy LLC | F698: PA | G698: 1 | H698: 1 | I698: Yes | J698: Yes | K698: 163619 | L698: 2013990 | M698: 12.309 | N698: GT/NG | O698: GT01, GT02, GT03, GT04, GT05 | P698: 267.5 | Q698: Accepted: high plant/group proxy | R698: https://www.eia.gov/electricity/data/eia923/ | S698: https://www.eia.gov/electricity/data/eia860/ | T698: =T697+P698 -> 452935.84
A699: NORTHAMPTON NUG | B699: Coal | C699: 1 | D699: 50888 | E699: Northampton Generating Company LP | F699: PA | G699: 0.5466 | H699: 0.5926 | I699: Yes | J699: Yes | K699: 555258.16 | L699: 6841393 | M699: 12.3211 | N699: ST/WC | O699: GEN1 | P699: 112 | Q699: Candidate only – do not treat as matched | R699: https://www.eia.gov/electricity/data/eia923/ | S699: https://www.eia.gov/electricity/data/eia860/ | T699: =T698+P699 -> 453047.84
... A890: CHALK POINT CT 6 | B890: Gas Combustion Turbine Dual | C890: 2 | D890: 61890 | E890: NRG Chalk Point CT | F890: MD | G890: 0.9023 | H890: 0.9483 | I890: Yes | J890: Yes | K890: 7131.753 | L890: 106305 | M890: 14.9059 | N890: GT/DFO | O890: SGT1 | P890: 80.2 | Q890: Candidate only – do not treat as matched | R890: https://www.eia.gov/electricity/data/eia923/ | S890: https://www.eia.gov/electricity/data/eia860/ | T890: =T889+P890 -> 501898.76
A891: WHEELABRATOR FALLS | B891: Steam | C891: 2 | D891: 550 | E891: Kettle Falls Generating Station | F891: WA | G891: 0.506 | H891: 0.406 | I891: No | J891: Yes | K891: 230.242 | L891: 3435 | M891: 14.9191 | N891: ST/NG | P891: 0 | Q891: Candidate only – do not treat as matched | R891: https://www.eia.gov/electricity/data/eia923/ | S891: https://www.eia.gov/electricity/data/eia860/ | T891: =T890+P891 -> 501898.76
A892: GRANT TOWN 1 | B892: Coal | C892: 1 | D892: 10151 | E892: Grant Town Power Plant | F892: WV | G892: 1 | H892: 1 | I892: Yes | J892: Yes | K892: 331538.27 | L892: 4981577 | M892: 15.0256 | N892: ST/WC | O892: GEN1 | P892: 80 | Q892: Accepted: high plant/group proxy | R892: https://www.eia.gov/electricity/data/eia923/ | S892: https://www.eia.gov/electricity/data/eia860/ | T892: =T891+P892 -> 501978.76
A893: YANKEE 1 | B893: Gas Combustion Turbine Dual | C893: 1 | D893: 2854 | E893: Yankee Street | F893: OH | G893: 0.8287 | H893: 0.8747 | I893: Yes | J893: Yes | K893: 27992 | L893: 420924 | M893: 15.0373 | N893: GT/DFO, GT/NG | O893: 1, 2, 3, 4, 5, 6, 7 | P893: 126.7 | Q893: Accepted: high plant/group proxy | R893: https://www.eia.gov/electricity/data/eia923/ | S893: https://www.eia.gov/electricity/data/eia860/ | T893: =T892+P893 -> 502105.46
A894: YANKEE 2 | B894: Gas Combustion Turbine Dual | C894: 1 | D894: 2854 | E894: Yankee Street | F894: OH | G894: 0.8287 | H894: 0.8747 | I894: Yes | J894: Yes | K894: 27992 | L894: 420924 | M894: 15.0373 | N894: GT/DFO, GT/NG | O894: 1, 2, 3, 4, 5, 6, 7 | P894: 126.7 | Q894: Accepted: high plant/group proxy | R894: https://www.eia.gov/electricity/data/eia923/ | S894: https://www.eia.gov/electricity/data/eia860/ | T894: =T893+P894 -> 502232.16
A895: YANKEE 3 | B895: Gas Combustion Turbine Dual | C895: 1 | D895: 2854 | E895: Yankee Street | F895: OH | G895: 0.8287 | H895: 0.8747 | I895: Yes | J895: Yes | K895: 27992 | L895: 420924 | M895: 15.0373 | N895: GT/DFO, GT/NG | O895: 1, 2, 3, 4, 5, 6, 7 | P895: 126.7 | Q895: Accepted: high plant/group proxy | R895: https://www.eia.gov/electricity/data/eia923/ | S895: https://www.eia.gov/electricity/data/eia860/ | T895: =T894+P895 -> 502358.86
A896: YANKEE 4 | B896: Gas Combustion Turbine Dual | C896: 1 | D896: 2854 | E896: Yankee Street | F896: OH | G896: 0.8287 | H896: 0.8747 | I896: Yes | J896: Yes | K896: 27992 | L896: 420924 | M896: 15.0373 | N896: GT/DFO, GT/NG | O896: 1, 2, 3, 4, 5, 6, 7 | P896: 126.7 | Q896: Accepted: high plant/group proxy | R896: https://www.eia.gov/electricity/data/eia923/ | S896: https://www.eia.gov/electricity/data/eia860/ | T896: =T895+P896 -> 502485.56
A897: YANKEE 5 | B897: Gas Combustion Turbine Dual | C897: 1 | D897: 2854 | E897: Yankee Street | F897: OH | G897: 0.8287 | H897: 0.8747 | I897: Yes | J897: Yes | K897: 27992 | L897: 420924 | M897: 15.0373 | N897: GT/DFO, GT/NG | O897: 1, 2, 3, 4, 5, 6, 7 | P897: 126.7 | Q897: Accepted: high plant/group proxy | R897: https://www.eia.gov/electricity/data/eia923/ | S897: https://www.eia.gov/electricity/data/eia860/ | T897: =T896+P897 -> 502612.26
A898: YANKEE 6 | B898: Gas Combustion Turbine Dual | C898: 1 | D898: 2854 | E898: Yankee Street | F898: OH | G898: 0.8287 | H898: 0.8747 | I898: Yes | J898: Yes | K898: 27992 | L898: 420924 | M898: 15.0373 | N898: GT/DFO, GT/NG | O898: 1, 2, 3, 4, 5, 6, 7 | P898: 126.7 | Q898: Accepted: high plant/group proxy | R898: https://www.eia.gov/electricity/data/eia923/ | S898: https://www.eia.gov/electricity/data/eia860/ | T898: =T897+P898 -> 502738.96
...

Sheet 2025 EIA Group Data
A1: EIA Plant ID | B1: EIA Plant Name | C1: State | D1: Prime Mover | E1: Fuel | F1: 2025 Electric Fuel (MMBtu) | G1: 2025 Net Generation (MWh) | H1: Reported Group HR (MMBtu/MWh) | I1: Reported Records | J1: Data Source
A2: 3954 | B2: Mt Storm | C2: WV | D2: ST | E2: WO | F2: 318 | G2: 31.856 | H2: =IF(AND(F2>0,G2>0),F2/G2,"") -> 9.9824209 | I2: 1 | J2: https://www.eia.gov/electricity/data/eia923/
A3: 50888 | B3: Northampton Generating Company LP | C3: PA | D3: ST | E3: WO | F3: 77423 | G3: 5958.602 | H3: =IF(AND(F3>0,G3>0),F3/G3,"") -> 12.993484 | I3: 1 | J3: https://www.eia.gov/electricity/data/eia923/
A4: 57767 | B4: Brown County Wind Turbine | C4: IL | D4: WT | E4: WND | F4: 6 | G4: 2 | H4: =IF(AND(F4>0,G4>0),F4/G4,"") -> 3 | I4: 1 | J4: https://www.eia.gov/electricity/data/eia923/
A5: 57613 | B5: LE Wind Turbine 1 | C5: OH | D5: WT | E5: WND | F5: 6281 | G5: 1841 | H5: =IF(AND(F5>0,G5>0),F5/G5,"") -> 3.4117328 | I5: 1 | J5: https://www.eia.gov/electricity/data/eia923/
A6: 57176 | B6: University of Delaware Wind Turbine | C6: DE | D6: WT | E6: WND | F6: 16895 | G6: 4952 | H6: =IF(AND(F6>0,G6>0),F6/G6,"") -> 3.4117528 | I6: 1 | J6: https://www.eia.gov/electricity/data/eia923/
A7: 56376 | B7: Pike County Wind Power | C7: IL | D7: WT | E7: WND | F7: 1044 | G7: 306 | H7: =IF(AND(F7>0,G7>0),F7/G7,"") -> 3.4117647 | I7: 1 | J7: https://www.eia.gov/electricity/data/eia923/
A8: 58887 | B8: Com Adam 1WF-1 | C8: IL | D8: WT | E8: WND | F8: 16128 | G8: 4727 | H8: =IF(AND(F8>0,G8>0),F8/G8,"") -> 3.4118891 | I8: 1 | J8: https://www.eia.gov/electricity/data/eia923/
A9: 56226 | B9: Bowling Green Wind | C9: OH | D9: WT | E9: WND | F9: 2692 | G9: 789 | H9: =IF(AND(F9>0,G9>0),F9/G9,"") -> 3.4119138 | I9: 1 | J9: https://www.eia.gov/electricity/data/eia923/
A10: 55803 | B10: Somerset Windpower LLC | C10: PA | D10: WT | E10: WND | F10: 18967 | G10: 5559 | H10: =IF(AND(F10>0,G10>0),F10/G10,"") -> 3.4119446 | I10: 1 | J10: https://www.eia.gov/electricity/data/eia923/
A11: 55805 | B11: Mill Run Windpower LLC | C11: PA | D11: WT | E11: WND | F11: 64404 | G11: 18876 | H11: =IF(AND(F11>0,G11>0),F11/G11,"") -> 3.4119517 | I11: 1 | J11: https://www.eia.gov/electricity/data/eia923/
A12: 57182 | B12: PPL Frey Farm Landfill Wind | C12: PA | D12: WT | E12: WND | F12: 3197 | G12: 937 | H12: =IF(AND(F12>0,G12>0),F12/G12,"") -> 3.411953 | I12: 1 | J12: https://www.eia.gov/electricity/data/eia923/
A13: 57853 | B13: McKinley Wind Park | C13: MI | D13: WT | E13: WND | F13: 176579 | G13: 51753 | H13: =IF(AND(F13>0,G13>0),F13/G13,"") -> 3.4119568 | I13: 1 | J13: https://www.eia.gov/electricity/data/eia923/
... A4026: 62873 | B4026: Carolina Poultry Power Farmville | C4026: NC | D4026: ST | E4026: AB | F4026: 67171 | G4026: 3288 | H4026: =IF(AND(F4026>0,G4026>0),F4026/G4026,"") -> 20.429136 | I4026: 1 | J4026: https://www.eia.gov/electricity/data/eia923/
